Workbook

Sheet Resumen
A1: CENSO SNACKS MB — HORMIGA NEGRA
A2: Resumen ejecutivo del análisis (base = 2.883 PDV activos en la categoría)
A4: PARÁMETROS Y SUPUESTOS
A5: Umbral Potencial Alto (Pareto, corte ~70% del volumen) | B5: 40 | D5: Def.: PDV ordenados por Potencial Pdv desc. El corte que acumula el 70% del volumen total cae en 40 unidades/semana (730 PDV, 25,3% de la base, concentran 72,9% del volumen).
A6: Tolerancia sobre/sub-exhibición (puntos porcentuales) | B6: 0.05 | D6: Diferencia mínima entre % de frentes y % de share de volumen para considerar sobre/sub-exhibido.
A7: PTR Lays (precio de compra del PDV, fijo) | B7: 2500 | D7: Dato provisto por Fabian: precio de compra único para todos los PDV (a diferencia de Quento/Julicroc, que varía por PDV).
A8: Umbral mínimo de diferencia de markup para activar el plan de baja | B8: 0.04 | D8: Solo se marca oportunidad si Markup Lays supera al de la competencia por más de este umbral (ej: 44% vs 40% = 4pp, no alcanza).
A9: DISTRIBUCIÓN FÍSICA
A10: Total PDV analizados (base final) | B10: =COUNTA('Base PDV'!$A$2:$A$2884) -> 2883
A11: Vende Lays | B11: =COUNTIF('Base PDV'!$P$2:$P$2884,"Sí") -> 2795
A12: % sobre el total | B12: =B11/B10 -> 0.96947624
A13: Vende Competencia (Quento y/o Julicroc) | B13: =COUNTIF('Base PDV'!$Q$2:$Q$2884,"Sí") -> 1415
A14: % sobre el total | B14: =B13/B10 -> 0.49080819
A15: de los cuales, vende Quento | B15: =COUNTIF('Base PDV'!$N$2:$N$2884,"Sí") -> 1415
A16: de los cuales, vende Julicroc | B16: =COUNTIF('Base PDV'!$O$2:$O$2884,"Sí") -> 909
A17: Conviven (Lays + Competencia) | B17: =COUNTIFS('Base PDV'!$P$2:$P$2884,"Sí",'Base PDV'!$Q$2:$Q$2884,"Sí") -> 1327
A18: Solo Lays (sin competencia) | B18: =COUNTIFS('Base PDV'!$P$2:$P$2884,"Sí",'Base PDV'!$Q$2:$Q$2884,"No") -> 1468
A19: Solo Competencia (sin Lays) | B19: =COUNTIFS('Base PDV'!$P$2:$P$2884,"No",'Base PDV'!$Q$2:$Q$2884,"Sí") -> 88
A21: POTENCIAL DE MERCADO Y PARETO
A22: Potencial total de mercado (unid./semana) | B22: =SUM('Base PDV'!$M$2:$M$2884) -> 72577.7
A23: PDV de Alto Potencial (Pareto) | B23: =COUNTIF('Base PDV'!$AP$2:$AP$2884,"Alto") -> 730
A24: % de PDV | B24: =B23/B10 -> 0.25320846
A25: % del volumen que concentran | B25: =SUMIF('Base PDV'!$AP$2:$AP$2884,"Alto",'Base PDV'!$M$2:$M$2884)/B22 -> 0.7294596
A27: SHARE (NOSOTROS = LAYS)
A28: Share Total (Lays / Potencial, todos los PDV) | B28: =SUM('Base PDV'!$K$2:$K$2884)/SUM('Base PDV'!$M$2:$M$2884) -> 0.38873786
A29: Corte Alto Share en Competencia (definido por Fabian) | B29: 0.5 | D29: Corte de negocio a 50% de SOM (en vez del promedio observado, ver referencia debajo) — más simple de comunicar al equipo comercial.
A30: Share real promedio en Competencia (referencia, dato observado) | B30: =SUMIF('Base PDV'!$Q$2:$Q$2884,"Sí",'Base PDV'!$K$2:$K$2884)/SUMIF('Base PDV'!$Q$2:$Q$2884,"Sí",'Base PDV'!$M$2:$M$2884) -> 0.36099788
A31: CUADRANTES — Potencial x Share Total (todos los PDV)
A32: Cuadrante | B32: PDV | C32: % PDV | D32: Volumen (Potencial) | E32: % Volumen
A33: Alto Potencial / Alto Share | B33: =COUNTIF('Base PDV'!$AR$2:$AR$2884,A33) -> 347 | C33: =B33/$B$10 -> 0.12036074 | D33: =SUMIF('Base PDV'!$AR$2:$AR$2884,A33,'Base PDV'!$M$2:$M$2884) -> 27551.5 | E33: =D33/$B$22 -> 0.37961385
A34: Alto Potencial / Bajo Share | B34: =COUNTIF('Base PDV'!$AR$2:$AR$2884,A34) -> 383 | C34: =B34/$B$10 -> 0.13284773 | D34: =SUMIF('Base PDV'!$AR$2:$AR$2884,A34,'Base PDV'!$M$2:$M$2884) -> 25391 | E34: =D34/$B$22 -> 0.34984575
A35: Bajo Potencial / Alto Share | B35: =COUNTIF('Base PDV'!$AR$2:$AR$2884,A35) -> 1606 | C35: =B35/$B$10 -> 0.55705862 | D35: =SUMIF('Base PDV'!$AR$2:$AR$2884,A35,'Base PDV'!$M$2:$M$2884) -> 6604.2 | E35: =D35/$B$22 -> 0.090994892
A36: Bajo Potencial / Bajo Share | B36: =COUNTIF('Base PDV'!$AR$2:$AR$2884,A36) -> 547 | C36: =B36/$B$10 -> 0.18973292 | D36: =SUMIF('Base PDV'!$AR$2:$AR$2884,A36,'Base PDV'!$M$2:$M$2884) -> 13031 | E36: =D36/$B$22 -> 0.17954551
A38: CUADRANTES — Potencial x Share en Competencia (solo PDV donde vende la competencia)
A39: Cuadrante | B39: PDV | C39: % PDV | D39: Volumen (Potencial) | E39: % Volumen
A40: Alto Potencial / Alto Share | B40: =COUNTIF('Base PDV'!$AT$2:$AT$2884,A40) -> 186 | C40: =B40/COUNTIF('Base PDV'!$Q$2:$Q$2884,"Sí") -> 0.13144876 | D40: =SUMIF('Base PDV'!$AT$2:$AT$2884,A40,'Base PDV'!$M$2:$M$2884) -> 15236 | E40: =D40/SUMIF('Base PDV'!$Q$2:$Q$2884,"Sí",'Base PDV'!$M$2:$M$2884) -> 0.21945353
A41: Alto Potencial / Bajo Share | B41: =COUNTIF('Base PDV'!$AT$2:$AT$2884,A41) -> 540 | C41: =B41/COUNTIF('Base PDV'!$Q$2:$Q$2884,"Sí") -> 0.38162544 | D41: =SUMIF('Base PDV'!$AT$2:$AT$2884,A41,'Base PDV'!$M$2:$M$2884) -> 37427 | E41: =D41/SUMIF('Base PDV'!$Q$2:$Q$2884,"Sí",'Base PDV'!$M$2:$M$2884) -> 0.53908422
A42: Bajo Potencial / Alto Share | B42: =COUNTIF('Base PDV'!$AT$2:$AT$2884,A42) -> 60 | C42: =B42/COUNTIF('Base PDV'!$Q$2:$Q$2884,"Sí") -> 0.042402827 | D42: =SUMIF('Base PDV'!$AT$2:$AT$2884,A42,'Base PDV'!$M$2:$M$2884) -> 1486 | E42: =D42/SUMIF('Base PDV'!$Q$2:$Q$2884,"Sí",'Base PDV'!$M$2:$M$2884) -> 0.021403777
A43: Bajo Potencial / Bajo Share | B43: =COUNTIF('Base PDV'!$AT$2:$AT$2884,A43) -> 629 | C43: =B43/COUNTIF('Base PDV'!$Q$2:$Q$2884,"Sí") -> 0.44452297 | D43: =SUMIF('Base PDV'!$AT$2:$AT$2884,A43,'Base PDV'!$M$2:$M$2884) -> 15278 | E43: =D43/SUMIF('Base PDV'!$Q$2:$Q$2884,"Sí",'Base PDV'!$M$2:$M$2884) -> 0.22005848
A45: PRECIOS Y MARKUP
A46: PTC promedio Lays | B46: =AVERAGEIF('Base PDV'!$P$2:$P$2884,"Sí",'Base PDV'!$V$2:$V$2884) -> 3550.8068
A47: PTC promedio Quento | B47: =AVERAGEIF('Base PDV'!$N$2:$N$2884,"Sí",'Base PDV'!$S$2:$S$2884) -> 2641.7011
A48: PTC promedio Julicroc | B48: =AVERAGEIF('Base PDV'!$O$2:$O$2884,"Sí",'Base PDV'!$U$2:$U$2884) -> 1987.813 | C48: PDV en moda | D48: % de la marca
A49: Precio moda (el que más se repite) — Lays | B49: =MODE('Base PDV'!$V$2:$V$2884) -> 3500 | C49: =COUNTIF('Base PDV'!$V$2:$V$2884,B49) -> 756 | D49: =C49/COUNTIF('Base PDV'!$P$2:$P$2884,"Sí") -> 0.27048301
A50: Precio moda — Quento | B50: =MODE('Base PDV'!$S$2:$S$2884) -> 2500 | C50: =COUNTIF('Base PDV'!$S$2:$S$2884,B50) -> 692 | D50: =C50/COUNTIF('Base PDV'!$N$2:$N$2884,"Sí") -> 0.48904594
A51: Precio moda — Julicroc | B51: =MODE('Base PDV'!$U$2:$U$2884) -> 2000 | C51: =COUNTIF('Base PDV'!$U$2:$U$2884,B51) -> 309 | D51: =C51/COUNTIF('Base PDV'!$O$2:$O$2884,"Sí") -> 0.33993399
A52: Brecha promedio Lays vs Quento ($ y %) | B52: =AVERAGE('Base PDV'!$Z$2:$Z$2884) -> 902.37821
B53: =AVERAGE('Base PDV'!$AA$2:$AA$2884) -> 0.34961012
A54: Brecha promedio Lays vs Julicroc ($ y %) | B54: =AVERAGE('Base PDV'!$AB$2:$AB$2884) -> 1574.5334
B55: =AVERAGE('Base PDV'!$AC$2:$AC$2884) -> 0.80896844
A56: Markup promedio Quento (PTC-PTR)/PTR, por PDV | B56: =AVERAGE('Base PDV'!$W$2:$W$2884) -> 0.47973686
A57: Markup promedio Julicroc (PTC-PTR)/PTR, por PDV | B57: =AVERAGE('Base PDV'!$X$2:$X$2884) -> 0.61920478
A58: Markup promedio Lays (PTC de cada PDV vs PTR fijo $2.500) | B58: =AVERAGE('Base PDV'!$Y$2:$Y$2884) -> 0.42032272
A59: Markup Lays con Precio Moda (moda PTC vs PTR $2.500) | B59: =(B49-B7)/B7 -> 0.4 | D59: Markup 'típico': usa el precio más frecuente en vez del promedio, menos sensible a outliers.
A61: PDV en precio moda — Lays | B61: =COUNTIF('Base PDV'!$V$2:$V$2884,B49)&" ("&TEXT(COUNTIF('Base PDV'!$V$2:$V$2884,B49)/B11,"0.0%")&" de los que venden Lays)" -> 756 (27.0% de los que venden Lays)
A62: PDV en precio moda — Quento | B62: =COUNTIF('Base PDV'!$S$2:$S$2884,B50)&" ("&TEXT(COUNTIF('Base PDV'!$S$2:$S$2884,B50)/B15,"0.0%")&" de los que venden Quento)" -> 692 (48.9% de los que venden Quento)
A63: PDV en precio moda — Julicroc | B63: =COUNTIF('Base PDV'!$U$2:$U$2884,B51)&" ("&TEXT(COUNTIF('Base PDV'!$U$2:$U$2884,B51)/B16,"0.0%")&" de los que venden Julicroc)" -> 309 (34.0% de los que venden Julicroc)
A64: EXHIBICIÓN (solo PDV donde vende Quento — único universo con formulario completo)
A65: PDV con formulario de exhibición completo | B65: =COUNTIF('Base PDV'!$N$2:$N$2884,"Sí") -> 1415
A66: Frentes Share Lays promedio | B66: =AVERAGE('Base PDV'!$AH$2:$AH$2884) -> 0.35266016
A67: Share de volumen promedio (mismo universo) | B67: =AVERAGEIF('Base PDV'!$N$2:$N$2884,"Sí",'Base PDV'!$AO$2:$AO$2884) -> 0.31954254
A68: Sobre-exhibidos | B68: =COUNTIF('Base PDV'!$AU$2:$AU$2884,"Sobre-exhibido") -> 631
A69: En línea | B69: =COUNTIF('Base PDV'!$AU$2:$AU$2884,"En línea") -> 581
A70: Sub-exhibidos | B70: =COUNTIF('Base PDV'!$AU$2:$AU$2884,"Sub-exhibido") -> 205
A71: Plan Colocar Exhibidor (competencia tiene, nosotros no) | B71: =COUNTIF('Base PDV'!$BC$2:$BC$2884,"Sí") -> 95
A73: CLUSTERS FINALES DE ACCIÓN (Share en Competencia, corte 50% SOM)
A74: Cluster | B74: PDV | C74: % PDV | D74: Volumen (Potencial) | E74: % Volumen
A75: 1 - Foco Conquista (Alto Pot / Bajo Share) | B75: =COUNTIF('Base PDV'!$AW$2:$AW$2884,A75) -> 540 | C75: =B75/COUNTIF('Base PDV'!$Q$2:$Q$2884,"Sí") -> 0.38162544 | D75: =SUMIF('Base PDV'!$AW$2:$AW$2884,A75,'Base PDV'!$M$2:$M$2884) -> 37427 | E75: =D75/SUMIF('Base PDV'!$Q$2:$Q$2884,"Sí",'Base PDV'!$M$2:$M$2884) -> 0.53908422
A76: 2 - Foco Defensa (Alto Pot / Alto Share) | B76: =COUNTIF('Base PDV'!$AW$2:$AW$2884,A76) -> 186 | C76: =B76/COUNTIF('Base PDV'!$Q$2:$Q$2884,"Sí") -> 0.13144876 | D76: =SUMIF('Base PDV'!$AW$2:$AW$2884,A76,'Base PDV'!$M$2:$M$2884) -> 15236 | E76: =D76/SUMIF('Base PDV'!$Q$2:$Q$2884,"Sí",'Base PDV'!$M$2:$M$2884) -> 0.21945353
A77: 3 - Monitoreo (Bajo Pot / Alto Share) | B77: =COUNTIF('Base PDV'!$AW$2:$AW$2884,A77) -> 60 | C77: =B77/COUNTIF('Base PDV'!$Q$2:$Q$2884,"Sí") -> 0.042402827 | D77: =SUMIF('Base PDV'!$AW$2:$AW$2884,A77,'Base PDV'!$M$2:$M$2884) -> 1486 | E77: =D77/SUMIF('Base PDV'!$Q$2:$Q$2884,"Sí",'Base PDV'!$M$2:$M$2884) -> 0.021403777
A78: 4 - Baja Prioridad (Bajo Pot / Bajo Share) | B78: =COUNTIF('Base PDV'!$AW$2:$AW$2884,A78) -> 629 | C78: =B78/COUNTIF('Base PDV'!$Q$2:$Q$2884,"Sí") -> 0.44452297 | D78: =SUMIF('Base PDV'!$AW$2:$AW$2884,A78,'Base PDV'!$M$2:$M$2884) -> 15278 | E78: =D78/SUMIF('Base PDV'!$Q$2:$Q$2884,"Sí",'Base PDV'!$M$2:$M$2884) -> 0.22005848
A80: OPORTUNIDADES TRANSVERSALES (aplican sin importar el cluster)
A81: Plan Colocar Exhibidor (competencia tiene, nosotros no) | B81: =COUNTIF('Base PDV'!$BC$2:$BC$2884,"Sí") -> 95
A82: Oportunidad de bajar markup Lays (diferencia > umbral, ver Parámetros) | B82: =SUMPRODUCT(--('Base PDV'!$AY$2:$AY$2884<>"")) -> 207
A83: Gap de markup promedio en esos PDV | B83: =AVERAGE('Base PDV'!$AX$2:$AX$2884) -> 0.13390725
A84: Plan Aumentar Frentes (gap ≥15%, o >5pp si el PDV está en Plan 9+1 — ver Parámetros) | B84: =COUNTIF('Base PDV'!$BB$2:$BB$2884,"Sí") -> 87
A85: % sobre PDV con dato de frentes | B85: =B84/SUMPRODUCT(--('Base PDV'!$AU$2:$AU$2884<>"Sin dato")) -> 0.061397318
A87: COBERTURA TOTAL DE LA BASE (reconciliación con el universo inicial del censo)
A88: Concepto | B88: PDV | C88: % Base Inicial | D88: % Censados
A89: Total PDV en la base inicial del censo | B89: 4028 | D89: Fuente: Censo_para_Analisis_HN_27-8, hoja Base hn
A90: No censados | B90: 321 | C90: =B90/$B$89 -> 0.079692155
A91: Censados | B91: =B89-B90 -> 3707 | C91: =B91/$B$89 -> 0.92030785 | D91: =B91/$B$91 -> 1
A92: No trabajan el calibre (ni Lays ni competencia, sin compra en 4 meses) | B92: 824 | C92: =B92/$B$89 -> 0.20456802 | D92: =B92/$B$91 -> 0.22228217
A93: Base final de análisis | B93: =B10 -> 2883 | C93: =B93/$B$89 -> 0.71573982 | D93: =B93/$B$91 -> 0.77771783
A95: PLAN PEHUAMAR (cruce por Código)
A96: Total de códigos en la lista Pehuamar | B96: 166 | D96: Fuente: Versión_final_4-9.xlsx
A97: Encontrados en la base final de análisis | B97: =COUNTIF('Base PDV'!$AZ$2:$AZ$2884,"Sí") -> 153
A98: % de la lista Pehuamar | B98: =B97/B96 -> 0.92168675
A99: No encontrados (ver hoja 'Plan Pehuamar - No Encontrados') | B99: 13 | D99: 5 no existen en el censo · 8 existen pero no están en la base final (no censados)
A101: Cluster de los PDV Pehuamar encontrados
A102: Cluster | B102: PDV Pehuamar | C102: % del total Pehuamar encontrado
A103: 1 - Foco Conquista (Alto Pot / Bajo Share) | B103: =SUMPRODUCT(('Base PDV'!$AZ$2:$AZ$2884="Sí")*('Base PDV'!$AW$2:$AW$2884=A103)) -> 87 | C103: =B103/$B$97 -> 0.56862745
A104: 2 - Foco Defensa (Alto Pot / Alto Share) | B104: =SUMPRODUCT(('Base PDV'!$AZ$2:$AZ$2884="Sí")*('Base PDV'!$AW$2:$AW$2884=A104)) -> 12 | C104: =B104/$B$97 -> 0.078431373
A105: 3 - Monitoreo (Bajo Pot / Alto Share) | B105: =SUMPRODUCT(('Base PDV'!$AZ$2:$AZ$2884="Sí")*('Base PDV'!$AW$2:$AW$2884=A105)) -> 0 | C105: =B105/$B$97 -> 0
A106: 4 - Baja Prioridad (Bajo Pot / Bajo Share) | B106: =SUMPRODUCT(('Base PDV'!$AZ$2:$AZ$2884="Sí")*('Base PDV'!$AW$2:$AW$2884=A106)) -> 37 | C106: =B106/$B$97 -> 0.24183007
A107: Sin competencia directa | B107: =SUMPRODUCT(('Base PDV'!$AZ$2:$AZ$2884="Sí")*('Base PDV'!$AW$2:$AW$2884=A107)) -> 17 | C107: =B107/$B$97 -> 0.11111111
A109: PLAN COMBO 9+1 — CAPTURA DE VOLUMEN QUENTO
A110: Presupuesto: paquetes Lays bonificados / mes | B110: 2000 | D110: Mecánica 9+1 (10% de bonificación): cada paquete gratis habilita 10 unidades de venta.
A111: Capacidad total de unidades transadas / mes (2.000 × 10) | B111: =B110*10 -> 20000
A112: Crecimiento objetivo por PDV (mín. – máx.) | B112: 10% – 15% | D112: Se bonifica el volumen TOTAL del PDV (no solo el incremental), para sostener la baja de PTC todo el mes.
...

Sheet Base PDV
A1: Código | B1: Vendedor | C1: Zona | D1: Día | E1: Razón social | F1: Subcanal | G1: Territorio | H1: Sdv | I1: Vol. Quento | J1: Vol. Julicroc | K1: Vol. Lays | L1: Total Competencia | M1: Potencial Pdv | N1: Vende Quento (Sí/No) | O1: Vende Julicroc (Sí/No) | P1: Vende Lays (Sí/No) | Q1: Vende Competencia (Sí/No) | R1: PTR Quento | S1: PTC Quento | T1: PTR Julicroc | U1: PTC Julicroc | V1: PTC Lays | W1: Markup Quento | X1: Markup Julicroc | Y1: Markup Lays | Z1: Gap PTC Lays vs Quento | AA1: Gap % Lays vs Quento | AB1: Gap PTC Lays vs Julicroc | AC1: Gap % Lays vs Julicroc | AD1: Frentes Lays | AE1: Frentes Quento | AF1: Frentes Julicroc | AG1: Frentes Totales | AH1: Frentes Share Lays | AI1: Exhibidores PepsiCo (Lays) | AJ1: Exhibidores Quento | AK1: Exhibidores Julicroc | AL1: Tiene Exhibidor Competencia | AM1: Condición de pago Quento | AN1: Condición de pago Julicroc | AO1: Share Total (Lays/Potencial) | AP1: Alto Potencial (Pareto 70%) | AQ1: Alto Share Total | AR1: Cuadrante (Share Total) | AS1: Alto Share en Competencia | AT1: Cuadrante (Share en Competencia) | AU1: Estado Exhibición | AV1: Prioridad Cluster | AW1: Cluster Final | AX1: Gap Markup (Lays vs competencia) | AY1: Oportunidad Bajar Markup Lays | AZ1: Plan Pehuamar | BA1: Plan Combo 9+1 | BB1: Plan Aumentar Frentes | BC1: Plan Colocar Exhibidor | BD1: Plan 9+1 (con Pehuamar)
A2: 400747 | B2: 1 | C2: 101 | D2: Lunes | E2: DROVETTA CESAR JUAN DOMINGO | F2: Almacen/Despensa | G2: Santa Fe | H2: Conrado Pujol | I2: 25 | J2: 12 | K2: 15 | L2: =I2+J2 -> 37 | M2: =L2+K2 -> 52 | N2: =IF(I2>0,"Sí","No") -> Sí | O2: =IF(J2>0,"Sí","No") -> Sí | P2: =IF(K2>0,"Sí","No") -> Sí | Q2: =IF(OR(I2>0,J2>0),"Sí","No") -> Sí | R2: 2000 | S2: 2800 | T2: 1800 | U2: 2500 | V2: 3600 | W2: =IF(AND(I2>0,R2>0),(S2-R2)/R2,"") -> 0.4 | X2: =IF(AND(J2>0,T2>0),(U2-T2)/T2,"") -> 0.38888889 | Y2: =IF(AND(K2>0,V2>0),(V2-Resumen!$B$7)/Resumen!$B$7,"") -> 0.44 | Z2: =IF(AND(K2>0,I2>0,V2>0,S2>0),V2-S2,"") -> 800 | AA2: =IF(Z2<>"",Z2/S2,"") -> 0.28571429 | AB2: =IF(AND(K2>0,J2>0,V2>0,U2>0),V2-U2,"") -> 1100 | AC2: =IF(AB2<>"",AB2/U2,"") -> 0.44 | AD2: 5 | AE2: 6 | AF2: 4 | AG2: =AD2+AE2+AF2 -> 15 | AH2: =IF(AG2>0,AD2/AG2,"") -> 0.33333333 | AI2: 0 | AJ2: 0 | AK2: 0 | AL2: =IF(OR(AJ2>0,AK2>0),"Sí","No") -> No | AM2: Contado | AN2: Contado | AO2: =IF(M2>0,K2/M2,"") -> 0.28846154 | AP2: =IF(M2>=Resumen!$B$5,"Alto","Bajo") -> Alto | AQ2: =IF(AO2>=Resumen!$B$28,"Alto","Bajo") -> Bajo | AR2: =AP2&" Potencial / "&AQ2&" Share" -> Alto Potencial / Bajo Share | AS2: =IF(Q2="Sí",IF(AO2>=Resumen!$B$29,"Alto","Bajo"),"") -> Bajo | AT2: =IF(AS2<>"",AP2&" Potencial / "&AS2&" Share","") -> Alto Potencial / Bajo Share | AU2: =IF(AH2="","Sin dato",IF(AH2-AO2>Resumen!$B$6,"Sobre-exhibido",IF(AO2-AH2>Resumen!$B$6,"Sub-exhibido","En línea"))) -> En línea | AV2: =IF(AT2="","",IF(AT2="Alto Potencial / Bajo Share",1,IF(AT2="Alto Potencial / Alto Share",2,IF(AT2="Bajo Potencial / Alto Share",3,4)))) -> 1 | AW2: =IF(Q2="No","Sin competencia directa",IF(AV2=1,"1 - Foco Conquista (Alto Pot / Bajo Share)",IF(AV2=2,"2 - Foco Defensa (Alto Pot / Alto Share)",IF(AV2=3,"3 - Monitoreo (Bajo Pot / Alto Share)","4 - Baja Prioridad (Bajo Pot / Bajo Share)")))) -> 1 - Foco Conquista (Alto Pot / Bajo Share) | AX2: =IF(OR(IFERROR(AND(W2<>"",Y2<>"",Y2-W2>Resumen!$B$8),FALSE()),IFERROR(AND(X2<>"",Y2<>"",Y2-X2>Resumen!$B$8),FALSE())),MAX(IF(IFERROR(AND(W2<>"",Y2<>"",Y2-W2>Resumen!$B$8),FALSE()),Y2-W2,0),IF(IFERROR(AND(X2<>"",Y2<>"",Y2-X2>Resumen!$B$8),FALSE()),Y2-X2,0)),"") -> 0.051111111 | AY2: =IF(OR(IFERROR(AND(W2<>"",Y2<>"",Y2-W2>Resumen!$B$8),FALSE()),IFERROR(AND(X2<>"",Y2<>"",Y2-X2>Resumen!$B$8),FALSE())),TRIM("Lays tiene mayor markup que "&IF(IFERROR(AND(W2<>"",Y2<>"",Y2-W2>Resumen!$B$8),FALSE()),"Quento ","")&IF(IFERROR(AND(X2<>"",Y2<>"",Y2-X2>Resumen!$B$8),FALSE()),"Julicroc ","")&"en este PDV"),"") -> Lays tiene mayor markup que Julicroc en este PDV | AZ2: =IF(COUNTIF('Plan Pehuamar - Lista'!$A$2:$A$167,A2)>0,"Sí","No") -> No | BA2: =IF(COUNTIF('Plan Combo 9+1'!$A$2:$A$226,A2)>0,"Sí","No") -> Sí | BB2: =IF(AH2="","No",IF(BA2="Sí",IF((AO2-AH2)>Resumen!$B$6,"Sí","No"),IF((AO2-AH2)>=Resumen!$B$132,"Sí","No"))) -> No | BC2: =IF(AND(N2="Sí",AL2="Sí",AI2=0),"Sí","No") -> No | BD2: =IF(COUNTIF('Plan 9+1 (con Pehuamar)'!$A$2:$A$227,A2)>0,"Sí","No") -> Sí
A3: 400752 | B3: 1 | C3: 101 | D3: Lunes | E3: LOPEZ MARCOS FEDERICO | F3: Almacen/Despensa | G3: Santa Fe | H3: Conrado Pujol | I3: 30 | J3: 30 | K3: 20 | L3: =I3+J3 -> 60 | M3: =L3+K3 -> 80 | N3: =IF(I3>0,"Sí","No") -> Sí | O3: =IF(J3>0,"Sí","No") -> Sí | P3: =IF(K3>0,"Sí","No") -> Sí | Q3: =IF(OR(I3>0,J3>0),"Sí","No") -> Sí | R3: 2000 | S3: 3100 | T3: 1800 | U3: 2500 | V3: 3800 | W3: =IF(AND(I3>0,R3>0),(S3-R3)/R3,"") -> 0.55 | X3: =IF(AND(J3>0,T3>0),(U3-T3)/T3,"") -> 0.38888889 | Y3: =IF(AND(K3>0,V3>0),(V3-Resumen!$B$7)/Resumen!$B$7,"") -> 0.52 | Z3: =IF(AND(K3>0,I3>0,V3>0,S3>0),V3-S3,"") -> 700 | AA3: =IF(Z3<>"",Z3/S3,"") -> 0.22580645 | AB3: =IF(AND(K3>0,J3>0,V3>0,U3>0),V3-U3,"") -> 1300 | AC3: =IF(AB3<>"",AB3/U3,"") -> 0.52 | AD3: 3 | AE3: 4 | AF3: 3 | AG3: =AD3+AE3+AF3 -> 10 | AH3: =IF(AG3>0,AD3/AG3,"") -> 0.3 | AI3: 0 | AJ3: 0 | AK3: 0 | AL3: =IF(OR(AJ3>0,AK3>0),"Sí","No") -> No | AM3: Contado | AN3: Contado | AO3: =IF(M3>0,K3/M3,"") -> 0.25 | AP3: =IF(M3>=Resumen!$B$5,"Alto","Bajo") -> Alto | AQ3: =IF(AO3>=Resumen!$B$28,"Alto","Bajo") -> Bajo | AR3: =AP3&" Potencial / "&AQ3&" Share" -> Alto Potencial / Bajo Share | AS3: =IF(Q3="Sí",IF(AO3>=Resumen!$B$29,"Alto","Bajo"),"") -> Bajo | AT3: =IF(AS3<>"",AP3&" Potencial / "&AS3&" Share","") -> Alto Potencial / Bajo Share | AU3: =IF(AH3="","Sin dato",IF(AH3-AO3>Resumen!$B$6,"Sobre-exhibido",IF(AO3-AH3>Resumen!$B$6,"Sub-exhibido","En línea"))) -> En línea | AV3: =IF(AT3="","",IF(AT3="Alto Potencial / Bajo Share",1,IF(AT3="Alto Potencial / Alto Share",2,IF(AT3="Bajo Potencial / Alto Share",3,4)))) -> 1 | AW3: =IF(Q3="No","Sin competencia directa",IF(AV3=1,"1 - Foco Conquista (Alto Pot / Bajo Share)",IF(AV3=2,"2 - Foco Defensa (Alto Pot / Alto Share)",IF(AV3=3,"3 - Monitoreo (Bajo Pot / Alto Share)","4 - Baja Prioridad (Bajo Pot / Bajo Share)")))) -> 1 - Foco Conquista (Alto Pot / Bajo Share) | AX3: =IF(OR(IFERROR(AND(W3<>"",Y3<>"",Y3-W3>Resumen!$B$8),FALSE()),IFERROR(AND(X3<>"",Y3<>"",Y3-X3>Resumen!$B$8),FALSE())),MAX(IF(IFERROR(AND(W3<>"",Y3<>"",Y3-W3>Resumen!$B$8),FALSE()),Y3-W3,0),IF(IFERROR(AND(X3<>"",Y3<>"",Y3-X3>Resumen!$B$8),FALSE()),Y3-X3,0)),"") -> 0.13111111 | AY3: =IF(OR(IFERROR(AND(W3<>"",Y3<>"",Y3-W3>Resumen!$B$8),FALSE()),IFERROR(AND(X3<>"",Y3<>"",Y3-X3>Resumen!$B$8),FALSE())),TRIM("Lays tiene mayor markup que "&IF(IFERROR(AND(W3<>"",Y3<>"",Y3-W3>Resumen!$B$8),FALSE()),"Quento ","")&IF(IFERROR(AND(X3<>"",Y3<>"",Y3-X3>Resumen!$B$8),FALSE()),"Julicroc ","")&"en este PDV"),"") -> Lays tiene mayor markup que Julicroc en este PDV | AZ3: =IF(COUNTIF('Plan Pehuamar - Lista'!$A$2:$A$167,A3)>0,"Sí","No") -> No | BA3: =IF(COUNTIF('Plan Combo 9+1'!$A$2:$A$226,A3)>0,"Sí","No") -> Sí | BB3: =IF(AH3="","No",IF(BA3="Sí",IF((AO3-AH3)>Resumen!$B$6,"Sí","No"),IF((AO3-AH3)>=Resumen!$B$132,"Sí","No"))) -> No | BC3: =IF(AND(N3="Sí",AL3="Sí",AI3=0),"Sí","No") -> No | BD3: =IF(COUNTIF('Plan 9+1 (con Pehuamar)'!$A$2:$A$227,A3)>0,"Sí","No") -> Sí
A4: 400757 | B4: 1 | C4: 101 | D4: Lunes | E4: RODRIGUEZ LUCIANA MARIA FLOREN | F4: Kiosco/Maxikiosco | G4: Santa Fe | H4: Conrado Pujol | I4: 35 | J4: 30 | K4: 30 | L4: =I4+J4 -> 65 | M4: =L4+K4 -> 95 | N4: =IF(I4>0,"Sí","No") -> Sí | O4: =IF(J4>0,"Sí","No") -> Sí | P4: =IF(K4>0,"Sí","No") -> Sí | Q4: =IF(OR(I4>0,J4>0),"Sí","No") -> Sí | R4: 1900 | S4: 2700 | T4: 1700 | U4: 2600 | V4: 3600 | W4: =IF(AND(I4>0,R4>0),(S4-R4)/R4,"") -> 0.42105263 | X4: =IF(AND(J4>0,T4>0),(U4-T4)/T4,"") -> 0.52941176 | Y4: =IF(AND(K4>0,V4>0),(V4-Resumen!$B$7)/Resumen!$B$7,"") -> 0.44 | Z4: =IF(AND(K4>0,I4>0,V4>0,S4>0),V4-S4,"") -> 900 | AA4: =IF(Z4<>"",Z4/S4,"") -> 0.33333333 | AB4: =IF(AND(K4>0,J4>0,V4>0,U4>0),V4-U4,"") -> 1000 | AC4: =IF(AB4<>"",AB4/U4,"") -> 0.38461538 | AD4: 3 | AE4: 4 | AF4: 3 | AG4: =AD4+AE4+AF4 -> 10 | AH4: =IF(AG4>0,AD4/AG4,"") -> 0.3 | AI4: 0 | AJ4: 0 | AK4: 0 | AL4: =IF(OR(AJ4>0,AK4>0),"Sí","No") -> No | AM4: Contado | AN4: Contado | AO4: =IF(M4>0,K4/M4,"") -> 0.31578947 | AP4: =IF(M4>=Resumen!$B$5,"Alto","Bajo") -> Alto | AQ4: =IF(AO4>=Resumen!$B$28,"Alto","Bajo") -> Bajo | AR4: =AP4&" Potencial / "&AQ4&" Share" -> Alto Potencial / Bajo Share | AS4: =IF(Q4="Sí",IF(AO4>=Resumen!$B$29,"Alto","Bajo"),"") -> Bajo | AT4: =IF(AS4<>"",AP4&" Potencial / "&AS4&" Share","") -> Alto Potencial / Bajo Share | AU4: =IF(AH4="","Sin dato",IF(AH4-AO4>Resumen!$B$6,"Sobre-exhibido",IF(AO4-AH4>Resumen!$B$6,"Sub-exhibido","En línea"))) -> En línea | AV4: =IF(AT4="","",IF(AT4="Alto Potencial / Bajo Share",1,IF(AT4="Alto Potencial / Alto Share",2,IF(AT4="Bajo Potencial / Alto Share",3,4)))) -> 1 | AW4: =IF(Q4="No","Sin competencia directa",IF(AV4=1,"1 - Foco Conquista (Alto Pot / Bajo Share)",IF(AV4=2,"2 - Foco Defensa (Alto Pot / Alto Share)",IF(AV4=3,"3 - Monitoreo (Bajo Pot / Alto Share)","4 - Baja Prioridad (Bajo Pot / Bajo Share)")))) -> 1 - Foco Conquista (Alto Pot / Bajo Share) | AX4: =IF(OR(IFERROR(AND(W4<>"",Y4<>"",Y4-W4>Resumen!$B$8),FALSE()),IFERROR(AND(X4<>"",Y4<>"",Y4-X4>Resumen!$B$8),FALSE())),MAX(IF(IFERROR(AND(W4<>"",Y4<>"",Y4-W4>Resumen!$B$8),FALSE()),Y4-W4,0),IF(IFERROR(AND(X4<>"",Y4<>"",Y4-X4>Resumen!$B$8),FALSE()),Y4-X4,0)),"") | AY4: =IF(OR(IFERROR(AND(W4<>"",Y4<>"",Y4-W4>Resumen!$B$8),FALSE()),IFERROR(AND(X4<>"",Y4<>"",Y4-X4>Resumen!$B$8),FALSE())),TRIM("Lays tiene mayor markup que "&IF(IFERROR(AND(W4<>"",Y4<>"",Y4-W4>Resumen!$B$8),FALSE()),"Quento ","")&IF(IFERROR(AND(X4<>"",Y4<>"",Y4-X4>Resumen!$B$8),FALSE()),"Julicroc ","")&"en este PDV"),"") | AZ4: =IF(COUNTIF('Plan Pehuamar - Lista'!$A$2:$A$167,A4)>0,"Sí","No") -> No | BA4: =IF(COUNTIF('Plan Combo 9+1'!$A$2:$A$226,A4)>0,"Sí","No") -> No | BB4: =IF(AH4="","No",IF(BA4="Sí",IF((AO4-AH4)>Resumen!$B$6,"Sí","No"),IF((AO4-AH4)>=Resumen!$B$132,"Sí","No"))) -> No | BC4: =IF(AND(N4="Sí",AL4="Sí",AI4=0),"Sí","No") -> No | BD4: =IF(COUNTIF('Plan 9+1 (con Pehuamar)'!$A$2:$A$227,A4)>0,"Sí","No") -> Sí
A5: 400758 | B5: 1 | C5: 101 | D5: Lunes | E5: CLAUSEN DANIEL | F5: Kiosco/Maxikiosco | G5: Santa Fe | H5: Conrado Pujol | I5: 0 | J5: 0 | K5: 0.2 | L5: =I5+J5 -> 0 | M5: =L5+K5 -> 0.2 | N5: =IF(I5>0,"Sí","No") -> No | O5: =IF(J5>0,"Sí","No") -> No | P5: =IF(K5>0,"Sí","No") -> Sí | Q5: =IF(OR(I5>0,J5>0),"Sí","No") -> No | W5: =IF(AND(I5>0,R5>0),(S5-R5)/R5,"") | X5: =IF(AND(J5>0,T5>0),(U5-T5)/T5,"") | Y5: =IF(AND(K5>0,V5>0),(V5-Resumen!$B$7)/Resumen!$B$7,"") | Z5: =IF(AND(K5>0,I5>0,V5>0,S5>0),V5-S5,"") | AA5: =IF(Z5<>"",Z5/S5,"") | AB5: =IF(AND(K5>0,J5>0,V5>0,U5>0),V5-U5,"") | AC5: =IF(AB5<>"",AB5/U5,"") | AD5: 0 | AE5: 0 | AF5: 0 | AG5: =AD5+AE5+AF5 -> 0 | AH5: =IF(AG5>0,AD5/AG5,"") | AI5: 0 | AJ5: 0 | AK5: 0 | AL5: =IF(OR(AJ5>0,AK5>0),"Sí","No") -> No | AO5: =IF(M5>0,K5/M5,"") -> 1 | AP5: =IF(M5>=Resumen!$B$5,"Alto","Bajo") -> Bajo | AQ5: =IF(AO5>=Resumen!$B$28,"Alto","Bajo") -> Alto | AR5: =AP5&" Potencial / "&AQ5&" Share" -> Bajo Potencial / Alto Share | AS5: =IF(Q5="Sí",IF(AO5>=Resumen!$B$29,"Alto","Bajo"),"") | AT5: =IF(AS5<>"",AP5&" Potencial / "&AS5&" Share","") | AU5: =IF(AH5="","Sin dato",IF(AH5-AO5>Resumen!$B$6,"Sobre-exhibido",IF(AO5-AH5>Resumen!$B$6,"Sub-exhibido","En línea"))) -> Sin dato | AV5: =IF(AT5="","",IF(AT5="Alto Potencial / Bajo Share",1,IF(AT5="Alto Potencial / Alto Share",2,IF(AT5="Bajo Potencial / Alto Share",3,4)))) | AW5: =IF(Q5="No","Sin competencia directa",IF(AV5=1,"1 - Foco Conquista (Alto Pot / Bajo Share)",IF(AV5=2,"2 - Foco Defensa (Alto Pot / Alto Share)",IF(AV5=3,"3 - Monitoreo (Bajo Pot / Alto Share)","4 - Baja Prioridad (Bajo Pot / Bajo Share)")))) -> Sin competencia directa | AX5: =IF(OR(IFERROR(AND(W5<>"",Y5<>"",Y5-W5>Resumen!$B$8),FALSE()),IFERROR(AND(X5<>"",Y5<>"",Y5-X5>Resumen!$B$8),FALSE())),MAX(IF(IFERROR(AND(W5<>"",Y5<>"",Y5-W5>Resumen!$B$8),FALSE()),Y5-W5,0),IF(IFERROR(AND(X5<>"",Y5<>"",Y5-X5>Resumen!$B$8),FALSE()),Y5-X5,0)),"") | AY5: =IF(OR(IFERROR(AND(W5<>"",Y5<>"",Y5-W5>Resumen!$B$8),FALSE()),IFERROR(AND(X5<>"",Y5<>"",Y5-X5>Resumen!$B$8),FALSE())),TRIM("Lays tiene mayor markup que "&IF(IFERROR(AND(W5<>"",Y5<>"",Y5-W5>Resumen!$B$8),FALSE()),"Quento ","")&IF(IFERROR(AND(X5<>"",Y5<>"",Y5-X5>Resumen!$B$8),FALSE()),"Julicroc ","")&"en este PDV"),"") | AZ5: =IF(COUNTIF('Plan Pehuamar - Lista'!$A$2:$A$167,A5)>0,"Sí","No") -> No | BA5: =IF(COUNTIF('Plan Combo 9+1'!$A$2:$A$226,A5)>0,"Sí","No") -> No | BB5: =IF(AH5="","No",IF(BA5="Sí",IF((AO5-AH5)>Resumen!$B$6,"Sí","No"),IF((AO5-AH5)>=Resumen!$B$132,"Sí","No"))) -> No | BC5: =IF(AND(N5="Sí",AL5="Sí",AI5=0),"Sí","No") -> No | BD5: =IF(COUNTIF('Plan 9+1 (con Pehuamar)'!$A$2:$A$227,A5)>0,"Sí","No") -> No
A6: 400761 | B6: 1 | C6: 101 | D6: Lunes | E6: SANCHEZ MARIA JOSE | F6: Almacen/Despensa | G6: Santa Fe | H6: Conrado Pujol | I6: 0 | J6: 0 | K6: 0.4 | L6: =I6+J6 -> 0 | M6: =L6+K6 -> 0.4 | N6: =IF(I6>0,"Sí","No") -> No | O6: =IF(J6>0,"Sí","No") -> No | P6: =IF(K6>0,"Sí","No") -> Sí | Q6: =IF(OR(I6>0,J6>0),"Sí","No") -> No | W6: =IF(AND(I6>0,R6>0),(S6-R6)/R6,"") | X6: =IF(AND(J6>0,T6>0),(U6-T6)/T6,"") | Y6: =IF(AND(K6>0,V6>0),(V6-Resumen!$B$7)/Resumen!$B$7,"") | Z6: =IF(AND(K6>0,I6>0,V6>0,S6>0),V6-S6,"") | AA6: =IF(Z6<>"",Z6/S6,"") | AB6: =IF(AND(K6>0,J6>0,V6>0,U6>0),V6-U6,"") | AC6: =IF(AB6<>"",AB6/U6,"") | AD6: 0 | AE6: 0 | AF6: 0 | AG6: =AD6+AE6+AF6 -> 0 | AH6: =IF(AG6>0,AD6/AG6,"") | AI6: 0 | AJ6: 0 | AK6: 0 | AL6: =IF(OR(AJ6>0,AK6>0),"Sí","No") -> No | AO6: =IF(M6>0,K6/M6,"") -> 1 | AP6: =IF(M6>=Resumen!$B$5,"Alto","Bajo") -> Bajo | AQ6: =IF(AO6>=Resumen!$B$28,"Alto","Bajo") -> Alto | AR6: =AP6&" Potencial / "&AQ6&" Share" -> Bajo Potencial / Alto Share | AS6: =IF(Q6="Sí",IF(AO6>=Resumen!$B$29,"Alto","Bajo"),"") | AT6: =IF(AS6<>"",AP6&" Potencial / "&AS6&" Share","") | AU6: =IF(AH6="","Sin dato",IF(AH6-AO6>Resumen!$B$6,"Sobre-exhibido",IF(AO6-AH6>Resumen!$B$6,"Sub-exhibido","En línea"))) -> Sin dato | AV6: =IF(AT6="","",IF(AT6="Alto Potencial / Bajo Share",1,IF(AT6="Alto Potencial / Alto Share",2,IF(AT6="Bajo Potencial / Alto Share",3,4)))) | AW6: =IF(Q6="No","Sin competencia directa",IF(AV6=1,"1 - Foco Conquista (Alto Pot / Bajo Share)",IF(AV6=2,"2 - Foco Defensa (Alto Pot / Alto Share)",IF(AV6=3,"3 - Monitoreo (Bajo Pot / Alto Share)","4 - Baja Prioridad (Bajo Pot / Bajo Share)")))) -> Sin competencia directa | AX6: =IF(OR(IFERROR(AND(W6<>"",Y6<>"",Y6-W6>Resumen!$B$8),FALSE()),IFERROR(AND(X6<>"",Y6<>"",Y6-X6>Resumen!$B$8),FALSE())),MAX(IF(IFERROR(AND(W6<>"",Y6<>"",Y6-W6>Resumen!$B$8),FALSE()),Y6-W6,0),IF(IFERROR(AND(X6<>"",Y6<>"",Y6-X6>Resumen!$B$8),FALSE()),Y6-X6,0)),"") | AY6: =IF(OR(IFERROR(AND(W6<>"",Y6<>"",Y6-W6>Resumen!$B$8),FALSE()),IFERROR(AND(X6<>"",Y6<>"",Y6-X6>Resumen!$B$8),FALSE())),TRIM("Lays tiene mayor markup que "&IF(IFERROR(AND(W6<>"",Y6<>"",Y6-W6>Resumen!$B$8),FALSE()),"Quento ","")&IF(IFERROR(AND(X6<>"",Y6<>"",Y6-X6>Resumen!$B$8),FALSE()),"Julicroc ","")&"en este PDV"),"") | AZ6: =IF(COUNTIF('Plan Pehuamar - Lista'!$A$2:$A$167,A6)>0,"Sí","No") -> No | BA6: =IF(COUNTIF('Plan Combo 9+1'!$A$2:$A$226,A6)>0,"Sí","No") -> No | BB6: =IF(AH6="","No",IF(BA6="Sí",IF((AO6-AH6)>Resumen!$B$6,"Sí","No"),IF((AO6-AH6)>=Resumen!$B$132,"Sí","No"))) -> No | BC6: =IF(AND(N6="Sí",AL6="Sí",AI6=0),"Sí","No") -> No | BD6: =IF(COUNTIF('Plan 9+1 (con Pehuamar)'!$A$2:$A$227,A6)>0,"Sí","No") -> No
A7: 400766 | B7: 1 | C7: 101 | D7: Lunes | E7: SULIGOY ALBERTO RAUL | F7: Almacen/Despensa | G7: Santa Fe | H7: Conrado Pujol | I7: 15 | J7: 20 | K7: 10 | L7: =I7+J7 -> 35 | M7: =L7+K7 -> 45 | N7: =IF(I7>0,"Sí","No") -> Sí | O7: =IF(J7>0,"Sí","No") -> Sí | P7: =IF(K7>0,"Sí","No") -> Sí | Q7: =IF(OR(I7>0,J7>0),"Sí","No") -> Sí | R7: 1900 | S7: 2700 | T7: 1600 | U7: 2400 | V7: 3500 | W7: =IF(AND(I7>0,R7>0),(S7-R7)/R7,"") -> 0.42105263 | X7: =IF(AND(J7>0,T7>0),(U7-T7)/T7,"") -> 0.5 | Y7: =IF(AND(K7>0,V7>0),(V7-Resumen!$B$7)/Resumen!$B$7,"") -> 0.4 | Z7: =IF(AND(K7>0,I7>0,V7>0,S7>0),V7-S7,"") -> 800 | AA7: =IF(Z7<>"",Z7/S7,"") -> 0.2962963 | AB7: =IF(AND(K7>0,J7>0,V7>0,U7>0),V7-U7,"") -> 1100 | AC7: =IF(AB7<>"",AB7/U7,"") -> 0.45833333 | AD7: 3 | AE7: 4 | AF7: 3 | AG7: =AD7+AE7+AF7 -> 10 | AH7: =IF(AG7>0,AD7/AG7,"") -> 0.3 | AI7: 0 | AJ7: 0 | AK7: 0 | AL7: =IF(OR(AJ7>0,AK7>0),"Sí","No") -> No | AM7: Contado | AN7: Contado | AO7: =IF(M7>0,K7/M7,"") -> 0.22222222 | AP7: =IF(M7>=Resumen!$B$5,"Alto","Bajo") -> Alto | AQ7: =IF(AO7>=Resumen!$B$28,"Alto","Bajo") -> Bajo | AR7: =AP7&" Potencial / "&AQ7&" Share" -> Alto Potencial / Bajo Share | AS7: =IF(Q7="Sí",IF(AO7>=Resumen!$B$29,"Alto","Bajo"),"") -> Bajo | AT7: =IF(AS7<>"",AP7&" Potencial / "&AS7&" Share","") -> Alto Potencial / Bajo Share | AU7: =IF(AH7="","Sin dato",IF(AH7-AO7>Resumen!$B$6,"Sobre-exhibido",IF(AO7-AH7>Resumen!$B$6,"Sub-exhibido","En línea"))) -> Sobre-exhibido | AV7: =IF(AT7="","",IF(AT7="Alto Potencial / Bajo Share",1,IF(AT7="Alto Potencial / Alto Share",2,IF(AT7="Bajo Potencial / Alto Share",3,4)))) -> 1 | AW7: =IF(Q7="No","Sin competencia directa",IF(AV7=1,"1 - Foco Conquista (Alto Pot / Bajo Share)",IF(AV7=2,"2 - Foco Defensa (Alto Pot / Alto Share)",IF(AV7=3,"3 - Monitoreo (Bajo Pot / Alto Share)","4 - Baja Prioridad (Bajo Pot / Bajo Share)")))) -> 1 - Foco Conquista (Alto Pot / Bajo Share) | AX7: =IF(OR(IFERROR(AND(W7<>"",Y7<>"",Y7-W7>Resumen!$B$8),FALSE()),IFERROR(AND(X7<>"",Y7<>"",Y7-X7>Resumen!$B$8),FALSE())),MAX(IF(IFERROR(AND(W7<>"",Y7<>"",Y7-W7>Resumen!$B$8),FALSE()),Y7-W7,0),IF(IFERROR(AND(X7<>"",Y7<>"",Y7-X7>Resumen!$B$8),FALSE()),Y7-X7,0)),"") | AY7: =IF(OR(IFERROR(AND(W7<>"",Y7<>"",Y7-W7>Resumen!$B$8),FALSE()),IFERROR(AND(X7<>"",Y7<>"",Y7-X7>Resumen!$B$8),FALSE())),TRIM("Lays tiene mayor markup que "&IF(IFERROR(AND(W7<>"",Y7<>"",Y7-W7>Resumen!$B$8),FALSE()),"Quento ","")&IF(IFERROR(AND(X7<>"",Y7<>"",Y7-X7>Resumen!$B$8),FALSE()),"Julicroc ","")&"en este PDV"),"") | AZ7: =IF(COUNTIF('Plan Pehuamar - Lista'!$A$2:$A$167,A7)>0,"Sí","No") -> No | BA7: =IF(COUNTIF('Plan Combo 9+1'!$A$2:$A$226,A7)>0,"Sí","No") -> Sí | BB7: =IF(AH7="","No",IF(BA7="Sí",IF((AO7-AH7)>Resumen!$B$6,"Sí","No"),IF((AO7-AH7)>=Resumen!$B$132,"Sí","No"))) -> No | BC7: =IF(AND(N7="Sí",AL7="Sí",AI7=0),"Sí","No") -> No | BD7: =IF(COUNTIF('Plan 9+1 (con Pehuamar)'!$A$2:$A$227,A7)>0,"Sí","No") -> Sí
A8: 400770 | B8: 1 | C8: 101 | D8: Lunes | E8: BATTISTELLA MIGUEL ANGEL | F8: Autoservicio Tradicional | G8: Santa Fe | H8: Conrado Pujol | I8: 25 | J8: 20 | K8: 15 | L8: =I8+J8 -> 45 | M8: =L8+K8 -> 60 | N8: =IF(I8>0,"Sí","No") -> Sí | O8: =IF(J8>0,"Sí","No") -> Sí | P8: =IF(K8>0,"Sí","No") -> Sí | Q8: =IF(OR(I8>0,J8>0),"Sí","No") -> Sí | R8: 2000 | S8: 2900 | T8: 1800 | U8: 2500 | V8: 3700 | W8: =IF(AND(I8>0,R8>0),(S8-R8)/R8,"") -> 0.45 | X8: =IF(AND(J8>0,T8>0),(U8-T8)/T8,"") -> 0.38888889 | Y8: =IF(AND(K8>0,V8>0),(V8-Resumen!$B$7)/Resumen!$B$7,"") -> 0.48 | Z8: =IF(AND(K8>0,I8>0,V8>0,S8>0),V8-S8,"") -> 800 | AA8: =IF(Z8<>"",Z8/S8,"") -> 0.27586207 | AB8: =IF(AND(K8>0,J8>0,V8>0,U8>0),V8-U8,"") -> 1200 | AC8: =IF(AB8<>"",AB8/U8,"") -> 0.48 | AD8: 5 | AE8: 3 | AF8: 3 | AG8: =AD8+AE8+AF8 -> 11 | AH8: =IF(AG8>0,AD8/AG8,"") -> 0.45454545 | AI8: 1 | AJ8: 1 | AK8: 0 | AL8: =IF(OR(AJ8>0,AK8>0),"Sí","No") -> Sí | AM8: Contado | AN8: Contado | AO8: =IF(M8>0,K8/M8,"") -> 0.25 | AP8: =IF(M8>=Resumen!$B$5,"Alto","Bajo") -> Alto | AQ8: =IF(AO8>=Resumen!$B$28,"Alto","Bajo") -> Bajo | AR8: =AP8&" Potencial / "&AQ8&" Share" -> Alto Potencial / Bajo Share | AS8: =IF(Q8="Sí",IF(AO8>=Resumen!$B$29,"Alto","Bajo"),"") -> Bajo | AT8: =IF(AS8<>"",AP8&" Potencial / "&AS8&" Share","") -> Alto Potencial / Bajo Share | AU8: =IF(AH8="","Sin dato",IF(AH8-AO8>Resumen!$B$6,"Sobre-exhibido",IF(AO8-AH8>Resumen!$B$6,"Sub-exhibido","En línea"))) -> Sobre-exhibido | AV8: =IF(AT8="","",IF(AT8="Alto Potencial / Bajo Share",1,IF(AT8="Alto Potencial / Alto Share",2,IF(AT8="Bajo Potencial / Alto Share",3,4)))) -> 1 | AW8: =IF(Q8="No","Sin competencia directa",IF(AV8=1,"1 - Foco Conquista (Alto Pot / Bajo Share)",IF(AV8=2,"2 - Foco Defensa (Alto Pot / Alto Share)",IF(AV8=3,"3 - Monitoreo (Bajo Pot / Alto Share)","4 - Baja Prioridad (Bajo Pot / Bajo Share)")))) -> 1 - Foco Conquista (Alto Pot / Bajo Share) | AX8: =IF(OR(IFERROR(AND(W8<>"",Y8<>"",Y8-W8>Resumen!$B$8),FALSE()),IFERROR(AND(X8<>"",Y8<>"",Y8-X8>Resumen!$B$8),FALSE())),MAX(IF(IFERROR(AND(W8<>"",Y8<>"",Y8-W8>Resumen!$B$8),FALSE()),Y8-W8,0),IF(IFERROR(AND(X8<>"",Y8<>"",Y8-X8>Resumen!$B$8),FALSE()),Y8-X8,0)),"") -> 0.091111111 | AY8: =IF(OR(IFERROR(AND(W8<>"",Y8<>"",Y8-W8>Resumen!$B$8),FALSE()),IFERROR(AND(X8<>"",Y8<>"",Y8-X8>Resumen!$B$8),FALSE())),TRIM("Lays tiene mayor markup que "&IF(IFERROR(AND(W8<>"",Y8<>"",Y8-W8>Resumen!$B$8),FALSE()),"Quento ","")&IF(IFERROR(AND(X8<>"",Y8<>"",Y8-X8>Resumen!$B$8),FALSE()),"Julicroc ","")&"en este PDV"),"") -> Lays tiene mayor markup que Julicroc en este PDV | AZ8: =IF(COUNTIF('Plan Pehuamar - Lista'!$A$2:$A$167,A8)>0,"Sí","No") -> No | BA8: =IF(COUNTIF('Plan Combo 9+1'!$A$2:$A$226,A8)>0,"Sí","No") -> Sí | BB8: =IF(AH8="","No",IF(BA8="Sí",IF((AO8-AH8)>Resumen!$B$6,"Sí","No"),IF((AO8-AH8)>=Resumen!$B$132,"Sí","No"))) -> No | BC8: =IF(AND(N8="Sí",AL8="Sí",AI8=0),"Sí","No") -> No | BD8: =IF(COUNTIF('Plan 9+1 (con Pehuamar)'!$A$2:$A$227,A8)>0,"Sí","No") -> Sí
A9: 400771 | B9: 1 | C9: 101 | D9: Lunes | E9: PANIFICACION KOCH SRL | F9: Almacen/Despensa | G9: Santa Fe | H9: Conrado Pujol | I9: 0 | J9: 0 | K9: 0.4 | L9: =I9+J9 -> 0 | M9: =L9+K9 -> 0.4 | N9: =IF(I9>0,"Sí","No") -> No | O9: =IF(J9>0,"Sí","No") -> No | P9: =IF(K9>0,"Sí","No") -> Sí | Q9: =IF(OR(I9>0,J9>0),"Sí","No") -> No | W9: =IF(AND(I9>0,R9>0),(S9-R9)/R9,"") | X9: =IF(AND(J9>0,T9>0),(U9-T9)/T9,"") | Y9: =IF(AND(K9>0,V9>0),(V9-Resumen!$B$7)/Resumen!$B$7,"") | Z9: =IF(AND(K9>0,I9>0,V9>0,S9>0),V9-S9,"") | AA9: =IF(Z9<>"",Z9/S9,"") | AB9: =IF(AND(K9>0,J9>0,V9>0,U9>0),V9-U9,"") | AC9: =IF(AB9<>"",AB9/U9,"") | AD9: 0 | AE9: 0 | AF9: 0 | AG9: =AD9+AE9+AF9 -> 0 | AH9: =IF(AG9>0,AD9/AG9,"") | AI9: 0 | AJ9: 0 | AK9: 0 | AL9: =IF(OR(AJ9>0,AK9>0),"Sí","No") -> No | AO9: =IF(M9>0,K9/M9,"") -> 1 | AP9: =IF(M9>=Resumen!$B$5,"Alto","Bajo") -> Bajo | AQ9: =IF(AO9>=Resumen!$B$28,"Alto","Bajo") -> Alto | AR9: =AP9&" Potencial / "&AQ9&" Share" -> Bajo Potencial / Alto Share | AS9: =IF(Q9="Sí",IF(AO9>=Resumen!$B$29,"Alto","Bajo"),"") | AT9: =IF(AS9<>"",AP9&" Potencial / "&AS9&" Share","") | AU9: =IF(AH9="","Sin dato",IF(AH9-AO9>Resumen!$B$6,"Sobre-exhibido",IF(AO9-AH9>Resumen!$B$6,"Sub-exhibido","En línea"))) -> Sin dato | AV9: =IF(AT9="","",IF(AT9="Alto Potencial / Bajo Share",1,IF(AT9="Alto Potencial / Alto Share",2,IF(AT9="Bajo Potencial / Alto Share",3,4)))) | AW9: =IF(Q9="No","Sin competencia directa",IF(AV9=1,"1 - Foco Conquista (Alto Pot / Bajo Share)",IF(AV9=2,"2 - Foco Defensa (Alto Pot / Alto Share)",IF(AV9=3,"3 - Monitoreo (Bajo Pot / Alto Share)","4 - Baja Prioridad (Bajo Pot / Bajo Share)")))) -> Sin competencia directa | AX9: =IF(OR(IFERROR(AND(W9<>"",Y9<>"",Y9-W9>Resumen!$B$8),FALSE()),IFERROR(AND(X9<>"",Y9<>"",Y9-X9>Resumen!$B$8),FALSE())),MAX(IF(IFERROR(AND(W9<>"",Y9<>"",Y9-W9>Resumen!$B$8),FALSE()),Y9-W9,0),IF(IFERROR(AND(X9<>"",Y9<>"",Y9-X9>Resumen!$B$8),FALSE()),Y9-X9,0)),"") | AY9: =IF(OR(IFERROR(AND(W9<>"",Y9<>"",Y9-W9>Resumen!$B$8),FALSE()),IFERROR(AND(X9<>"",Y9<>"",Y9-X9>Resumen!$B$8),FALSE())),TRIM("Lays tiene mayor markup que "&IF(IFERROR(AND(W9<>"",Y9<>"",Y9-W9>Resumen!$B$8),FALSE()),"Quento ","")&IF(IFERROR(AND(X9<>"",Y9<>"",Y9-X9>Resumen!$B$8),FALSE()),"Julicroc ","")&"en este PDV"),"") | AZ9: =IF(COUNTIF('Plan Pehuamar - Lista'!$A$2:$A$167,A9)>0,"Sí","No") -> No | BA9: =IF(COUNTIF('Plan Combo 9+1'!$A$2:$A$226,A9)>0,"Sí","No") -> No | BB9: =IF(AH9="","No",IF(BA9="Sí",IF((AO9-AH9)>Resumen!$B$6,"Sí","No"),IF((AO9-AH9)>=Resumen!$B$132,"Sí","No"))) -> No | BC9: =IF(AND(N9="Sí",AL9="Sí",AI9=0),"Sí","No") -> No | BD9: =IF(COUNTIF('Plan 9+1 (con Pehuamar)'!$A$2:$A$227,A9)>0,"Sí","No") -> No
A10: 400789 | B10: 1 | C10: 101 | D10: Lunes | E10: VALIENTE HECTOR DARIO | F10: Almacen/Despensa | G10: Santa Fe | H10: Conrado Pujol | I10: 0 | J10: 0 | K10: 0.9 | L10: =I10+J10 -> 0 | M10: =L10+K10 -> 0.9 | N10: =IF(I10>0,"Sí","No") -> No | O10: =IF(J10>0,"Sí","No") -> No | P10: =IF(K10>0,"Sí","No") -> Sí | Q10: =IF(OR(I10>0,J10>0),"Sí","No") -> No | W10: =IF(AND(I10>0,R10>0),(S10-R10)/R10,"") | X10: =IF(AND(J10>0,T10>0),(U10-T10)/T10,"") | Y10: =IF(AND(K10>0,V10>0),(V10-Resumen!$B$7)/Resumen!$B$7,"") | Z10: =IF(AND(K10>0,I10>0,V10>0,S10>0),V10-S10,"") | AA10: =IF(Z10<>"",Z10/S10,"") | AB10: =IF(AND(K10>0,J10>0,V10>0,U10>0),V10-U10,"") | AC10: =IF(AB10<>"",AB10/U10,"") | AD10: 0 | AE10: 0 | AF10: 0 | AG10: =AD10+AE10+AF10 -> 0 | AH10: =IF(AG10>0,AD10/AG10,"") | AI10: 0 | AJ10: 0 | AK10: 0 | AL10: =IF(OR(AJ10>0,AK10>0),"Sí","No") -> No | AO10: =IF(M10>0,K10/M10,"") -> 1 | AP10: =IF(M10>=Resumen!$B$5,"Alto","Bajo") -> Bajo | AQ10: =IF(AO10>=Resumen!$B$28,"Alto","Bajo") -> Alto | AR10: =AP10&" Potencial / "&AQ10&" Share" -> Bajo Potencial / Alto Share | AS10: =IF(Q10="Sí",IF(AO10>=Resumen!$B$29,"Alto","Bajo"),"") | AT10: =IF(AS10<>"",AP10&" Potencial / "&AS10&" Share","") | AU10: =IF(AH10="","Sin dato",IF(AH10-AO10>Resumen!$B$6,"Sobre-exhibido",IF(AO10-AH10>Resumen!$B$6,"Sub-exhibido","En línea"))) -> Sin dato | AV10: =IF(AT10="","",IF(AT10="Alto Potencial / Bajo Share",1,IF(AT10="Alto Potencial / Alto Share",2,IF(AT10="Bajo Potencial / Alto Share",3,4)))) | AW10: =IF(Q10="No","Sin competencia directa",IF(AV10=1,"1 - Foco Conquista (Alto Pot / Bajo Share)",IF(AV10=2,"2 - Foco Defensa (Alto Pot / Alto Share)",IF(AV10=3,"3 - Monitoreo (Bajo Pot / Alto Share)","4 - Baja Prioridad (Bajo Pot / Bajo Share)")))) -> Sin competencia directa | AX10: =IF(OR(IFERROR(AND(W10<>"",Y10<>"",Y10-W10>Resumen!$B$8),FALSE()),IFERROR(AND(X10<>"",Y10<>"",Y10-X10>Resumen!$B$8),FALSE())),MAX(IF(IFERROR(AND(W10<>"",Y10<>"",Y10-W10>Resumen!$B$8),FALSE()),Y10-W10,0),IF(IFERROR(AND(X10<>"",Y10<>"",Y10-X10>Resumen!$B$8),FALSE()),Y10-X10,0)),"") | AY10: =IF(OR(IFERROR(AND(W10<>"",Y10<>"",Y10-W10>Resumen!$B$8),FALSE()),IFERROR(AND(X10<>"",Y10<>"",Y10-X10>Resumen!$B$8),FALSE())),TRIM("Lays tiene mayor markup que "&IF(IFERROR(AND(W10<>"",Y10<>"",Y10-W10>Resumen!$B$8),FALSE()),"Quento ","")&IF(IFERROR(AND(X10<>"",Y10<>"",Y10-X10>Resumen!$B$8),FALSE()),"Julicroc ","")&"en este PDV"),"") | AZ10: =IF(COUNTIF('Plan Pehuamar - Lista'!$A$2:$A$167,A10)>0,"Sí","No") -> No | BA10: =IF(COUNTIF('Plan Combo 9+1'!$A$2:$A$226,A10)>0,"Sí","No") -> No | BB10: =IF(AH10="","No",IF(BA10="Sí",IF((AO10-AH10)>Resumen!$B$6,"Sí","No"),IF((AO10-AH10)>=Resumen!$B$132,"Sí","No"))) -> No | BC10: =IF(AND(N10="Sí",AL10="Sí",AI10=0),"Sí","No") -> No | BD10: =IF(COUNTIF('Plan 9+1 (con Pehuamar)'!$A$2:$A$227,A10)>0,"Sí","No") -> No
A11: 400790 | B11: 1 | C11: 101 | D11: Lunes | E11: GALIANO MARIANA ANALIA | F11: Panaderia | G11: Santa Fe | H11: Conrado Pujol | I11: 0 | J11: 0 | K11: 0.8 | L11: =I11+J11 -> 0 | M11: =L11+K11 -> 0.8 | N11: =IF(I11>0,"Sí","No") -> No | O11: =IF(J11>0,"Sí","No") -> No | P11: =IF(K11>0,"Sí","No") -> Sí | Q11: =IF(OR(I11>0,J11>0),"Sí","No") -> No | W11: =IF(AND(I11>0,R11>0),(S11-R11)/R11,"") | X11: =IF(AND(J11>0,T11>0),(U11-T11)/T11,"") | Y11: =IF(AND(K11>0,V11>0),(V11-Resumen!$B$7)/Resumen!$B$7,"") | Z11: =IF(AND(K11>0,I11>0,V11>0,S11>0),V11-S11,"") | AA11: =IF(Z11<>"",Z11/S11,"") | AB11: =IF(AND(K11>0,J11>0,V11>0,U11>0),V11-U11,"") | AC11: =IF(AB11<>"",AB11/U11,"") | AD11: 0 | AE11: 0 | AF11: 0 | AG11: =AD11+AE11+AF11 -> 0 | AH11: =IF(AG11>0,AD11/AG11,"") | AI11: 0 | AJ11: 0 | AK11: 0 | AL11: =IF(OR(AJ11>0,AK11>0),"Sí","No") -> No | AO11: =IF(M11>0,K11/M11,"") -> 1 | AP11: =IF(M11>=Resumen!$B$5,"Alto","Bajo") -> Bajo | AQ11: =IF(AO11>=Resumen!$B$28,"Alto","Bajo") -> Alto | AR11: =AP11&" Potencial / "&AQ11&" Share" -> Bajo Potencial / Alto Share | AS11: =IF(Q11="Sí",IF(AO11>=Resumen!$B$29,"Alto","Bajo"),"") | AT11: =IF(AS11<>"",AP11&" Potencial / "&AS11&" Share","") | AU11: =IF(AH11="","Sin dato",IF(AH11-AO11>Resumen!$B$6,"Sobre-exhibido",IF(AO11-AH11>Resumen!$B$6,"Sub-exhibido","En línea"))) -> Sin dato | AV11: =IF(AT11="","",IF(AT11="Alto Potencial / Bajo Share",1,IF(AT11="Alto Potencial / Alto Share",2,IF(AT11="Bajo Potencial / Alto Share",3,4)))) | AW11: =IF(Q11="No","Sin competencia directa",IF(AV11=1,"1 - Foco Conquista (Alto Pot / Bajo Share)",IF(AV11=2,"2 - Foco Defensa (Alto Pot / Alto Share)",IF(AV11=3,"3 - Monitoreo (Bajo Pot / Alto Share)","4 - Baja Prioridad (Bajo Pot / Bajo Share)")))) -> Sin competencia directa | AX11: =IF(OR(IFERROR(AND(W11<>"",Y11<>"",Y11-W11>Resumen!$B$8),FALSE()),IFERROR(AND(X11<>"",Y11<>"",Y11-X11>Resumen!$B$8),FALSE())),MAX(IF(IFERROR(AND(W11<>"",Y11<>"",Y11-W11>Resumen!$B$8),FALSE()),Y11-W11,0),IF(IFERROR(AND(X11<>"",Y11<>"",Y11-X11>Resumen!$B$8),FALSE()),Y11-X11,0)),"") | AY11: =IF(OR(IFERROR(AND(W11<>"",Y11<>"",Y11-W11>Resumen!$B$8),FALSE()),IFERROR(AND(X11<>"",Y11<>"",Y11-X11>Resumen!$B$8),FALSE())),TRIM("Lays tiene mayor markup que "&IF(IFERROR(AND(W11<>"",Y11<>"",Y11-W11>Resumen!$B$8),FALSE()),"Quento ","")&IF(IFERROR(AND(X11<>"",Y11<>"",Y11-X11>Resumen!$B$8),FALSE()),"Julicroc ","")&"en este PDV"),"") | AZ11: =IF(COUNTIF('Plan Pehuamar - Lista'!$A$2:$A$167,A11)>0,"Sí","No") -> No | BA11: =IF(COUNTIF('Plan Combo 9+1'!$A$2:$A$226,A11)>0,"Sí","No") -> No | BB11: =IF(AH11="","No",IF(BA11="Sí",IF((AO11-AH11)>Resumen!$B$6,"Sí","No"),IF((AO11-AH11)>=Resumen!$B$132,"Sí","No"))) -> No | BC11: =IF(AND(N11="Sí",AL11="Sí",AI11=0),"Sí","No") -> No | BD11: =IF(COUNTIF('Plan 9+1 (con Pehuamar)'!$A$2:$A$227,A11)>0,"Sí","No") -> No
A12: 400791 | B12: 1 | C12: 101 | D12: Lunes | E12: ARBIZU VIVIANA BELKYS | F12: Almacen/Despensa | G12: Santa Fe | H12: Conrado Pujol | I12: 15 | J12: 10 | K12: 15 | L12: =I12+J12 -> 25 | M12: =L12+K12 -> 40 | N12: =IF(I12>0,"Sí","No") -> Sí | O12: =IF(J12>0,"Sí","No") -> Sí | P12: =IF(K12>0,"Sí","No") -> Sí | Q12: =IF(OR(I12>0,J12>0),"Sí","No") -> Sí | R12: 1800 | S12: 3000 | T12: 1500 | U12: 2300 | V12: 3600 | W12: =IF(AND(I12>0,R12>0),(S12-R12)/R12,"") -> 0.66666667 | X12: =IF(AND(J12>0,T12>0),(U12-T12)/T12,"") -> 0.53333333 | Y12: =IF(AND(K12>0,V12>0),(V12-Resumen!$B$7)/Resumen!$B$7,"") -> 0.44 | Z12: =IF(AND(K12>0,I12>0,V12>0,S12>0),V12-S12,"") -> 600 | AA12: =IF(Z12<>"",Z12/S12,"") -> 0.2 | AB12: =IF(AND(K12>0,J12>0,V12>0,U12>0),V12-U12,"") -> 1300 | AC12: =IF(AB12<>"",AB12/U12,"") -> 0.56521739 | AD12: 3 | AE12: 3 | AF12: 2 | AG12: =AD12+AE12+AF12 -> 8 | AH12: =IF(AG12>0,AD12/AG12,"") -> 0.375 | AI12: 0 | AJ12: 0 | AK12: 0 | AL12: =IF(OR(AJ12>0,AK12>0),"Sí","No") -> No | AM12: Contado | AN12: Contado | AO12: =IF(M12>0,K12/M12,"") -> 0.375 | AP12: =IF(M12>=Resumen!$B$5,"Alto","Bajo") -> Alto | AQ12: =IF(AO12>=Resumen!$B$28,"Alto","Bajo") -> Bajo | AR12: =AP12&" Potencial / "&AQ12&" Share" -> Alto Potencial / Bajo Share | AS12: =IF(Q12="Sí",IF(AO12>=Resumen!$B$29,"Alto","Bajo"),"") -> Bajo | AT12: =IF(AS12<>"",AP12&" Potencial / "&AS12&" Share","") -> Alto Potencial / Bajo Share | AU12: =IF(AH12="","Sin dato",IF(AH12-AO12>Resumen!$B$6,"Sobre-exhibido",IF(AO12-AH12>Resumen!$B$6,"Sub-exhibido","En línea"))) -> En línea | AV12: =IF(AT12="","",IF(AT12="Alto Potencial / Bajo Share",1,IF(AT12="Alto Potencial / Alto Share",2,IF(AT12="Bajo Potencial / Alto Share",3,4)))) -> 1 | AW12: =IF(Q12="No","Sin competencia directa",IF(AV12=1,"1 - Foco Conquista (Alto Pot / Bajo Share)",IF(AV12=2,"2 - Foco Defensa (Alto Pot / Alto Share)",IF(AV12=3,"3 - Monitoreo (Bajo Pot / Alto Share)","4 - Baja Prioridad (Bajo Pot / Bajo Share)")))) -> 1 - Foco Conquista (Alto Pot / Bajo Share) | AX12: =IF(OR(IFERROR(AND(W12<>"",Y12<>"",Y12-W12>Resumen!$B$8),FALSE()),IFERROR(AND(X12<>"",Y12<>"",Y12-X12>Resumen!$B$8),FALSE())),MAX(IF(IFERROR(AND(W12<>"",Y12<>"",Y12-W12>Resumen!$B$8),FALSE()),Y12-W12,0),IF(IFERROR(AND(X12<>"",Y12<>"",Y12-X12>Resumen!$B$8),FALSE()),Y12-X12,0)),"") | AY12: =IF(OR(IFERROR(AND(W12<>"",Y12<>"",Y12-W12>Resumen!$B$8),FALSE()),IFERROR(AND(X12<>"",Y12<>"",Y12-X12>Resumen!$B$8),FALSE())),TRIM("Lays tiene mayor markup que "&IF(IFERROR(AND(W12<>"",Y12<>"",Y12-W12>Resumen!$B$8),FALSE()),"Quento ","")&IF(IFERROR(AND(X12<>"",Y12<>"",Y12-X12>Resumen!$B$8),FALSE()),"Julicroc ","")&"en este PDV"),"") | AZ12: =IF(COUNTIF('Plan Pehuamar - Lista'!$A$2:$A$167,A12)>0,"Sí","No") -> No | BA12: =IF(COUNTIF('Plan Combo 9+1'!$A$2:$A$226,A12)>0,"Sí","No") -> No | BB12: =IF(AH12="","No",IF(BA12="Sí",IF((AO12-AH12)>Resumen!$B$6,"Sí","No"),IF((AO12-AH12)>=Resumen!$B$132,"Sí","No"))) -> No | BC12: =IF(AND(N12="Sí",AL12="Sí",AI12=0),"Sí","No") -> No | BD12: =IF(COUNTIF('Plan 9+1 (con Pehuamar)'!$A$2:$A$227,A12)>0,"Sí","No") -> No
A13: 400976 | B13: 1 | C13: 101 | D13: Lunes | E13: CABRERA MARIA CRISTINA | F13: Rotiseria | G13: Santa Fe | H13: Conrado Pujol | I13: 20 | J13: 15 | K13: 15 | L13: =I13+J13 -> 35 | M13: =L13+K13 -> 50 | N13: =IF(I13>0,"Sí","No") -> Sí | O13: =IF(J13>0,"Sí","No") -> Sí | P13: =IF(K13>0,"Sí","No") -> Sí | Q13: =IF(OR(I13>0,J13>0),"Sí","No") -> Sí | R13: 1800 | S13: 2800 | T13: 1600 | U13: 2500 | V13: 3700 | W13: =IF(AND(I13>0,R13>0),(S13-R13)/R13,"") -> 0.55555556 | X13: =IF(AND(J13>0,T13>0),(U13-T13)/T13,"") -> 0.5625 | Y13: =IF(AND(K13>0,V13>0),(V13-Resumen!$B$7)/Resumen!$B$7,"") -> 0.48 | Z13: =IF(AND(K13>0,I13>0,V13>0,S13>0),V13-S13,"") -> 900 | AA13: =IF(Z13<>"",Z13/S13,"") -> 0.32142857 | AB13: =IF(AND(K13>0,J13>0,V13>0,U13>0),V13-U13,"") -> 1200 | AC13: =IF(AB13<>"",AB13/U13,"") -> 0.48 | AD13: 4 | AE13: 3 | AF13: 3 | AG13: =AD13+AE13+AF13 -> 10 | AH13: =IF(AG13>0,AD13/AG13,"") -> 0.4 | AI13: 0 | AJ13: 0 | AK13: 0 | AL13: =IF(OR(AJ13>0,AK13>0),"Sí","No") -> No | AM13: Contado | AN13: Contado | AO13: =IF(M13>0,K13/M13,"") -> 0.3 | AP13: =IF(M13>=Resumen!$B$5,"Alto","Bajo") -> Alto | AQ13: =IF(AO13>=Resumen!$B$28,"Alto","Bajo") -> Bajo | AR13: =AP13&" Potencial / "&AQ13&" Share" -> Alto Potencial / Bajo Share | AS13: =IF(Q13="Sí",IF(AO13>=Resumen!$B$29,"Alto","Bajo"),"") -> Bajo | AT13: =IF(AS13<>"",AP13&" Potencial / "&AS13&" Share","") -> Alto Potencial / Bajo Share | AU13: =IF(AH13="","Sin dato",IF(AH13-AO13>Resumen!$B$6,"Sobre-exhibido",IF(AO13-AH13>Resumen!$B$6,"Sub-exhibido","En línea"))) -> Sobre-exhibido | AV13: =IF(AT13="","",IF(AT13="Alto Potencial / Bajo Share",1,IF(AT13="Alto Potencial / Alto Share",2,IF(AT13="Bajo Potencial / Alto Share",3,4)))) -> 1 | AW13: =IF(Q13="No","Sin competencia directa",IF(AV13=1,"1 - Foco Conquista (Alto Pot / Bajo Share)",IF(AV13=2,"2 - Foco Defensa (Alto Pot / Alto Share)",IF(AV13=3,"3 - Monitoreo (Bajo Pot / Alto Share)","4 - Baja Prioridad (Bajo Pot / Bajo Share)")))) -> 1 - Foco Conquista (Alto Pot / Bajo Share) | AX13: =IF(OR(IFERROR(AND(W13<>"",Y13<>"",Y13-W13>Resumen!$B$8),FALSE()),IFERROR(AND(X13<>"",Y13<>"",Y13-X13>Resumen!$B$8),FALSE())),MAX(IF(IFERROR(AND(W13<>"",Y13<>"",Y13-W13>Resumen!$B$8),FALSE()),Y13-W13,0),IF(IFERROR(AND(X13<>"",Y13<>"",Y13-X13>Resumen!$B$8),FALSE()),Y13-X13,0)),"") | AY13: =IF(OR(IFERROR(AND(W13<>"",Y13<>"",Y13-W13>Resumen!$B$8),FALSE()),IFERROR(AND(X13<>"",Y13<>"",Y13-X13>Resumen!$B$8),FALSE())),TRIM("Lays tiene mayor markup que "&IF(IFERROR(AND(W13<>"",Y13<>"",Y13-W13>Resumen!$B$8),FALSE()),"Quento ","")&IF(IFERROR(AND(X13<>"",Y13<>"",Y13-X13>Resumen!$B$8),FALSE()),"Julicroc ","")&"en este PDV"),"") | AZ13: =IF(COUNTIF('Plan Pehuamar - Lista'!$A$2:$A$167,A13)>0,"Sí","No") -> No | BA13: =IF(COUNTIF('Plan Combo 9+1'!$A$2:$A$226,A13)>0,"Sí","No") -> Sí | BB13: =IF(AH13="","No",IF(BA13="Sí",IF((AO13-AH13)>Resumen!$B$6,"Sí","No"),IF((AO13-AH13)>=Resumen!$B$132,"Sí","No"))) -> No | BC13: =IF(AND(N13="Sí",AL13="Sí",AI13=0),"Sí","No") -> No | BD13: =IF(COUNTIF('Plan 9+1 (con Pehuamar)'!$A$2:$A$227,A13)>0,"Sí","No") -> Sí
A14: 400995 | B14: 1 | C14: 101 | D14: Lunes | E14: MAINA GUSTAVO JOSE | F14: Almacen/Despensa | G14: Santa Fe | H14: Conrado Pujol | I14: 40 | J14: 20 | K14: 30 | L14: =I14+J14 -> 60 | M14: =L14+K14 -> 90 | N14: =IF(I14>0,"Sí","No") -> Sí | O14: =IF(J14>0,"Sí","No") -> Sí | P14: =IF(K14>0,"Sí","No") -> Sí | Q14: =IF(OR(I14>0,J14>0),"Sí","No") -> Sí | R14: 1900 | S14: 2700 | T14: 1800 | U14: 2400 | V14: 3600 | W14: =IF(AND(I14>0,R14>0),(S14-R14)/R14,"") -> 0.42105263 | X14: =IF(AND(J14>0,T14>0),(U14-T14)/T14,"") -> 0.33333333 | Y14: =IF(AND(K14>0,V14>0),(V14-Resumen!$B$7)/Resumen!$B$7,"") -> 0.44 | Z14: =IF(AND(K14>0,I14>0,V14>0,S14>0),V14-S14,"") -> 900 | AA14: =IF(Z14<>"",Z14/S14,"") -> 0.33333333 | AB14: =IF(AND(K14>0,J14>0,V14>0,U14>0),V14-U14,"") -> 1200 | AC14: =IF(AB14<>"",AB14/U14,"") -> 0.5 | AD14: 6 | AE14: 5 | AF14: 4 | AG14: =AD14+AE14+AF14 -> 15 | AH14: =IF(AG14>0,AD14/AG14,"") -> 0.4 | AI14: 0 | AJ14: 0 | AK14: 0 | AL14: =IF(OR(AJ14>0,AK14>0),"Sí","No") -> No | AM14: Contado | AN14: Contado | AO14: =IF(M14>0,K14/M14,"") -> 0.33333333 | AP14: =IF(M14>=Resumen!$B$5,"Alto","Bajo") -> Alto | AQ14: =IF(AO14>=Resumen!$B$28,"Alto","Bajo") -> Bajo | AR14: =AP14&" Potencial / "&AQ14&" Share" -> Alto Potencial / Bajo Share | AS14: =IF(Q14="Sí",IF(AO14>=Resumen!$B$29,"Alto","Bajo"),"") -> Bajo | AT14: =IF(AS14<>"",AP14&" Potencial / "&AS14&" Share","") -> Alto Potencial / Bajo Share | AU14: =IF(AH14="","Sin dato",IF(AH14-AO14>Resumen!$B$6,"Sobre-exhibido",IF(AO14-AH14>Resumen!$B$6,"Sub-exhibido","En línea"))) -> Sobre-exhibido | AV14: =IF(AT14="","",IF(AT14="Alto Potencial / Bajo Share",1,IF(AT14="Alto Potencial / Alto Share",2,IF(AT14="Bajo Potencial / Alto Share",3,4)))) -> 1 | AW14: =IF(Q14="No","Sin competencia directa",IF(AV14=1,"1 - Foco Conquista (Alto Pot / Bajo Share)",IF(AV14=2,"2 - Foco Defensa (Alto Pot / Alto Share)",IF(AV14=3,"3 - Monitoreo (Bajo Pot / Alto Share)","4 - Baja Prioridad (Bajo Pot / Bajo Share)")))) -> 1 - Foco Conquista (Alto Pot / Bajo Share) | AX14: =IF(OR(IFERROR(AND(W14<>"",Y14<>"",Y14-W14>Resumen!$B$8),FALSE()),IFERROR(AND(X14<>"",Y14<>"",Y14-X14>Resumen!$B$8),FALSE())),MAX(IF(IFERROR(AND(W14<>"",Y14<>"",Y14-W14>Resumen!$B$8),FALSE()),Y14-W14,0),IF(IFERROR(AND(X14<>"",Y14<>"",Y14-X14>Resumen!$B$8),FALSE()),Y14-X14,0)),"") -> 0.10666667 | AY14: =IF(OR(IFERROR(AND(W14<>"",Y14<>"",Y14-W14>Resumen!$B$8),FALSE()),IFERROR(AND(X14<>"",Y14<>"",Y14-X14>Resumen!$B$8),FALSE())),TRIM("Lays tiene mayor markup que "&IF(IFERROR(AND(W14<>"",Y14<>"",Y14-W14>Resumen!$B$8),FALSE()),"Quento ","")&IF(IFERROR(AND(X14<>"",Y14<>"",Y14-X14>Resumen!$B$8),FALSE()),"Julicroc ","")&"en este PDV"),"") -> Lays tiene mayor markup que Julicroc en este PDV | AZ14: =IF(COUNTIF('Plan Pehuamar - Lista'!$A$2:$A$167,A14)>0,"Sí","No") -> Sí | BA14: =IF(COUNTIF('Plan Combo 9+1'!$A$2:$A$226,A14)>0,"Sí","No") -> No | BB14: =IF(AH14="","No",IF(BA14="Sí",IF((AO14-AH14)>Resumen!$B$6,"Sí","No"),IF((AO14-AH14)>=Resumen!$B$132,"Sí","No"))) -> No | BC14: =IF(AND(N14="Sí",AL14="Sí",AI14=0),"Sí","No") -> No | BD14: =IF(COUNTIF('Plan 9+1 (con Pehuamar)'!$A$2:$A$227,A14)>0,"Sí","No") -> Sí
A15: 400996 | B15: 1 | C15: 101 | D15: Lunes | E15: MERILES ANDREA SOLEDAD | F15: Autoservicio Tradicional | G15: Santa Fe | H15: Conrado Pujol | I15: 15 | J15: 20 | K15: 30 | L15: =I15+J15 -> 35 | M15: =L15+K15 -> 65 | N15: =IF(I15>0,"Sí","No") -> Sí | O15: =IF(J15>0,"Sí","No") -> Sí | P15: =IF(K15>0,"Sí","No") -> Sí | Q15: =IF(OR(I15>0,J15>0),"Sí","No") -> Sí | R15: 1800 | S15: 2900 | T15: 1600 | U15: 2600 | V15: 3700 | W15: =IF(AND(I15>0,R15>0),(S15-R15)/R15,"") -> 0.61111111 | X15: =IF(AND(J15>0,T15>0),(U15-T15)/T15,"") -> 0.625 | Y15: =IF(AND(K15>0,V15>0),(V15-Resumen!$B$7)/Resumen!$B$7,"") -> 0.48 | Z15: =IF(AND(K15>0,I15>0,V15>0,S15>0),V15-S15,"") -> 800 | AA15: =IF(Z15<>"",Z15/S15,"") -> 0.27586207 | AB15: =IF(AND(K15>0,J15>0,V15>0,U15>0),V15-U15,"") -> 1100 | AC15: =IF(AB15<>"",AB15/U15,"") -> 0.42307692 | AD15: 5 | AE15: 3 | AF15: 3 | AG15: =AD15+AE15+AF15 -> 11 | AH15: =IF(AG15>0,AD15/AG15,"") -> 0.45454545 | AI15: 1 | AJ15: 0 | AK15: 0 | AL15: =IF(OR(AJ15>0,AK15>0),"Sí","No") -> No | AM15: Contado | AN15: Contado | AO15: =IF(M15>0,K15/M15,"") -> 0.46153846 | AP15: =IF(M15>=Resumen!$B$5,"Alto","Bajo") -> Alto | AQ15: =IF(AO15>=Resumen!$B$28,"Alto","Bajo") -> Alto | AR15: =AP15&" Potencial / "&AQ15&" Share" -> Alto Potencial / Alto Share | AS15: =IF(Q15="Sí",IF(AO15>=Resumen!$B$29,"Alto","Bajo"),"") -> Bajo | AT15: =IF(AS15<>"",AP15&" Potencial / "&AS15&" Share","") -> Alto Potencial / Bajo Share | AU15: =IF(AH15="","Sin dato",IF(AH15-AO15>Resumen!$B$6,"Sobre-exhibido",IF(AO15-AH15>Resumen!$B$6,"Sub-exhibido","En línea"))) -> En línea | AV15: =IF(AT15="","",IF(AT15="Alto Potencial / Bajo Share",1,IF(AT15="Alto Potencial / Alto Share",2,IF(AT15="Bajo Potencial / Alto Share",3,4)))) -> 1 | AW15: =IF(Q15="No","Sin competencia directa",IF(AV15=1,"1 - Foco Conquista (Alto Pot / Bajo Share)",IF(AV15=2,"2 - Foco Defensa (Alto Pot / Alto Share)",IF(AV15=3,"3 - Monitoreo (Bajo Pot / Alto Share)","4 - Baja Prioridad (Bajo Pot / Bajo Share)")))) -> 1 - Foco Conquista (Alto Pot / Bajo Share) | AX15: =IF(OR(IFERROR(AND(W15<>"",Y15<>"",Y15-W15>Resumen!$B$8),FALSE()),IFERROR(AND(X15<>"",Y15<>"",Y15-X15>Resumen!$B$8),FALSE())),MAX(IF(IFERROR(AND(W15<>"",Y15<>"",Y15-W15>Resumen!$B$8),FALSE()),Y15-W15,0),IF(IFERROR(AND(X15<>"",Y15<>"",Y15-X15>Resumen!$B$8),FALSE()),Y15-X15,0)),"") | AY15: =IF(OR(IFERROR(AND(W15<>"",Y15<>"",Y15-W15>Resumen!$B$8),FALSE()),IFERROR(AND(X15<>"",Y15<>"",Y15-X15>Resumen!$B$8),FALSE())),TRIM("Lays tiene mayor markup que "&IF(IFERROR(AND(W15<>"",Y15<>"",Y15-W15>Resumen!$B$8),FALSE()),"Quento ","")&IF(IFERROR(AND(X15<>"",Y15<>"",Y15-X15>Resumen!$B$8),FALSE()),"Julicroc ","")&"en este PDV"),"") | AZ15: =IF(COUNTIF('Plan Pehuamar - Lista'!$A$2:$A$167,A15)>0,"Sí","No") -> No | BA15: =IF(COUNTIF('Plan Combo 9+1'!$A$2:$A$226,A15)>0,"Sí","No") -> No | BB15: =IF(AH15="","No",IF(BA15="Sí",IF((AO15-AH15)>Resumen!$B$6,"Sí","No"),IF((AO15-AH15)>=Resumen!$B$132,"Sí","No"))) -> No | BC15: =IF(AND(N15="Sí",AL15="Sí",AI15=0),"Sí","No") -> No | BD15: =IF(COUNTIF('Plan 9+1 (con Pehuamar)'!$A$2:$A$227,A15)>0,"Sí","No") -> No
A16: 401002 | B16: 1 | C16: 101 | D16: Lunes | E16: GAMBOA FERNANDO RUBEN | F16: Rotiseria | G16: Santa Fe | H16: Conrado Pujol | I16: 20 | J16: 0 | K16: 20 | L16: =I16+J16 -> 20 | M16: =L16+K16 -> 40 | N16: =IF(I16>0,"Sí","No") -> Sí | O16: =IF(J16>0,"Sí","No") -> No | P16: =IF(K16>0,"Sí","No") -> Sí | Q16: =IF(OR(I16>0,J16>0),"Sí","No") -> Sí | R16: 1800 | S16: 3000 | V16: 3500 | W16: =IF(AND(I16>0,R16>0),(S16-R16)/R16,"") -> 0.66666667 | X16: =IF(AND(J16>0,T16>0),(U16-T16)/T16,"") | Y16: =IF(AND(K16>0,V16>0),(V16-Resumen!$B$7)/Resumen!$B$7,"") -> 0.4 | Z16: =IF(AND(K16>0,I16>0,V16>0,S16>0),V16-S16,"") -> 500 | AA16: =IF(Z16<>"",Z16/S16,"") -> 0.16666667 | AB16: =IF(AND(K16>0,J16>0,V16>0,U16>0),V16-U16,"") | AC16: =IF(AB16<>"",AB16/U16,"") | AD16: 5 | AE16: 4 | AF16: 0 | AG16: =AD16+AE16+AF16 -> 9 | AH16: =IF(AG16>0,AD16/AG16,"") -> 0.55555556 | AI16: 1 | AJ16: 0 | AK16: 0 | AL16: =IF(OR(AJ16>0,AK16>0),"Sí","No") -> No | AM16: Contado | AO16: =IF(M16>0,K16/M16,"") -> 0.5 | AP16: =IF(M16>=Resumen!$B$5,"Alto","Bajo") -> Alto | AQ16: =IF(AO16>=Resumen!$B$28,"Alto","Bajo") -> Alto | AR16: =AP16&" Potencial / "&AQ16&" Share" -> Alto Potencial / Alto Share | AS16: =IF(Q16="Sí",IF(AO16>=Resumen!$B$29,"Alto","Bajo"),"") -> Alto | AT16: =IF(AS16<>"",AP16&" Potencial / "&AS16&" Share","") -> Alto Potencial / Alto Share | AU16: =IF(AH16="","Sin dato",IF(AH16-AO16>Resumen!$B$6,"Sobre-exhibido",IF(AO16-AH16>Resumen!$B$6,"Sub-exhibido","En línea"))) -> Sobre-exhibido | AV16: =IF(AT16="","",IF(AT16="Alto Potencial / Bajo Share",1,IF(AT16="Alto Potencial / Alto Share",2,IF(AT16="Bajo Potencial / Alto Share",3,4)))) -> 2 | AW16: =IF(Q16="No","Sin competencia directa",IF(AV16=1,"1 - Foco Conquista (Alto Pot / Bajo Share)",IF(AV16=2,"2 - Foco Defensa (Alto Pot / Alto Share)",IF(AV16=3,"3 - Monitoreo (Bajo Pot / Alto Share)","4 - Baja Prioridad (Bajo Pot / Bajo Share)")))) -> 2 - Foco Defensa (Alto Pot / Alto Share) | AX16: =IF(OR(IFERROR(AND(W16<>"",Y16<>"",Y16-W16>Resumen!$B$8),FALSE()),IFERROR(AND(X16<>"",Y16<>"",Y16-X16>Resumen!$B$8),FALSE())),MAX(IF(IFERROR(AND(W16<>"",Y16<>"",Y16-W16>Resumen!$B$8),FALSE()),Y16-W16,0),IF(IFERROR(AND(X16<>"",Y16<>"",Y16-X16>Resumen!$B$8),FALSE()),Y16-X16,0)),"") | AY16: =IF(OR(IFERROR(AND(W16<>"",Y16<>"",Y16-W16>Resumen!$B$8),FALSE()),IFERROR(AND(X16<>"",Y16<>"",Y16-X16>Resumen!$B$8),FALSE())),TRIM("Lays tiene mayor markup que "&IF(IFERROR(AND(W16<>"",Y16<>"",Y16-W16>Resumen!$B$8),FALSE()),"Quento ","")&IF(IFERROR(AND(X16<>"",Y16<>"",Y16-X16>Resumen!$B$8),FALSE()),"Julicroc ","")&"en este PDV"),"") | AZ16: =IF(COUNTIF('Plan Pehuamar - Lista'!$A$2:$A$167,A16)>0,"Sí","No") -> No | BA16: =IF(COUNTIF('Plan Combo 9+1'!$A$2:$A$226,A16)>0,"Sí","No") -> No | BB16: =IF(AH16="","No",IF(BA16="Sí",IF((AO16-AH16)>Resumen!$B$6,"Sí","No"),IF((AO16-AH16)>=Resumen!$B$132,"Sí","No"))) -> No | BC16: =IF(AND(N16="Sí",AL16="Sí",AI16=0),"Sí","No") -> No | BD16: =IF(COUNTIF('Plan 9+1 (con Pehuamar)'!$A$2:$A$227,A16)>0,"Sí","No") -> No
A17: 401003 | B17: 1 | C17: 101 | D17: Lunes | E17: VILLANUEVA ALBERTO LUIS EDUARD | F17: Almacen/Despensa | G17: Santa Fe | H17: Conrado Pujol | I17: 0 | J17: 0 | K17: 0.4 | L17: =I17+J17 -> 0 | M17: =L17+K17 -> 0.4 | N17: =IF(I17>0,"Sí","No") -> No | O17: =IF(J17>0,"Sí","No") -> No | P17: =IF(K17>0,"Sí","No") -> Sí | Q17: =IF(OR(I17>0,J17>0),"Sí","No") -> No | W17: =IF(AND(I17>0,R17>0),(S17-R17)/R17,"") | X17: =IF(AND(J17>0,T17>0),(U17-T17)/T17,"") | Y17: =IF(AND(K17>0,V17>0),(V17-Resumen!$B$7)/Resumen!$B$7,"") | Z17: =IF(AND(K17>0,I17>0,V17>0,S17>0),V17-S17,"") | AA17: =IF(Z17<>"",Z17/S17,"") | AB17: =IF(AND(K17>0,J17>0,V17>0,U17>0),V17-U17,"") | AC17: =IF(AB17<>"",AB17/U17,"") | AD17: 0 | AE17: 0 | AF17: 0 | AG17: =AD17+AE17+AF17 -> 0 | AH17: =IF(AG17>0,AD17/AG17,"") | AI17: 0 | AJ17: 0 | AK17: 0 | AL17: =IF(OR(AJ17>0,AK17>0),"Sí","No") -> No | AO17: =IF(M17>0,K17/M17,"") -> 1 | AP17: =IF(M17>=Resumen!$B$5,"Alto","Bajo") -> Bajo | AQ17: =IF(AO17>=Resumen!$B$28,"Alto","Bajo") -> Alto | AR17: =AP17&" Potencial / "&AQ17&" Share" -> Bajo Potencial / Alto Share | AS17: =IF(Q17="Sí",IF(AO17>=Resumen!$B$29,"Alto","Bajo"),"") | AT17: =IF(AS17<>"",AP17&" Potencial / "&AS17&" Share","") | AU17: =IF(AH17="","Sin dato",IF(AH17-AO17>Resumen!$B$6,"Sobre-exhibido",IF(AO17-AH17>Resumen!$B$6,"Sub-exhibido","En línea"))) -> Sin dato | AV17: =IF(AT17="","",IF(AT17="Alto Potencial / Bajo Share",1,IF(AT17="Alto Potencial / Alto Share",2,IF(AT17="Bajo Potencial / Alto Share",3,4)))) | AW17: =IF(Q17="No","Sin competencia directa",IF(AV17=1,"1 - Foco Conquista (Alto Pot / Bajo Share)",IF(AV17=2,"2 - Foco Defensa (Alto Pot / Alto Share)",IF(AV17=3,"3 - Monitoreo (Bajo Pot / Alto Share)","4 - Baja Prioridad (Bajo Pot / Bajo Share)")))) -> Sin competencia directa | AX17: =IF(OR(IFERROR(AND(W17<>"",Y17<>"",Y17-W17>Resumen!$B$8),FALSE()),IFERROR(AND(X17<>"",Y17<>"",Y17-X17>Resumen!$B$8),FALSE())),MAX(IF(IFERROR(AND(W17<>"",Y17<>"",Y17-W17>Resumen!$B$8),FALSE()),Y17-W17,0),IF(IFERROR(AND(X17<>"",Y17<>"",Y17-X17>Resumen!$B$8),FALSE()),Y17-X17,0)),"") | AY17: =IF(OR(IFERROR(AND(W17<>"",Y17<>"",Y17-W17>Resumen!$B$8),FALSE()),IFERROR(AND(X17<>"",Y17<>"",Y17-X17>Resumen!$B$8),FALSE())),TRIM("Lays tiene mayor markup que "&IF(IFERROR(AND(W17<>"",Y17<>"",Y17-W17>Resumen!$B$8),FALSE()),"Quento ","")&IF(IFERROR(AND(X17<>"",Y17<>"",Y17-X17>Resumen!$B$8),FALSE()),"Julicroc ","")&"en este PDV"),"") | AZ17: =IF(COUNTIF('Plan Pehuamar - Lista'!$A$2:$A$167,A17)>0,"Sí","No") -> No | BA17: =IF(COUNTIF('Plan Combo 9+1'!$A$2:$A$226,A17)>0,"Sí","No") -> No | BB17: =IF(AH17="","No",IF(BA17="Sí",IF((AO17-AH17)>Resumen!$B$6,"Sí","No"),IF((AO17-AH17)>=Resumen!$B$132,"Sí","No"))) -> No | BC17: =IF(AND(N17="Sí",AL17="Sí",AI17=0),"Sí","No") -> No | BD17: =IF(COUNTIF('Plan 9+1 (con Pehuamar)'!$A$2:$A$227,A17)>0,"Sí","No") -> No
A18: 401004 | B18: 1 | C18: 101 | D18: Lunes | E18: YOSSEN ARIEL EDGARDO | F18: Almacen/Despensa | G18: Santa Fe | H18: Conrado Pujol | I18: 0 | J18: 0 | K18: 0.7 | L18: =I18+J18 -> 0 | M18: =L18+K18 -> 0.7 | N18: =IF(I18>0,"Sí","No") -> No | O18: =IF(J18>0,"Sí","No") -> No | P18: =IF(K18>0,"Sí","No") -> Sí | Q18: =IF(OR(I18>0,J18>0),"Sí","No") -> No | W18: =IF(AND(I18>0,R18>0),(S18-R18)/R18,"") | X18: =IF(AND(J18>0,T18>0),(U18-T18)/T18,"") | Y18: =IF(AND(K18>0,V18>0),(V18-Resumen!$B$7)/Resumen!$B$7,"") | Z18: =IF(AND(K18>0,I18>0,V18>0,S18>0),V18-S18,"") | AA18: =IF(Z18<>"",Z18/S18,"") | AB18: =IF(AND(K18>0,J18>0,V18>0,U18>0),V18-U18,"") | AC18: =IF(AB18<>"",AB18/U18,"") | AD18: 0 | AE18: 0 | AF18: 0 | AG18: =AD18+AE18+AF18 -> 0 | AH18: =IF(AG18>0,AD18/AG18,"") | AI18: 0 | AJ18: 0 | AK18: 0 | AL18: =IF(OR(AJ18>0,AK18>0),"Sí","No") -> No | AO18: =IF(M18>0,K18/M18,"") -> 1 | AP18: =IF(M18>=Resumen!$B$5,"Alto","Bajo") -> Bajo | AQ18: =IF(AO18>=Resumen!$B$28,"Alto","Bajo") -> Alto | AR18: =AP18&" Potencial / "&AQ18&" Share" -> Bajo Potencial / Alto Share | AS18: =IF(Q18="Sí",IF(AO18>=Resumen!$B$29,"Alto","Bajo"),"") | AT18: =IF(AS18<>"",AP18&" Potencial / "&AS18&" Share","") | AU18: =IF(AH18="","Sin dato",IF(AH18-AO18>Resumen!$B$6,"Sobre-exhibido",IF(AO18-AH18>Resumen!$B$6,"Sub-exhibido","En línea"))) -> Sin dato | AV18: =IF(AT18="","",IF(AT18="Alto Potencial / Bajo Share",1,IF(AT18="Alto Potencial / Alto Share",2,IF(AT18="Bajo Potencial / Alto Share",3,4)))) | AW18: =IF(Q18="No","Sin competencia directa",IF(AV18=1,"1 - Foco Conquista (Alto Pot / Bajo Share)",IF(AV18=2,"2 - Foco Defensa (Alto Pot / Alto Share)",IF(AV18=3,"3 - Monitoreo (Bajo Pot / Alto Share)","4 - Baja Prioridad (Bajo Pot / Bajo Share)")))) -> Sin competencia directa | AX18: =IF(OR(IFERROR(AND(W18<>"",Y18<>"",Y18-W18>Resumen!$B$8),FALSE()),IFERROR(AND(X18<>"",Y18<>"",Y18-X18>Resumen!$B$8),FALSE())),MAX(IF(IFERROR(AND(W18<>"",Y18<>"",Y18-W18>Resumen!$B$8),FALSE()),Y18-W18,0),IF(IFERROR(AND(X18<>"",Y18<>"",Y18-X18>Resumen!$B$8),FALSE()),Y18-X18,0)),"") | AY18: =IF(OR(IFERROR(AND(W18<>"",Y18<>"",Y18-W18>Resumen!$B$8),FALSE()),IFERROR(AND(X18<>"",Y18<>"",Y18-X18>Resumen!$B$8),FALSE())),TRIM("Lays tiene mayor markup que "&IF(IFERROR(AND(W18<>"",Y18<>"",Y18-W18>Resumen!$B$8),FALSE()),"Quento ","")&IF(IFERROR(AND(X18<>"",Y18<>"",Y18-X18>Resumen!$B$8),FALSE()),"Julicroc ","")&"en este PDV"),"") | AZ18: =IF(COUNTIF('Plan Pehuamar - Lista'!$A$2:$A$167,A18)>0,"Sí","No") -> No | BA18: =IF(COUNTIF('Plan Combo 9+1'!$A$2:$A$226,A18)>0,"Sí","No") -> No | BB18: =IF(AH18="","No",IF(BA18="Sí",IF((AO18-AH18)>Resumen!$B$6,"Sí","No"),IF((AO18-AH18)>=Resumen!$B$132,"Sí","No"))) -> No | BC18: =IF(AND(N18="Sí",AL18="Sí",AI18=0),"Sí","No") -> No | BD18: =IF(COUNTIF('Plan 9+1 (con Pehuamar)'!$A$2:$A$227,A18)>0,"Sí","No") -> No
A19: 401010 | B19: 1 | C19: 101 | D19: Lunes | E19: SEDRAN SANTOS FABIAN | F19: Panaderia | G19: Santa Fe | H19: Conrado Pujol | I19: 0 | J19: 0 | K19: 0.5 | L19: =I19+J19 -> 0 | M19: =L19+K19 -> 0.5 | N19: =IF(I19>0,"Sí","No") -> No | O19: =IF(J19>0,"Sí","No") -> No | P19: =IF(K19>0,"Sí","No") -> Sí | Q19: =IF(OR(I19>0,J19>0),"Sí","No") -> No | W19: =IF(AND(I19>0,R19>0),(S19-R19)/R19,"") | X19: =IF(AND(J19>0,T19>0),(U19-T19)/T19,"") | Y19: =IF(AND(K19>0,V19>0),(V19-Resumen!$B$7)/Resumen!$B$7,"") | Z19: =IF(AND(K19>0,I19>0,V19>0,S19>0),V19-S19,"") | AA19: =IF(Z19<>"",Z19/S19,"") | AB19: =IF(AND(K19>0,J19>0,V19>0,U19>0),V19-U19,"") | AC19: =IF(AB19<>"",AB19/U19,"") | AD19: 0 | AE19: 0 | AF19: 0 | AG19: =AD19+AE19+AF19 -> 0 | AH19: =IF(AG19>0,AD19/AG19,"") | AI19: 0 | AJ19: 0 | AK19: 0 | AL19: =IF(OR(AJ19>0,AK19>0),"Sí","No") -> No | AO19: =IF(M19>0,K19/M19,"") -> 1 | AP19: =IF(M19>=Resumen!$B$5,"Alto","Bajo") -> Bajo | AQ19: =IF(AO19>=Resumen!$B$28,"Alto","Bajo") -> Alto | AR19: =AP19&" Potencial / "&AQ19&" Share" -> Bajo Potencial / Alto Share | AS19: =IF(Q19="Sí",IF(AO19>=Resumen!$B$29,"Alto","Bajo"),"") | AT19: =IF(AS19<>"",AP19&" Potencial / "&AS19&" Share","") | AU19: =IF(AH19="","Sin dato",IF(AH19-AO19>Resumen!$B$6,"Sobre-exhibido",IF(AO19-AH19>Resumen!$B$6,"Sub-exhibido","En línea"))) -> Sin dato | AV19: =IF(AT19="","",IF(AT19="Alto Potencial / Bajo Share",1,IF(AT19="Alto Potencial / Alto Share",2,IF(AT19="Bajo Potencial / Alto Share",3,4)))) | AW19: =IF(Q19="No","Sin competencia directa",IF(AV19=1,"1 - Foco Conquista (Alto Pot / Bajo Share)",IF(AV19=2,"2 - Foco Defensa (Alto Pot / Alto Share)",IF(AV19=3,"3 - Monitoreo (Bajo Pot / Alto Share)","4 - Baja Prioridad (Bajo Pot / Bajo Share)")))) -> Sin competencia directa | AX19: =IF(OR(IFERROR(AND(W19<>"",Y19<>"",Y19-W19>Resumen!$B$8),FALSE()),IFERROR(AND(X19<>"",Y19<>"",Y19-X19>Resumen!$B$8),FALSE())),MAX(IF(IFERROR(AND(W19<>"",Y19<>"",Y19-W19>Resumen!$B$8),FALSE()),Y19-W19,0),IF(IFERROR(AND(X19<>"",Y19<>"",Y19-X19>Resumen!$B$8),FALSE()),Y19-X19,0)),"") | AY19: =IF(OR(IFERROR(AND(W19<>"",Y19<>"",Y19-W19>Resumen!$B$8),FALSE()),IFERROR(AND(X19<>"",Y19<>"",Y19-X19>Resumen!$B$8),FALSE())),TRIM("Lays tiene mayor markup que "&IF(IFERROR(AND(W19<>"",Y19<>"",Y19-W19>Resumen!$B$8),FALSE()),"Quento ","")&IF(IFERROR(AND(X19<>"",Y19<>"",Y19-X19>Resumen!$B$8),FALSE()),"Julicroc ","")&"en este PDV"),"") | AZ19: =IF(COUNTIF('Plan Pehuamar - Lista'!$A$2:$A$167,A19)>0,"Sí","No") -> No | BA19: =IF(COUNTIF('Plan Combo 9+1'!$A$2:$A$226,A19)>0,"Sí","No") -> No | BB19: =IF(AH19="","No",IF(BA19="Sí",IF((AO19-AH19)>Resumen!$B$6,"Sí","No"),IF((AO19-AH19)>=Resumen!$B$132,"Sí","No"))) -> No | BC19: =IF(AND(N19="Sí",AL19="Sí",AI19=0),"Sí","No") -> No | BD19: =IF(COUNTIF('Plan 9+1 (con Pehuamar)'!$A$2:$A$227,A19)>0,"Sí","No") -> No
A20: 401534 | B20: 1 | C20: 101 | D20: Lunes | E20: MARIA CRISTINA GOMEZ | F20: Rotiseria | G20: Santa Fe | H20: Conrado Pujol | I20: 0 | J20: 0 | K20: 3.2 | L20: =I20+J20 -> 0 | M20: =L20+K20 -> 3.2 | N20: =IF(I20>0,"Sí","No") -> No | O20: =IF(J20>0,"Sí","No") -> No | P20: =IF(K20>0,"Sí","No") -> Sí | Q20: =IF(OR(I20>0,J20>0),"Sí","No") -> No | W20: =IF(AND(I20>0,R20>0),(S20-R20)/R20,"") | X20: =IF(AND(J20>0,T20>0),(U20-T20)/T20,"") | Y20: =IF(AND(K20>0,V20>0),(V20-Resumen!$B$7)/Resumen!$B$7,"") | Z20: =IF(AND(K20>0,I20>0,V20>0,S20>0),V20-S20,"") | AA20: =IF(Z20<>"",Z20/S20,"") | AB20: =IF(AND(K20>0,J20>0,V20>0,U20>0),V20-U20,"") | AC20: =IF(AB20<>"",AB20/U20,"") | AD20: 0 | AE20: 0 | AF20: 0 | AG20: =AD20+AE20+AF20 -> 0 | AH20: =IF(AG20>0,AD20/AG20,"") | AI20: 0 | AJ20: 0 | AK20: 0 | AL20: =IF(OR(AJ20>0,AK20>0),"Sí","No") -> No | AO20: =IF(M20>0,K20/M20,"") -> 1 | AP20: =IF(M20>=Resumen!$B$5,"Alto","Bajo") -> Bajo | AQ20: =IF(AO20>=Resumen!$B$28,"Alto","Bajo") -> Alto | AR20: =AP20&" Potencial / "&AQ20&" Share" -> Bajo Potencial / Alto Share | AS20: =IF(Q20="Sí",IF(AO20>=Resumen!$B$29,"Alto","Bajo"),"") | AT20: =IF(AS20<>"",AP20&" Potencial / "&AS20&" Share","") | AU20: =IF(AH20="","Sin dato",IF(AH20-AO20>Resumen!$B$6,"Sobre-exhibido",IF(AO20-AH20>Resumen!$B$6,"Sub-exhibido","En línea"))) -> Sin dato | AV20: =IF(AT20="","",IF(AT20="Alto Potencial / Bajo Share",1,IF(AT20="Alto Potencial / Alto Share",2,IF(AT20="Bajo Potencial / Alto Share",3,4)))) | AW20: =IF(Q20="No","Sin competencia directa",IF(AV20=1,"1 - Foco Conquista (Alto Pot / Bajo Share)",IF(AV20=2,"2 - Foco Defensa (Alto Pot / Alto Share)",IF(AV20=3,"3 - Monitoreo (Bajo Pot / Alto Share)","4 - Baja Prioridad (Bajo Pot / Bajo Share)")))) -> Sin competencia directa | AX20: =IF(OR(IFERROR(AND(W20<>"",Y20<>"",Y20-W20>Resumen!$B$8),FALSE()),IFERROR(AND(X20<>"",Y20<>"",Y20-X20>Resumen!$B$8),FALSE())),MAX(IF(IFERROR(AND(W20<>"",Y20<>"",Y20-W20>Resumen!$B$8),FALSE()),Y20-W20,0),IF(IFERROR(AND(X20<>"",Y20<>"",Y20-X20>Resumen!$B$8),FALSE()),Y20-X20,0)),"") | AY20: =IF(OR(IFERROR(AND(W20<>"",Y20<>"",Y20-W20>Resumen!$B$8),FALSE()),IFERROR(AND(X20<>"",Y20<>"",Y20-X20>Resumen!$B$8),FALSE())),TRIM("Lays tiene mayor markup que "&IF(IFERROR(AND(W20<>"",Y20<>"",Y20-W20>Resumen!$B$8),FALSE()),"Quento ","")&IF(IFERROR(AND(X20<>"",Y20<>"",Y20-X20>Resumen!$B$8),FALSE()),"Julicroc ","")&"en este PDV"),"") | AZ20: =IF(COUNTIF('Plan Pehuamar - Lista'!$A$2:$A$167,A20)>0,"Sí","No") -> No | BA20: =IF(COUNTIF('Plan Combo 9+1'!$A$2:$A$226,A20)>0,"Sí","No") -> No | BB20: =IF(AH20="","No",IF(BA20="Sí",IF((AO20-AH20)>Resumen!$B$6,"Sí","No"),IF((AO20-AH20)>=Resumen!$B$132,"Sí","No"))) -> No | BC20: =IF(AND(N20="Sí",AL20="Sí",AI20=0),"Sí","No") -> No | BD20: =IF(COUNTIF('Plan 9+1 (con Pehuamar)'!$A$2:$A$227,A20)>0,"Sí","No") -> No
A21: 401560 | B21: 1 | C21: 101 | D21: Lunes | E21: CAÑETE MONICA | F21: Almacen/Despensa | G21: Santa Fe | H21: Conrado Pujol | I21: 15 | J21: 20 | K21: 10 | L21: =I21+J21 -> 35 | M21: =L21+K21 -> 45 | N21: =IF(I21>0,"Sí","No") -> Sí | O21: =IF(J21>0,"Sí","No") -> Sí | P21: =IF(K21>0,"Sí","No") -> Sí | Q21: =IF(OR(I21>0,J21>0),"Sí","No") -> Sí | R21: 1800 | S21: 2900 | T21: 1700 | U21: 2500 | V21: 3500 | W21: =IF(AND(I21>0,R21>0),(S21-R21)/R21,"") -> 0.61111111 | X21: =IF(AND(J21>0,T21>0),(U21-T21)/T21,"") -> 0.47058824 | Y21: =IF(AND(K21>0,V21>0),(V21-Resumen!$B$7)/Resumen!$B$7,"") -> 0.4 | Z21: =IF(AND(K21>0,I21>0,V21>0,S21>0),V21-S21,"") -> 600 | AA21: =IF(Z21<>"",Z21/S21,"") -> 0.20689655 | AB21: =IF(AND(K21>0,J21>0,V21>0,U21>0),V21-U21,"") -> 1000 | AC21: =IF(AB21<>"",AB21/U21,"") -> 0.4 | AD21: 4 | AE21: 4 | AF21: 4 | AG21: =AD21+AE21+AF21 -> 12 | AH21: =IF(AG21>0,AD21/AG21,"") -> 0.33333333 | AI21: 0 | AJ21: 0 | AK21: 0 | AL21: =IF(OR(AJ21>0,AK21>0),"Sí","No") -> No | AM21: Contado | AN21: Contado | AO21: =IF(M21>0,K21/M21,"") -> 0.22222222 | AP21: =IF(M21>=Resumen!$B$5,"Alto","Bajo") -> Alto | AQ21: =IF(AO21>=Resumen!$B$28,"Alto","Bajo") -> Bajo | AR21: =AP21&" Potencial / "&AQ21&" Share" -> Alto Potencial / Bajo Share | AS21: =IF(Q21="Sí",IF(AO21>=Resumen!$B$29,"Alto","Bajo"),"") -> Bajo | AT21: =IF(AS21<>"",AP21&" Potencial / "&AS21&" Share","") -> Alto Potencial / Bajo Share | AU21: =IF(AH21="","Sin dato",IF(AH21-AO21>Resumen!$B$6,"Sobre-exhibido",IF(AO21-AH21>Resumen!$B$6,"Sub-exhibido","En línea"))) -> Sobre-exhibido | AV21: =IF(AT21="","",IF(AT21="Alto Potencial / Bajo Share",1,IF(AT21="Alto Potencial / Alto Share",2,IF(AT21="Bajo Potencial / Alto Share",3,4)))) -> 1 | AW21: =IF(Q21="No","Sin competencia directa",IF(AV21=1,"1 - Foco Conquista (Alto Pot / Bajo Share)",IF(AV21=2,"2 - Foco Defensa (Alto Pot / Alto Share)",IF(AV21=3,"3 - Monitoreo (Bajo Pot / Alto Share)","4 - Baja Prioridad (Bajo Pot / Bajo Share)")))) -> 1 - Foco Conquista (Alto Pot / Bajo Share) | AX21: =IF(OR(IFERROR(AND(W21<>"",Y21<>"",Y21-W21>Resumen!$B$8),FALSE()),IFERROR(AND(X21<>"",Y21<>"",Y21-X21>Resumen!$B$8),FALSE())),MAX(IF(IFERROR(AND(W21<>"",Y21<>"",Y21-W21>Resumen!$B$8),FALSE()),Y21-W21,0),IF(IFERROR(AND(X21<>"",Y21<>"",Y21-X21>Resumen!$B$8),FALSE()),Y21-X21,0)),"") | AY21: =IF(OR(IFERROR(AND(W21<>"",Y21<>"",Y21-W21>Resumen!$B$8),FALSE()),IFERROR(AND(X21<>"",Y21<>"",Y21-X21>Resumen!$B$8),FALSE())),TRIM("Lays tiene mayor markup que "&IF(IFERROR(AND(W21<>"",Y21<>"",Y21-W21>Resumen!$B$8),FALSE()),"Quento ","")&IF(IFERROR(AND(X21<>"",Y21<>"",Y21-X21>Resumen!$B$8),FALSE()),"Julicroc ","")&"en este PDV"),"") | AZ21: =IF(COUNTIF('Plan Pehuamar - Lista'!$A$2:$A$167,A21)>0,"Sí","No") -> No | BA21: =IF(COUNTIF('Plan Combo 9+1'!$A$2:$A$226,A21)>0,"Sí","No") -> Sí | BB21: =IF(AH21="","No",IF(BA21="Sí",IF((AO21-AH21)>Resumen!$B$6,"Sí","No"),IF((AO21-AH21)>=Resumen!$B$132,"Sí","No"))) -> No | BC21: =IF(AND(N21="Sí",AL21="Sí",AI21=0),"Sí","No") -> No | BD21: =IF(COUNTIF('Plan 9+1 (con Pehuamar)'!$A$2:$A$227,A21)>0,"Sí","No") -> Sí
A22: 401696 | B22: 1 | C22: 101 | D22: Lunes | E22: DALLIA LORENA ELIZABET | F22: Almacen/Despensa | G22: Santa Fe | H22: Conrado Pujol | I22: 20 | J22: 0 | K22: 15 | L22: =I22+J22 -> 20 | M22: =L22+K22 -> 35 | N22: =IF(I22>0,"Sí","No") -> Sí | O22: =IF(J22>0,"Sí","No") -> No | P22: =IF(K22>0,"Sí","No") -> Sí | Q22: =IF(OR(I22>0,J22>0),"Sí","No") -> Sí | R22: 1800 | S22: 2800 | V22: 3600 | W22: =IF(AND(I22>0,R22>0),(S22-R22)/R22,"") -> 0.55555556 | X22: =IF(AND(J22>0,T22>0),(U22-T22)/T22,"") | Y22: =IF(AND(K22>0,V22>0),(V22-Resumen!$B$7)/Resumen!$B$7,"") -> 0.44 | Z22: =IF(AND(K22>0,I22>0,V22>0,S22>0),V22-S22,"") -> 800 | AA22: =IF(Z22<>"",Z22/S22,"") -> 0.28571429 | AB22: =IF(AND(K22>0,J22>0,V22>0,U22>0),V22-U22,"") | AC22: =IF(AB22<>"",AB22/U22,"") | AD22: 3 | AE22: 3 | AF22: 0 | AG22: =AD22+AE22+AF22 -> 6 | AH22: =IF(AG22>0,AD22/AG22,"") -> 0.5 | AI22: 0 | AJ22: 0 | AK22: 0 | AL22: =IF(OR(AJ22>0,AK22>0),"Sí","No") -> No | AM22: Contado | AO22: =IF(M22>0,K22/M22,"") -> 0.42857143 | AP22: =IF(M22>=Resumen!$B$5,"Alto","Bajo") -> Bajo | AQ22: =IF(AO22>=Resumen!$B$28,"Alto","Bajo") -> Alto | AR22: =AP22&" Potencial / "&AQ22&" Share" -> Bajo Potencial / Alto Share | AS22: =IF(Q22="Sí",IF(AO22>=Resumen!$B$29,"Alto","Bajo"),"") -> Bajo | AT22: =IF(AS22<>"",AP22&" Potencial / "&AS22&" Share","") -> Bajo Potencial / Bajo Share | AU22: =IF(AH22="","Sin dato",IF(AH22-AO22>Resumen!$B$6,"Sobre-exhibido",IF(AO22-AH22>Resumen!$B$6,"Sub-exhibido","En línea"))) -> Sobre-exhibido | AV22: =IF(AT22="","",IF(AT22="Alto Potencial / Bajo Share",1,IF(AT22="Alto Potencial / Alto Share",2,IF(AT22="Bajo Potencial / Alto Share",3,4)))) -> 4 | AW22: =IF(Q22="No","Sin competencia directa",IF(AV22=1,"1 - Foco Conquista (Alto Pot / Bajo Share)",IF(AV22=2,"2 - Foco Defensa (Alto Pot / Alto Share)",IF(AV22=3,"3 - Monitoreo (Bajo Pot / Alto Share)","4 - Baja Prioridad (Bajo Pot / Bajo Share)")))) -> 4 - Baja Prioridad (Bajo Pot / Bajo Share) | AX22: =IF(OR(IFERROR(AND(W22<>"",Y22<>"",Y22-W22>Resumen!$B$8),FALSE()),IFERROR(AND(X22<>"",Y22<>"",Y22-X22>Resumen!$B$8),FALSE())),MAX(IF(IFERROR(AND(W22<>"",Y22<>"",Y22-W22>Resumen!$B$8),FALSE()),Y22-W22,0),IF(IFERROR(AND(X22<>"",Y22<>"",Y22-X22>Resumen!$B$8),FALSE()),Y22-X22,0)),"") | AY22: =IF(OR(IFERROR(AND(W22<>"",Y22<>"",Y22-W22>Resumen!$B$8),FALSE()),IFERROR(AND(X22<>"",Y22<>"",Y22-X22>Resumen!$B$8),FALSE())),TRIM("Lays tiene mayor markup que "&IF(IFERROR(AND(W22<>"",Y22<>"",Y22-W22>Resumen!$B$8),FALSE()),"Quento ","")&IF(IFERROR(AND(X22<>"",Y22<>"",Y22-X22>Resumen!$B$8),FALSE()),"Julicroc ","")&"en este PDV"),"") | AZ22: =IF(COUNTIF('Plan Pehuamar - Lista'!$A$2:$A$167,A22)>0,"Sí","No") -> No | BA22: =IF(COUNTIF('Plan Combo 9+1'!$A$2:$A$226,A22)>0,"Sí","No") -> No | BB22: =IF(AH22="","No",IF(BA22="Sí",IF((AO22-AH22)>Resumen!$B$6,"Sí","No"),IF((AO22-AH22)>=Resumen!$B$132,"Sí","No"))) -> No | BC22: =IF(AND(N22="Sí",AL22="Sí",AI22=0),"Sí","No") -> No | BD22: =IF(COUNTIF('Plan 9+1 (con Pehuamar)'!$A$2:$A$227,A22)>0,"Sí","No") -> No
A23: 401738 | B23: 1 | C23: 101 | D23: Lunes | E23: YOST GLADYS | F23: Almacen/Despensa | G23: Santa Fe | H23: Conrado Pujol | I23: 0 | J23: 0 | K23: 0.9 | L23: =I23+J23 -> 0 | M23: =L23+K23 -> 0.9 | N23: =IF(I23>0,"Sí","No") -> No | O23: =IF(J23>0,"Sí","No") -> No | P23: =IF(K23>0,"Sí","No") -> Sí | Q23: =IF(OR(I23>0,J23>0),"Sí","No") -> No | W23: =IF(AND(I23>0,R23>0),(S23-R23)/R23,"") | X23: =IF(AND(J23>0,T23>0),(U23-T23)/T23,"") | Y23: =IF(AND(K23>0,V23>0),(V23-Resumen!$B$7)/Resumen!$B$7,"") | Z23: =IF(AND(K23>0,I23>0,V23>0,S23>0),V23-S23,"") | AA23: =IF(Z23<>"",Z23/S23,"") | AB23: =IF(AND(K23>0,J23>0,V23>0,U23>0),V23-U23,"") | AC23: =IF(AB23<>"",AB23/U23,"") | AD23: 0 | AE23: 0 | AF23: 0 | AG23: =AD23+AE23+AF23 -> 0 | AH23: =IF(AG23>0,AD23/AG23,"") | AI23: 0 | AJ23: 0 | AK23: 0 | AL23: =IF(OR(AJ23>0,AK23>0),"Sí","No") -> No | AO23: =IF(M23>0,K23/M23,"") -> 1 | AP23: =IF(M23>=Resumen!$B$5,"Alto","Bajo") -> Bajo | AQ23: =IF(AO23>=Resumen!$B$28,"Alto","Bajo") -> Alto | AR23: =AP23&" Potencial / "&AQ23&" Share" -> Bajo Potencial / Alto Share | AS23: =IF(Q23="Sí",IF(AO23>=Resumen!$B$29,"Alto","Bajo"),"") | AT23: =IF(AS23<>"",AP23&" Potencial / "&AS23&" Share","") | AU23: =IF(AH23="","Sin dato",IF(AH23-AO23>Resumen!$B$6,"Sobre-exhibido",IF(AO23-AH23>Resumen!$B$6,"Sub-exhibido","En línea"))) -> Sin dato | AV23: =IF(AT23="","",IF(AT23="Alto Potencial / Bajo Share",1,IF(AT23="Alto Potencial / Alto Share",2,IF(AT23="Bajo Potencial / Alto Share",3,4)))) | AW23: =IF(Q23="No","Sin competencia directa",IF(AV23=1,"1 - Foco Conquista (Alto Pot / Bajo Share)",IF(AV23=2,"2 - Foco Defensa (Alto Pot / Alto Share)",IF(AV23=3,"3 - Monitoreo (Bajo Pot / Alto Share)","4 - Baja Prioridad (Bajo Pot / Bajo Share)")))) -> Sin competencia directa | AX23: =IF(OR(IFERROR(AND(W23<>"",Y23<>"",Y23-W23>Resumen!$B$8),FALSE()),IFERROR(AND(X23<>"",Y23<>"",Y23-X23>Resumen!$B$8),FALSE())),MAX(IF(IFERROR(AND(W23<>"",Y23<>"",Y23-W23>Resumen!$B$8),FALSE()),Y23-W23,0),IF(IFERROR(AND(X23<>"",Y23<>"",Y23-X23>Resumen!$B$8),FALSE()),Y23-X23,0)),"") | AY23: =IF(OR(IFERROR(AND(W23<>"",Y23<>"",Y23-W23>Resumen!$B$8),FALSE()),IFERROR(AND(X23<>"",Y23<>"",Y23-X23>Resumen!$B$8),FALSE())),TRIM("Lays tiene mayor markup que "&IF(IFERROR(AND(W23<>"",Y23<>"",Y23-W23>Resumen!$B$8),FALSE()),"Quento ","")&IF(IFERROR(AND(X23<>"",Y23<>"",Y23-X23>Resumen!$B$8),FALSE()),"Julicroc ","")&"en este PDV"),"") | AZ23: =IF(COUNTIF('Plan Pehuamar - Lista'!$A$2:$A$167,A23)>0,"Sí","No") -> No | BA23: =IF(COUNTIF('Plan Combo 9+1'!$A$2:$A$226,A23)>0,"Sí","No") -> No | BB23: =IF(AH23="","No",IF(BA23="Sí",IF((AO23-AH23)>Resumen!$B$6,"Sí","No"),IF((AO23-AH23)>=Resumen!$B$132,"Sí","No"))) -> No | BC23: =IF(AND(N23="Sí",AL23="Sí",AI23=0),"Sí","No") -> No | BD23: =IF(COUNTIF('Plan 9+1 (con Pehuamar)'!$A$2:$A$227,A23)>0,"Sí","No") -> No
A24: 401739 | B24: 1 | C24: 101 | D24: Lunes | E24: NUDEL LUIS ARIEL | F24: Almacen/Despensa | G24: Santa Fe | H24: Conrado Pujol | I24: 20 | J24: 25 | K24: 15 | L24: =I24+J24 -> 45 | M24: =L24+K24 -> 60 | N24: =IF(I24>0,"Sí","No") -> Sí | O24: =IF(J24>0,"Sí","No") -> Sí | P24: =IF(K24>0,"Sí","No") -> Sí | Q24: =IF(OR(I24>0,J24>0),"Sí","No") -> Sí | R24: 1900 | S24: 2600 | T24: 1700 | U24: 2200 | V24: 3700 | W24: =IF(AND(I24>0,R24>0),(S24-R24)/R24,"") -> 0.36842105 | X24: =IF(AND(J24>0,T24>0),(U24-T24)/T24,"") -> 0.29411765 | Y24: =IF(AND(K24>0,V24>0),(V24-Resumen!$B$7)/Resumen!$B$7,"") -> 0.48 | Z24: =IF(AND(K24>0,I24>0,V24>0,S24>0),V24-S24,"") -> 1100 | AA24: =IF(Z24<>"",Z24/S24,"") -> 0.42307692 | AB24: =IF(AND(K24>0,J24>0,V24>0,U24>0),V24-U24,"") -> 1500 | AC24: =IF(AB24<>"",AB24/U24,"") -> 0.68181818 | AD24: 5 | AE24: 4 | AF24: 3 | AG24: =AD24+AE24+AF24 -> 12 | AH24: =IF(AG24>0,AD24/AG24,"") -> 0.41666667 | AI24: 0 | AJ24: 0 | AK24: 0 | AL24: =IF(OR(AJ24>0,AK24>0),"Sí","No") -> No | AM24: Contado | AN24: Contado | AO24: =IF(M24>0,K24/M24,"") -> 0.25 | AP24: =IF(M24>=Resumen!$B$5,"Alto","Bajo") -> Alto | AQ24: =IF(AO24>=Resumen!$B$28,"Alto","Bajo") -> Bajo | AR24: =AP24&" Potencial / "&AQ24&" Share" -> Alto Potencial / Bajo Share | AS24: =IF(Q24="Sí",IF(AO24>=Resumen!$B$29,"Alto","Bajo"),"") -> Bajo | AT24: =IF(AS24<>"",AP24&" Potencial / "&AS24&" Share","") -> Alto Potencial / Bajo Share | AU24: =IF(AH24="","Sin dato",IF(AH24-AO24>Resumen!$B$6,"Sobre-exhibido",IF(AO24-AH24>Resumen!$B$6,"Sub-exhibido","En línea"))) -> Sobre-exhibido | AV24: =IF(AT24="","",IF(AT24="Alto Potencial / Bajo Share",1,IF(AT24="Alto Potencial / Alto Share",2,IF(AT24="Bajo Potencial / Alto Share",3,4)))) -> 1 | AW24: =IF(Q24="No","Sin competencia directa",IF(AV24=1,"1 - Foco Conquista (Alto Pot / Bajo Share)",IF(AV24=2,"2 - Foco Defensa (Alto Pot / Alto Share)",IF(AV24=3,"3 - Monitoreo (Bajo Pot / Alto Share)","4 - Baja Prioridad (Bajo Pot / Bajo Share)")))) -> 1 - Foco Conquista (Alto Pot / Bajo Share) | AX24: =IF(OR(IFERROR(AND(W24<>"",Y24<>"",Y24-W24>Resumen!$B$8),FALSE()),IFERROR(AND(X24<>"",Y24<>"",Y24-X24>Resumen!$B$8),FALSE())),MAX(IF(IFERROR(AND(W24<>"",Y24<>"",Y24-W24>Resumen!$B$8),FALSE()),Y24-W24,0),IF(IFERROR(AND(X24<>"",Y24<>"",Y24-X24>Resumen!$B$8),FALSE()),Y24-X24,0)),"") -> 0.18588235 | AY24: =IF(OR(IFERROR(AND(W24<>"",Y24<>"",Y24-W24>Resumen!$B$8),FALSE()),IFERROR(AND(X24<>"",Y24<>"",Y24-X24>Resumen!$B$8),FALSE())),TRIM("Lays tiene mayor markup que "&IF(IFERROR(AND(W24<>"",Y24<>"",Y24-W24>Resumen!$B$8),FALSE()),"Quento ","")&IF(IFERROR(AND(X24<>"",Y24<>"",Y24-X24>Resumen!$B$8),FALSE()),"Julicroc ","")&"en este PDV"),"") -> Lays tiene mayor markup que Quento Julicroc en este PDV | AZ24: =IF(COUNTIF('Plan Pehuamar - Lista'!$A$2:$A$167,A24)>0,"Sí","No") -> No | BA24: =IF(COUNTIF('Plan Combo 9+1'!$A$2:$A$226,A24)>0,"Sí","No") -> Sí | BB24: =IF(AH24="","No",IF(BA24="Sí",IF((AO24-AH24)>Resumen!$B$6,"Sí","No"),IF((AO24-AH24)>=Resumen!$B$132,"Sí","No"))) -> No | BC24: =IF(AND(N24="Sí",AL24="Sí",AI24=0),"Sí","No") -> No | BD24: =IF(COUNTIF('Plan 9+1 (con Pehuamar)'!$A$2:$A$227,A24)>0,"Sí","No") -> Sí
A25: 401874 | B25: 1 | C25: 101 | D25: Lunes | E25: FONTANA MAURO | F25: Almacen/Despensa | G25: Santa Fe | H25: Conrado Pujol | I25: 0 | J25: 0 | K25: 4.5 | L25: =I25+J25 -> 0 | M25: =L25+K25 -> 4.5 | N25: =IF(I25>0,"Sí","No") -> No | O25: =IF(J25>0,"Sí","No") -> No | P25: =IF(K25>0,"Sí","No") -> Sí | Q25: =IF(OR(I25>0,J25>0),"Sí","No") -> No | W25: =IF(AND(I25>0,R25>0),(S25-R25)/R25,"") | X25: =IF(AND(J25>0,T25>0),(U25-T25)/T25,"") | Y25: =IF(AND(K25>0,V25>0),(V25-Resumen!$B$7)/Resumen!$B$7,"") | Z25: =IF(AND(K25>0,I25>0,V25>0,S25>0),V25-S25,"") | AA25: =IF(Z25<>"",Z25/S25,"") | AB25: =IF(AND(K25>0,J25>0,V25>0,U25>0),V25-U25,"") | AC25: =IF(AB25<>"",AB25/U25,"") | AD25: 0 | AE25: 0 | AF25: 0 | AG25: =AD25+AE25+AF25 -> 0 | AH25: =IF(AG25>0,AD25/AG25,"") | AI25: 0 | AJ25: 0 | AK25: 0 | AL25: =IF(OR(AJ25>0,AK25>0),"Sí","No") -> No | AO25: =IF(M25>0,K25/M25,"") -> 1 | AP25: =IF(M25>=Resumen!$B$5,"Alto","Bajo") -> Bajo | AQ25: =IF(AO25>=Resumen!$B$28,"Alto","Bajo") -> Alto | AR25: =AP25&" Potencial / "&AQ25&" Share" -> Bajo Potencial / Alto Share | AS25: =IF(Q25="Sí",IF(AO25>=Resumen!$B$29,"Alto","Bajo"),"") | AT25: =IF(AS25<>"",AP25&" Potencial / "&AS25&" Share","") | AU25: =IF(AH25="","Sin dato",IF(AH25-AO25>Resumen!$B$6,"Sobre-exhibido",IF(AO25-AH25>Resumen!$B$6,"Sub-exhibido","En línea"))) -> Sin dato | AV25: =IF(AT25="","",IF(AT25="Alto Potencial / Bajo Share",1,IF(AT25="Alto Potencial / Alto Share",2,IF(AT25="Bajo Potencial / Alto Share",3,4)))) | AW25: =IF(Q25="No","Sin competencia directa",IF(AV25=1,"1 - Foco Conquista (Alto Pot / Bajo Share)",IF(AV25=2,"2 - Foco Defensa (Alto Pot / Alto Share)",IF(AV25=3,"3 - Monitoreo (Bajo Pot / Alto Share)","4 - Baja Prioridad (Bajo Pot / Bajo Share)")))) -> Sin competencia directa | AX25: =IF(OR(IFERROR(AND(W25<>"",Y25<>"",Y25-W25>Resumen!$B$8),FALSE()),IFERROR(AND(X25<>"",Y25<>"",Y25-X25>Resumen!$B$8),FALSE())),MAX(IF(IFERROR(AND(W25<>"",Y25<>"",Y25-W25>Resumen!$B$8),FALSE()),Y25-W25,0),IF(IFERROR(AND(X25<>"",Y25<>"",Y25-X25>Resumen!$B$8),FALSE()),Y25-X25,0)),"") | AY25: =IF(OR(IFERROR(AND(W25<>"",Y25<>"",Y25-W25>Resumen!$B$8),FALSE()),IFERROR(AND(X25<>"",Y25<>"",Y25-X25>Resumen!$B$8),FALSE())),TRIM("Lays tiene mayor markup que "&IF(IFERROR(AND(W25<>"",Y25<>"",Y25-W25>Resumen!$B$8),FALSE()),"Quento ","")&IF(IFERROR(AND(X25<>"",Y25<>"",Y25-X25>Resumen!$B$8),FALSE()),"Julicroc ","")&"en este PDV"),"") | AZ25: =IF(COUNTIF('Plan Pehuamar - Lista'!$A$2:$A$167,A25)>0,"Sí","No") -> No | BA25: =IF(COUNTIF('Plan Combo 9+1'!$A$2:$A$226,A25)>0,"Sí","No") -> No | BB25: =IF(AH25="","No",IF(BA25="Sí",IF((AO25-AH25)>Resumen!$B$6,"Sí","No"),IF((AO25-AH25)>=Resumen!$B$132,"Sí","No"))) -> No | BC25: =IF(AND(N25="Sí",AL25="Sí",AI25=0),"Sí","No") -> No | BD25: =IF(COUNTIF('Plan 9+1 (con Pehuamar)'!$A$2:$A$227,A25)>0,"Sí","No") -> No
A26: 403115 | B26: 1 | C26: 101 | D26: Lunes | E26: PERALTA GUSTAVO GABRIEL | F26: Kiosco/Maxikiosco | G26: Santa Fe | H26: Conrado Pujol | I26: 0 | J26: 0 | K26: 0.2 | L26: =I26+J26 -> 0 | M26: =L26+K26 -> 0.2 | N26: =IF(I26>0,"Sí","No") -> No | O26: =IF(J26>0,"Sí","No") -> No | P26: =IF(K26>0,"Sí","No") -> Sí | Q26: =IF(OR(I26>0,J26>0),"Sí","No") -> No | W26: =IF(AND(I26>0,R26>0),(S26-R26)/R26,"") | X26: =IF(AND(J26>0,T26>0),(U26-T26)/T26,"") | Y26: =IF(AND(K26>0,V26>0),(V26-Resumen!$B$7)/Resumen!$B$7,"") | Z26: =IF(AND(K26>0,I26>0,V26>0,S26>0),V26-S26,"") | AA26: =IF(Z26<>"",Z26/S26,"") | AB26: =IF(AND(K26>0,J26>0,V26>0,U26>0),V26-U26,"") | AC26: =IF(AB26<>"",AB26/U26,"") | AD26: 0 | AE26: 0 | AF26: 0 | AG26: =AD26+AE26+AF26 -> 0 | AH26: =IF(AG26>0,AD26/AG26,"") | AI26: 0 | AJ26: 0 | AK26: 0 | AL26: =IF(OR(AJ26>0,AK26>0),"Sí","No") -> No | AO26: =IF(M26>0,K26/M26,"") -> 1 | AP26: =IF(M26>=Resumen!$B$5,"Alto","Bajo") -> Bajo | AQ26: =IF(AO26>=Resumen!$B$28,"Alto","Bajo") -> Alto | AR26: =AP26&" Potencial / "&AQ26&" Share" -> Bajo Potencial / Alto Share | AS26: =IF(Q26="Sí",IF(AO26>=Resumen!$B$29,"Alto","Bajo"),"") | AT26: =IF(AS26<>"",AP26&" Potencial / "&AS26&" Share","") | AU26: =IF(AH26="","Sin dato",IF(AH26-AO26>Resumen!$B$6,"Sobre-exhibido",IF(AO26-AH26>Resumen!$B$6,"Sub-exhibido","En línea"))) -> Sin dato | AV26: =IF(AT26="","",IF(AT26="Alto Potencial / Bajo Share",1,IF(AT26="Alto Potencial / Alto Share",2,IF(AT26="Bajo Potencial / Alto Share",3,4)))) | AW26: =IF(Q26="No","Sin competencia directa",IF(AV26=1,"1 - Foco Conquista (Alto Pot / Bajo Share)",IF(AV26=2,"2 - Foco Defensa (Alto Pot / Alto Share)",IF(AV26=3,"3 - Monitoreo (Bajo Pot / Alto Share)","4 - Baja Prioridad (Bajo Pot / Bajo Share)")))) -> Sin competencia directa | AX26: =IF(OR(IFERROR(AND(W26<>"",Y26<>"",Y26-W26>Resumen!$B$8),FALSE()),IFERROR(AND(X26<>"",Y26<>"",Y26-X26>Resumen!$B$8),FALSE())),MAX(IF(IFERROR(AND(W26<>"",Y26<>"",Y26-W26>Resumen!$B$8),FALSE()),Y26-W26,0),IF(IFERROR(AND(X26<>"",Y26<>"",Y26-X26>Resumen!$B$8),FALSE()),Y26-X26,0)),"") | AY26: =IF(OR(IFERROR(AND(W26<>"",Y26<>"",Y26-W26>Resumen!$B$8),FALSE()),IFERROR(AND(X26<>"",Y26<>"",Y26-X26>Resumen!$B$8),FALSE())),TRIM("Lays tiene mayor markup que "&IF(IFERROR(AND(W26<>"",Y26<>"",Y26-W26>Resumen!$B$8),FALSE()),"Quento ","")&IF(IFERROR(AND(X26<>"",Y26<>"",Y26-X26>Resumen!$B$8),FALSE()),"Julicroc ","")&"en este PDV"),"") | AZ26: =IF(COUNTIF('Plan Pehuamar - Lista'!$A$2:$A$167,A26)>0,"Sí","No") -> No | BA26: =IF(COUNTIF('Plan Combo 9+1'!$A$2:$A$226,A26)>0,"Sí","No") -> No | BB26: =IF(AH26="","No",IF(BA26="Sí",IF((AO26-AH26)>Resumen!$B$6,"Sí","No"),IF((AO26-AH26)>=Resumen!$B$132,"Sí","No"))) -> No | BC26: =IF(AND(N26="Sí",AL26="Sí",AI26=0),"Sí","No") -> No | BD26: =IF(COUNTIF('Plan 9+1 (con Pehuamar)'!$A$2:$A$227,A26)>0,"Sí","No") -> No
A27: 403152 | B27: 1 | C27: 101 | D27: Lunes | E27: XUEDAN ZHOU | F27: Autoservicio Tradicional | G27: Santa Fe | H27: Conrado Pujol | I27: 40 | J27: 30 | K27: 35 | L27: =I27+J27 -> 70 | M27: =L27+K27 -> 105 | N27: =IF(I27>0,"Sí","No") -> Sí | O27: =IF(J27>0,"Sí","No") -> Sí | P27: =IF(K27>0,"Sí","No") -> Sí | Q27: =IF(OR(I27>0,J27>0),"Sí","No") -> Sí | R27: 1900 | S27: 3100 | T27: 1700 | U27: 2800 | V27: 3500 | W27: =IF(AND(I27>0,R27>0),(S27-R27)/R27,"") -> 0.63157895 | X27: =IF(AND(J27>0,T27>0),(U27-T27)/T27,"") -> 0.64705882 | Y27: =IF(AND(K27>0,V27>0),(V27-Resumen!$B$7)/Resumen!$B$7,"") -> 0.4 | Z27: =IF(AND(K27>0,I27>0,V27>0,S27>0),V27-S27,"") -> 400 | AA27: =IF(Z27<>"",Z27/S27,"") -> 0.12903226 | AB27: =IF(AND(K27>0,J27>0,V27>0,U27>0),V27-U27,"") -> 700 | AC27: =IF(AB27<>"",AB27/U27,"") -> 0.25 | AD27: 5 | AE27: 4 | AF27: 3 | AG27: =AD27+AE27+AF27 -> 12 | AH27: =IF(AG27>0,AD27/AG27,"") -> 0.41666667 | AI27: 1 | AJ27: 1 | AK27: 1 | AL27: =IF(OR(AJ27>0,AK27>0),"Sí","No") -> Sí | AM27: Contado | AN27: Contado | AO27: =IF(M27>0,K27/M27,"") -> 0.33333333 | AP27: =IF(M27>=Resumen!$B$5,"Alto","Bajo") -> Alto | AQ27: =IF(AO27>=Resumen!$B$28,"Alto","Bajo") -> Bajo | AR27: =AP27&" Potencial / "&AQ27&" Share" -> Alto Potencial / Bajo Share | AS27: =IF(Q27="Sí",IF(AO27>=Resumen!$B$29,"Alto","Bajo"),"") -> Bajo | AT27: =IF(AS27<>"",AP27&" Potencial / "&AS27&" Share","") -> Alto Potencial / Bajo Share | AU27: =IF(AH27="","Sin dato",IF(AH27-AO27>Resumen!$B$6,"Sobre-exhibido",IF(AO27-AH27>Resumen!$B$6,"Sub-exhibido","En línea"))) -> Sobre-exhibido | AV27: =IF(AT27="","",IF(AT27="Alto Potencial / Bajo Share",1,IF(AT27="Alto Potencial / Alto Share",2,IF(AT27="Bajo Potencial / Alto Share",3,4)))) -> 1 | AW27: =IF(Q27="No","Sin competencia directa",IF(AV27=1,"1 - Foco Conquista (Alto Pot / Bajo Share)",IF(AV27=2,"2 - Foco Defensa (Alto Pot / Alto Share)",IF(AV27=3,"3 - Monitoreo (Bajo Pot / Alto Share)","4 - Baja Prioridad (Bajo Pot / Bajo Share)")))) -> 1 - Foco Conquista (Alto Pot / Bajo Share) | AX27: =IF(OR(IFERROR(AND(W27<>"",Y27<>"",Y27-W27>Resumen!$B$8),FALSE()),IFERROR(AND(X27<>"",Y27<>"",Y27-X27>Resumen!$B$8),FALSE())),MAX(IF(IFERROR(AND(W27<>"",Y27<>"",Y27-W27>Resumen!$B$8),FALSE()),Y27-W27,0),IF(IFERROR(AND(X27<>"",Y27<>"",Y27-X27>Resumen!$B$8),FALSE()),Y27-X27,0)),"") | AY27: =IF(OR(IFERROR(AND(W27<>"",Y27<>"",Y27-W27>Resumen!$B$8),FALSE()),IFERROR(AND(X27<>"",Y27<>"",Y27-X27>Resumen!$B$8),FALSE())),TRIM("Lays tiene mayor markup que "&IF(IFERROR(AND(W27<>"",Y27<>"",Y27-W27>Resumen!$B$8),FALSE()),"Quento ","")&IF(IFERROR(AND(X27<>"",Y27<>"",Y27-X27>Resumen!$B$8),FALSE()),"Julicroc ","")&"en este PDV"),"") | AZ27: =IF(COUNTIF('Plan Pehuamar - Lista'!$A$2:$A$167,A27)>0,"Sí","No") -> No | BA27: =IF(COUNTIF('Plan Combo 9+1'!$A$2:$A$226,A27)>0,"Sí","No") -> No | BB27: =IF(AH27="","No",IF(BA27="Sí",IF((AO27-AH27)>Resumen!$B$6,"Sí","No"),IF((AO27-AH27)>=Resumen!$B$132,"Sí","No"))) -> No | BC27: =IF(AND(N27="Sí",AL27="Sí",AI27=0),"Sí","No") -> No | BD27: =IF(COUNTIF('Plan 9+1 (con Pehuamar)'!$A$2:$A$227,A27)>0,"Sí","No") -> Sí
A28: 403252 | B28: 1 | C28: 101 | D28: Lunes | E28: NEONAZA | F28: Almacen/Despensa | G28: Santa Fe | H28: Conrado Pujol | I28: 0 | J28: 0 | K28: 0.2 | L28: =I28+J28 -> 0 | M28: =L28+K28 -> 0.2 | N28: =IF(I28>0,"Sí","No") -> No | O28: =IF(J28>0,"Sí","No") -> No | P28: =IF(K28>0,"Sí","No") -> Sí | Q28: =IF(OR(I28>0,J28>0),"Sí","No") -> No | W28: =IF(AND(I28>0,R28>0),(S28-R28)/R28,"") | X28: =IF(AND(J28>0,T28>0),(U28-T28)/T28,"") | Y28: =IF(AND(K28>0,V28>0),(V28-Resumen!$B$7)/Resumen!$B$7,"") | Z28: =IF(AND(K28>0,I28>0,V28>0,S28>0),V28-S28,"") | AA28: =IF(Z28<>"",Z28/S28,"") | AB28: =IF(AND(K28>0,J28>0,V28>0,U28>0),V28-U28,"") | AC28: =IF(AB28<>"",AB28/U28,"") | AD28: 0 | AE28: 0 | AF28: 0 | AG28: =AD28+AE28+AF28 -> 0 | AH28: =IF(AG28>0,AD28/AG28,"") | AI28: 0 | AJ28: 0 | AK28: 0 | AL28: =IF(OR(AJ28>0,AK28>0),"Sí","No") -> No | AO28: =IF(M28>0,K28/M28,"") -> 1 | AP28: =IF(M28>=Resumen!$B$5,"Alto","Bajo") -> Bajo | AQ28: =IF(AO28>=Resumen!$B$28,"Alto","Bajo") -> Alto | AR28: =AP28&" Potencial / "&AQ28&" Share" -> Bajo Potencial / Alto Share | AS28: =IF(Q28="Sí",IF(AO28>=Resumen!$B$29,"Alto","Bajo"),"") | AT28: =IF(AS28<>"",AP28&" Potencial / "&AS28&" Share","") | AU28: =IF(AH28="","Sin dato",IF(AH28-AO28>Resumen!$B$6,"Sobre-exhibido",IF(AO28-AH28>Resumen!$B$6,"Sub-exhibido","En línea"))) -> Sin dato | AV28: =IF(AT28="","",IF(AT28="Alto Potencial / Bajo Share",1,IF(AT28="Alto Potencial / Alto Share",2,IF(AT28="Bajo Potencial / Alto Share",3,4)))) | AW28: =IF(Q28="No","Sin competencia directa",IF(AV28=1,"1 - Foco Conquista (Alto Pot / Bajo Share)",IF(AV28=2,"2 - Foco Defensa (Alto Pot / Alto Share)",IF(AV28=3,"3 - Monitoreo (Bajo Pot / Alto Share)","4 - Baja Prioridad (Bajo Pot / Bajo Share)")))) -> Sin competencia directa | AX28: =IF(OR(IFERROR(AND(W28<>"",Y28<>"",Y28-W28>Resumen!$B$8),FALSE()),IFERROR(AND(X28<>"",Y28<>"",Y28-X28>Resumen!$B$8),FALSE())),MAX(IF(IFERROR(AND(W28<>"",Y28<>"",Y28-W28>Resumen!$B$8),FALSE()),Y28-W28,0),IF(IFERROR(AND(X28<>"",Y28<>"",Y28-X28>Resumen!$B$8),FALSE()),Y28-X28,0)),"") | AY28: =IF(OR(IFERROR(AND(W28<>"",Y28<>"",Y28-W28>Resumen!$B$8),FALSE()),IFERROR(AND(X28<>"",Y28<>"",Y28-X28>Resumen!$B$8),FALSE())),TRIM("Lays tiene mayor markup que "&IF(IFERROR(AND(W28<>"",Y28<>"",Y28-W28>Resumen!$B$8),FALSE()),"Quento ","")&IF(IFERROR(AND(X28<>"",Y28<>"",Y28-X28>Resumen!$B$8),FALSE()),"Julicroc ","")&"en este PDV"),"") | AZ28: =IF(COUNTIF('Plan Pehuamar - Lista'!$A$2:$A$167,A28)>0,"Sí","No") -> No | BA28: =IF(COUNTIF('Plan Combo 9+1'!$A$2:$A$226,A28)>0,"Sí","No") -> No | BB28: =IF(AH28="","No",IF(BA28="Sí",IF((AO28-AH28)>Resumen!$B$6,"Sí","No"),IF((AO28-AH28)>=Resumen!$B$132,"Sí","No"))) -> No | BC28: =IF(AND(N28="Sí",AL28="Sí",AI28=0),"Sí","No") -> No | BD28: =IF(COUNTIF('Plan 9+1 (con Pehuamar)'!$A$2:$A$227,A28)>0,"Sí","No") -> No
A29: 403264 | B29: 1 | C29: 101 | D29: Lunes | E29: PINGET PATRICIA | F29: Kiosco/Maxikiosco | G29: Santa Fe | H29: Conrado Pujol | I29: 0 | J29: 0 | K29: 0.4 | L29: =I29+J29 -> 0 | M29: =L29+K29 -> 0.4 | N29: =IF(I29>0,"Sí","No") -> No | O29: =IF(J29>0,"Sí","No") -> No | P29: =IF(K29>0,"Sí","No") -> Sí | Q29: =IF(OR(I29>0,J29>0),"Sí","No") -> No | W29: =IF(AND(I29>0,R29>0),(S29-R29)/R29,"") | X29: =IF(AND(J29>0,T29>0),(U29-T29)/T29,"") | Y29: =IF(AND(K29>0,V29>0),(V29-Resumen!$B$7)/Resumen!$B$7,"") | Z29: =IF(AND(K29>0,I29>0,V29>0,S29>0),V29-S29,"") | AA29: =IF(Z29<>"",Z29/S29,"") | AB29: =IF(AND(K29>0,J29>0,V29>0,U29>0),V29-U29,"") | AC29: =IF(AB29<>"",AB29/U29,"") | AD29: 0 | AE29: 0 | AF29: 0 | AG29: =AD29+AE29+AF29 -> 0 | AH29: =IF(AG29>0,AD29/AG29,"") | AI29: 0 | AJ29: 0 | AK29: 0 | AL29: =IF(OR(AJ29>0,AK29>0),"Sí","No") -> No | AO29: =IF(M29>0,K29/M29,"") -> 1 | AP29: =IF(M29>=Resumen!$B$5,"Alto","Bajo") -> Bajo | AQ29: =IF(AO29>=Resumen!$B$28,"Alto","Bajo") -> Alto | AR29: =AP29&" Potencial / "&AQ29&" Share" -> Bajo Potencial / Alto Share | AS29: =IF(Q29="Sí",IF(AO29>=Resumen!$B$29,"Alto","Bajo"),"") | AT29: =IF(AS29<>"",AP29&" Potencial / "&AS29&" Share","") | AU29: =IF(AH29="","Sin dato",IF(AH29-AO29>Resumen!$B$6,"Sobre-exhibido",IF(AO29-AH29>Resumen!$B$6,"Sub-exhibido","En línea"))) -> Sin dato | AV29: =IF(AT29="","",IF(AT29="Alto Potencial / Bajo Share",1,IF(AT29="Alto Potencial / Alto Share",2,IF(AT29="Bajo Potencial / Alto Share",3,4)))) | AW29: =IF(Q29="No","Sin competencia directa",IF(AV29=1,"1 - Foco Conquista (Alto Pot / Bajo Share)",IF(AV29=2,"2 - Foco Defensa (Alto Pot / Alto Share)",IF(AV29=3,"3 - Monitoreo (Bajo Pot / Alto Share)","4 - Baja Prioridad (Bajo Pot / Bajo Share)")))) -> Sin competencia directa | AX29: =IF(OR(IFERROR(AND(W29<>"",Y29<>"",Y29-W29>Resumen!$B$8),FALSE()),IFERROR(AND(X29<>"",Y29<>"",Y29-X29>Resumen!$B$8),FALSE())),MAX(IF(IFERROR(AND(W29<>"",Y29<>"",Y29-W29>Resumen!$B$8),FALSE()),Y29-W29,0),IF(IFERROR(AND(X29<>"",Y29<>"",Y29-X29>Resumen!$B$8),FALSE()),Y29-X29,0)),"") | AY29: =IF(OR(IFERROR(AND(W29<>"",Y29<>"",Y29-W29>Resumen!$B$8),FALSE()),IFERROR(AND(X29<>"",Y29<>"",Y29-X29>Resumen!$B$8),FALSE())),TRIM("Lays tiene mayor markup que "&IF(IFERROR(AND(W29<>"",Y29<>"",Y29-W29>Resumen!$B$8),FALSE()),"Quento ","")&IF(IFERROR(AND(X29<>"",Y29<>"",Y29-X29>Resumen!$B$8),FALSE()),"Julicroc ","")&"en este PDV"),"") | AZ29: =IF(COUNTIF('Plan Pehuamar - Lista'!$A$2:$A$167,A29)>0,"Sí","No") -> No | BA29: =IF(COUNTIF('Plan Combo 9+1'!$A$2:$A$226,A29)>0,"Sí","No") -> No | BB29: =IF(AH29="","No",IF(BA29="Sí",IF((AO29-AH29)>Resumen!$B$6,"Sí","No"),IF((AO29-AH29)>=Resumen!$B$132,"Sí","No"))) -> No | BC29: =IF(AND(N29="Sí",AL29="Sí",AI29=0),"Sí","No") -> No | BD29: =IF(COUNTIF('Plan 9+1 (con Pehuamar)'!$A$2:$A$227,A29)>0,"Sí","No") -> No
A30: 403294 | B30: 1 | C30: 101 | D30: Lunes | E30: ISABEL ELENA RUIZ DIAZ | F30: Kiosco/Maxikiosco | G30: Santa Fe | H30: Conrado Pujol | I30: 0 | J30: 0 | K30: 2.1 | L30: =I30+J30 -> 0 | M30: =L30+K30 -> 2.1 | N30: =IF(I30>0,"Sí","No") -> No | O30: =IF(J30>0,"Sí","No") -> No | P30: =IF(K30>0,"Sí","No") -> Sí | Q30: =IF(OR(I30>0,J30>0),"Sí","No") -> No | W30: =IF(AND(I30>0,R30>0),(S30-R30)/R30,"") | X30: =IF(AND(J30>0,T30>0),(U30-T30)/T30,"") | Y30: =IF(AND(K30>0,V30>0),(V30-Resumen!$B$7)/Resumen!$B$7,"") | Z30: =IF(AND(K30>0,I30>0,V30>0,S30>0),V30-S30,"") | AA30: =IF(Z30<>"",Z30/S30,"") | AB30: =IF(AND(K30>0,J30>0,V30>0,U30>0),V30-U30,"") | AC30: =IF(AB30<>"",AB30/U30,"") | AD30: 0 | AE30: 0 | AF30: 0 | AG30: =AD30+AE30+AF30 -> 0 | AH30: =IF(AG30>0,AD30/AG30,"") | AI30: 0 | AJ30: 0 | AK30: 0 | AL30: =IF(OR(AJ30>0,AK30>0),"Sí","No") -> No | AO30: =IF(M30>0,K30/M30,"") -> 1 | AP30: =IF(M30>=Resumen!$B$5,"Alto","Bajo") -> Bajo | AQ30: =IF(AO30>=Resumen!$B$28,"Alto","Bajo") -> Alto | AR30: =AP30&" Potencial / "&AQ30&" Share" -> Bajo Potencial / Alto Share | AS30: =IF(Q30="Sí",IF(AO30>=Resumen!$B$29,"Alto","Bajo"),"") | AT30: =IF(AS30<>"",AP30&" Potencial / "&AS30&" Share","") | AU30: =IF(AH30="","Sin dato",IF(AH30-AO30>Resumen!$B$6,"Sobre-exhibido",IF(AO30-AH30>Resumen!$B$6,"Sub-exhibido","En línea"))) -> Sin dato | AV30: =IF(AT30="","",IF(AT30="Alto Potencial / Bajo Share",1,IF(AT30="Alto Potencial / Alto Share",2,IF(AT30="Bajo Potencial / Alto Share",3,4)))) | AW30: =IF(Q30="No","Sin competencia directa",IF(AV30=1,"1 - Foco Conquista (Alto Pot / Bajo Share)",IF(AV30=2,"2 - Foco Defensa (Alto Pot / Alto Share)",IF(AV30=3,"3 - Monitoreo (Bajo Pot / Alto Share)","4 - Baja Prioridad (Bajo Pot / Bajo Share)")))) -> Sin competencia directa | AX30: =IF(OR(IFERROR(AND(W30<>"",Y30<>"",Y30-W30>Resumen!$B$8),FALSE()),IFERROR(AND(X30<>"",Y30<>"",Y30-X30>Resumen!$B$8),FALSE())),MAX(IF(IFERROR(AND(W30<>"",Y30<>"",Y30-W30>Resumen!$B$8),FALSE()),Y30-W30,0),IF(IFERROR(AND(X30<>"",Y30<>"",Y30-X30>Resumen!$B$8),FALSE()),Y30-X30,0)),"") | AY30: =IF(OR(IFERROR(AND(W30<>"",Y30<>"",Y30-W30>Resumen!$B$8),FALSE()),IFERROR(AND(X30<>"",Y30<>"",Y30-X30>Resumen!$B$8),FALSE())),TRIM("Lays tiene mayor markup que "&IF(IFERROR(AND(W30<>"",Y30<>"",Y30-W30>Resumen!$B$8),FALSE()),"Quento ","")&IF(IFERROR(AND(X30<>"",Y30<>"",Y30-X30>Resumen!$B$8),FALSE()),"Julicroc ","")&"en este PDV"),"") | AZ30: =IF(COUNTIF('Plan Pehuamar - Lista'!$A$2:$A$167,A30)>0,"Sí","No") -> No | BA30: =IF(COUNTIF('Plan Combo 9+1'!$A$2:$A$226,A30)>0,"Sí","No") -> No | BB30: =IF(AH30="","No",IF(BA30="Sí",IF((AO30-AH30)>Resumen!$B$6,"Sí","No"),IF((AO30-AH30)>=Resumen!$B$132,"Sí","No"))) -> No | BC30: =IF(AND(N30="Sí",AL30="Sí",AI30=0),"Sí","No") -> No | BD30: =IF(COUNTIF('Plan 9+1 (con Pehuamar)'!$A$2:$A$227,A30)>0,"Sí","No") -> No
A31: 403338 | B31: 1 | C31: 101 | D31: Lunes | E31: FERNANDEZ GUSTAVO | F31: Almacen/Despensa | G31: Santa Fe | H31: Conrado Pujol | I31: 35 | J31: 15 | K31: 20 | L31: =I31+J31 -> 50 | M31: =L31+K31 -> 70 | N31: =IF(I31>0,"Sí","No") -> Sí | O31: =IF(J31>0,"Sí","No") -> Sí | P31: =IF(K31>0,"Sí","No") -> Sí | Q31: =IF(OR(I31>0,J31>0),"Sí","No") -> Sí | R31: 1800 | S31: 2800 | T31: 1600 | U31: 2500 | V31: 3700 | W31: =IF(AND(I31>0,R31>0),(S31-R31)/R31,"") -> 0.55555556 | X31: =IF(AND(J31>0,T31>0),(U31-T31)/T31,"") -> 0.5625 | Y31: =IF(AND(K31>0,V31>0),(V31-Resumen!$B$7)/Resumen!$B$7,"") -> 0.48 | Z31: =IF(AND(K31>0,I31>0,V31>0,S31>0),V31-S31,"") -> 900 | AA31: =IF(Z31<>"",Z31/S31,"") -> 0.32142857 | AB31: =IF(AND(K31>0,J31>0,V31>0,U31>0),V31-U31,"") -> 1200 | AC31: =IF(AB31<>"",AB31/U31,"") -> 0.48 | AD31: 5 | AE31: 3 | AF31: 3 | AG31: =AD31+AE31+AF31 -> 11 | AH31: =IF(AG31>0,AD31/AG31,"") -> 0.45454545 | AI31: 1 | AJ31: 0 | AK31: 0 | AL31: =IF(OR(AJ31>0,AK31>0),"Sí","No") -> No | AM31: Contado | AN31: Contado | AO31: =IF(M31>0,K31/M31,"") -> 0.28571429 | AP31: =IF(M31>=Resumen!$B$5,"Alto","Bajo") -> Alto | AQ31: =IF(AO31>=Resumen!$B$28,"Alto","Bajo") -> Bajo | AR31: =AP31&" Potencial / "&AQ31&" Share" -> Alto Potencial / Bajo Share | AS31: =IF(Q31="Sí",IF(AO31>=Resumen!$B$29,"Alto","Bajo"),"") -> Bajo | AT31: =IF(AS31<>"",AP31&" Potencial / "&AS31&" Share","") -> Alto Potencial / Bajo Share | AU31: =IF(AH31="","Sin dato",IF(AH31-AO31>Resumen!$B$6,"Sobre-exhibido",IF(AO31-AH31>Resumen!$B$6,"Sub-exhibido","En línea"))) -> Sobre-exhibido | AV31: =IF(AT31="","",IF(AT31="Alto Potencial / Bajo Share",1,IF(AT31="Alto Potencial / Alto Share",2,IF(AT31="Bajo Potencial / Alto Share",3,4)))) -> 1 | AW31: =IF(Q31="No","Sin competencia directa",IF(AV31=1,"1 - Foco Conquista (Alto Pot / Bajo Share)",IF(AV31=2,"2 - Foco Defensa (Alto Pot / Alto Share)",IF(AV31=3,"3 - Monitoreo (Bajo Pot / Alto Share)","4 - Baja Prioridad (Bajo Pot / Bajo Share)")))) -> 1 - Foco Conquista (Alto Pot / Bajo Share) | AX31: =IF(OR(IFERROR(AND(W31<>"",Y31<>"",Y31-W31>Resumen!$B$8),FALSE()),IFERROR(AND(X31<>"",Y31<>"",Y31-X31>Resumen!$B$8),FALSE())),MAX(IF(IFERROR(AND(W31<>"",Y31<>"",Y31-W31>Resumen!$B$8),FALSE()),Y31-W31,0),IF(IFERROR(AND(X31<>"",Y31<>"",Y31-X31>Resumen!$B$8),FALSE()),Y31-X31,0)),"") | AY31: =IF(OR(IFERROR(AND(W31<>"",Y31<>"",Y31-W31>Resumen!$B$8),FALSE()),IFERROR(AND(X31<>"",Y31<>"",Y31-X31>Resumen!$B$8),FALSE())),TRIM("Lays tiene mayor markup que "&IF(IFERROR(AND(W31<>"",Y31<>"",Y31-W31>Resumen!$B$8),FALSE()),"Quento ","")&IF(IFERROR(AND(X31<>"",Y31<>"",Y31-X31>Resumen!$B$8),FALSE()),"Julicroc ","")&"en este PDV"),"") | AZ31: =IF(COUNTIF('Plan Pehuamar - Lista'!$A$2:$A$167,A31)>0,"Sí","No") -> Sí | BA31: =IF(COUNTIF('Plan Combo 9+1'!$A$2:$A$226,A31)>0,"Sí","No") -> No | BB31: =IF(AH31="","No",IF(BA31="Sí",IF((AO31-AH31)>Resumen!$B$6,"Sí","No"),IF((AO31-AH31)>=Resumen!$B$132,"Sí","No"))) -> No | BC31: =IF(AND(N31="Sí",AL31="Sí",AI31=0),"Sí","No") -> No | BD31: =IF(COUNTIF('Plan 9+1 (con Pehuamar)'!$A$2:$A$227,A31)>0,"Sí","No") -> Sí
A32: 403429 | B32: 1 | C32: 101 | D32: Lunes | E32: Hector vega | F32: Almacen/Despensa | G32: Santa Fe | H32: Conrado Pujol | I32: 0 | J32: 0 | K32: 1 | L32: =I32+J32 -> 0 | M32: =L32+K32 -> 1 | N32: =IF(I32>0,"Sí","No") -> No | O32: =IF(J32>0,"Sí","No") -> No | P32: =IF(K32>0,"Sí","No") -> Sí | Q32: =IF(OR(I32>0,J32>0),"Sí","No") -> No | W32: =IF(AND(I32>0,R32>0),(S32-R32)/R32,"") | X32: =IF(AND(J32>0,T32>0),(U32-T32)/T32,"") | Y32: =IF(AND(K32>0,V32>0),(V32-Resumen!$B$7)/Resumen!$B$7,"") | Z32: =IF(AND(K32>0,I32>0,V32>0,S32>0),V32-S32,"") | AA32: =IF(Z32<>"",Z32/S32,"") | AB32: =IF(AND(K32>0,J32>0,V32>0,U32>0),V32-U32,"") | AC32: =IF(AB32<>"",AB32/U32,"") | AD32: 0 | AE32: 0 | AF32: 0 | AG32: =AD32+AE32+AF32 -> 0 | AH32: =IF(AG32>0,AD32/AG32,"") | AI32: 0 | AJ32: 0 | AK32: 0 | AL32: =IF(OR(AJ32>0,AK32>0),"Sí","No") -> No | AO32: =IF(M32>0,K32/M32,"") -> 1 | AP32: =IF(M32>=Resumen!$B$5,"Alto","Bajo") -> Bajo | AQ32: =IF(AO32>=Resumen!$B$28,"Alto","Bajo") -> Alto | AR32: =AP32&" Potencial / "&AQ32&" Share" -> Bajo Potencial / Alto Share | AS32: =IF(Q32="Sí",IF(AO32>=Resumen!$B$29,"Alto","Bajo"),"") | AT32: =IF(AS32<>"",AP32&" Potencial / "&AS32&" Share","") | AU32: =IF(AH32="","Sin dato",IF(AH32-AO32>Resumen!$B$6,"Sobre-exhibido",IF(AO32-AH32>Resumen!$B$6,"Sub-exhibido","En línea"))) -> Sin dato | AV32: =IF(AT32="","",IF(AT32="Alto Potencial / Bajo Share",1,IF(AT32="Alto Potencial / Alto Share",2,IF(AT32="Bajo Potencial / Alto Share",3,4)))) | AW32: =IF(Q32="No","Sin competencia directa",IF(AV32=1,"1 - Foco Conquista (Alto Pot / Bajo Share)",IF(AV32=2,"2 - Foco Defensa (Alto Pot / Alto Share)",IF(AV32=3,"3 - Monitoreo (Bajo Pot / Alto Share)","4 - Baja Prioridad (Bajo Pot / Bajo Share)")))) -> Sin competencia directa | AX32: =IF(OR(IFERROR(AND(W32<>"",Y32<>"",Y32-W32>Resumen!$B$8),FALSE()),IFERROR(AND(X32<>"",Y32<>"",Y32-X32>Resumen!$B$8),FALSE())),MAX(IF(IFERROR(AND(W32<>"",Y32<>"",Y32-W32>Resumen!$B$8),FALSE()),Y32-W32,0),IF(IFERROR(AND(X32<>"",Y32<>"",Y32-X32>Resumen!$B$8),FALSE()),Y32-X32,0)),"") | AY32: =IF(OR(IFERROR(AND(W32<>"",Y32<>"",Y32-W32>Resumen!$B$8),FALSE()),IFERROR(AND(X32<>"",Y32<>"",Y32-X32>Resumen!$B$8),FALSE())),TRIM("Lays tiene mayor markup que "&IF(IFERROR(AND(W32<>"",Y32<>"",Y32-W32>Resumen!$B$8),FALSE()),"Quento ","")&IF(IFERROR(AND(X32<>"",Y32<>"",Y32-X32>Resumen!$B$8),FALSE()),"Julicroc ","")&"en este PDV"),"") | AZ32: =IF(COUNTIF('Plan Pehuamar - Lista'!$A$2:$A$167,A32)>0,"Sí","No") -> No | BA32: =IF(COUNTIF('Plan Combo 9+1'!$A$2:$A$226,A32)>0,"Sí","No") -> No | BB32: =IF(AH32="","No",IF(BA32="Sí",IF((AO32-AH32)>Resumen!$B$6,"Sí","No"),IF((AO32-AH32)>=Resumen!$B$132,"Sí","No"))) -> No | BC32: =IF(AND(N32="Sí",AL32="Sí",AI32=0),"Sí","No") -> No | BD32: =IF(COUNTIF('Plan 9+1 (con Pehuamar)'!$A$2:$A$227,A32)>0,"Sí","No") -> No
A33: 403431 | B33: 1 | C33: 101 | D33: Lunes | E33: Daniel quiñones | F33: Almacen/Despensa | G33: Santa Fe | H33: Conrado Pujol | I33: 0 | J33: 0 | K33: 2.3 | L33: =I33+J33 -> 0 | M33: =L33+K33 -> 2.3 | N33: =IF(I33>0,"Sí","No") -> No | O33: =IF(J33>0,"Sí","No") -> No | P33: =IF(K33>0,"Sí","No") -> Sí | Q33: =IF(OR(I33>0,J33>0),"Sí","No") -> No | W33: =IF(AND(I33>0,R33>0),(S33-R33)/R33,"") | X33: =IF(AND(J33>0,T33>0),(U33-T33)/T33,"") | Y33: =IF(AND(K33>0,V33>0),(V33-Resumen!$B$7)/Resumen!$B$7,"") | Z33: =IF(AND(K33>0,I33>0,V33>0,S33>0),V33-S33,"") | AA33: =IF(Z33<>"",Z33/S33,"") | AB33: =IF(AND(K33>0,J33>0,V33>0,U33>0),V33-U33,"") | AC33: =IF(AB33<>"",AB33/U33,"") | AD33: 0 | AE33: 0 | AF33: 0 | AG33: =AD33+AE33+AF33 -> 0 | AH33: =IF(AG33>0,AD33/AG33,"") | AI33: 0 | AJ33: 0 | AK33: 0 | AL33: =IF(OR(AJ33>0,AK33>0),"Sí","No") -> No | AO33: =IF(M33>0,K33/M33,"") -> 1 | AP33: =IF(M33>=Resumen!$B$5,"Alto","Bajo") -> Bajo | AQ33: =IF(AO33>=Resumen!$B$28,"Alto","Bajo") -> Alto | AR33: =AP33&" Potencial / "&AQ33&" Share" -> Bajo Potencial / Alto Share | AS33: =IF(Q33="Sí",IF(AO33>=Resumen!$B$29,"Alto","Bajo"),"") | AT33: =IF(AS33<>"",AP33&" Potencial / "&AS33&" Share","") | AU33: =IF(AH33="","Sin dato",IF(AH33-AO33>Resumen!$B$6,"Sobre-exhibido",IF(AO33-AH33>Resumen!$B$6,"Sub-exhibido","En línea"))) -> Sin dato | AV33: =IF(AT33="","",IF(AT33="Alto Potencial / Bajo Share",1,IF(AT33="Alto Potencial / Alto Share",2,IF(AT33="Bajo Potencial / Alto Share",3,4)))) | AW33: =IF(Q33="No","Sin competencia directa",IF(AV33=1,"1 - Foco Conquista (Alto Pot / Bajo Share)",IF(AV33=2,"2 - Foco Defensa (Alto Pot / Alto Share)",IF(AV33=3,"3 - Monitoreo (Bajo Pot / Alto Share)","4 - Baja Prioridad (Bajo Pot / Bajo Share)")))) -> Sin competencia directa | AX33: =IF(OR(IFERROR(AND(W33<>"",Y33<>"",Y33-W33>Resumen!$B$8),FALSE()),IFERROR(AND(X33<>"",Y33<>"",Y33-X33>Resumen!$B$8),FALSE())),MAX(IF(IFERROR(AND(W33<>"",Y33<>"",Y33-W33>Resumen!$B$8),FALSE()),Y33-W33,0),IF(IFERROR(AND(X33<>"",Y33<>"",Y33-X33>Resumen!$B$8),FALSE()),Y33-X33,0)),"") | AY33: =IF(OR(IFERROR(AND(W33<>"",Y33<>"",Y33-W33>Resumen!$B$8),FALSE()),IFERROR(AND(X33<>"",Y33<>"",Y33-X33>Resumen!$B$8),FALSE())),TRIM("Lays tiene mayor markup que "&IF(IFERROR(AND(W33<>"",Y33<>"",Y33-W33>Resumen!$B$8),FALSE()),"Quento ","")&IF(IFERROR(AND(X33<>"",Y33<>"",Y33-X33>Resumen!$B$8),FALSE()),"Julicroc ","")&"en este PDV"),"") | AZ33: =IF(COUNTIF('Plan Pehuamar - Lista'!$A$2:$A$167,A33)>0,"Sí","No") -> No | BA33: =IF(COUNTIF('Plan Combo 9+1'!$A$2:$A$226,A33)>0,"Sí","No") -> No | BB33: =IF(AH33="","No",IF(BA33="Sí",IF((AO33-AH33)>Resumen!$B$6,"Sí","No"),IF((AO33-AH33)>=Resumen!$B$132,"Sí","No"))) -> No | BC33: =IF(AND(N33="Sí",AL33="Sí",AI33=0),"Sí","No") -> No | BD33: =IF(COUNTIF('Plan 9+1 (con Pehuamar)'!$A$2:$A$227,A33)>0,"Sí","No") -> No
A34: 403438 | B34: 1 | C34: 101 | D34: Lunes | E34: Karina Schmidt | F34: Almacen/Despensa | G34: Santa Fe | H34: Conrado Pujol | I34: 0 | J34: 0 | K34: 0.6 | L34: =I34+J34 -> 0 | M34: =L34+K34 -> 0.6 | N34: =IF(I34>0,"Sí","No") -> No | O34: =IF(J34>0,"Sí","No") -> No | P34: =IF(K34>0,"Sí","No") -> Sí | Q34: =IF(OR(I34>0,J34>0),"Sí","No") -> No | W34: =IF(AND(I34>0,R34>0),(S34-R34)/R34,"") | X34: =IF(AND(J34>0,T34>0),(U34-T34)/T34,"") | Y34: =IF(AND(K34>0,V34>0),(V34-Resumen!$B$7)/Resumen!$B$7,"") | Z34: =IF(AND(K34>0,I34>0,V34>0,S34>0),V34-S34,"") | AA34: =IF(Z34<>"",Z34/S34,"") | AB34: =IF(AND(K34>0,J34>0,V34>0,U34>0),V34-U34,"") | AC34: =IF(AB34<>"",AB34/U34,"") | AD34: 0 | AE34: 0 | AF34: 0 | AG34: =AD34+AE34+AF34 -> 0 | AH34: =IF(AG34>0,AD34/AG34,"") | AI34: 0 | AJ34: 0 | AK34: 0 | AL34: =IF(OR(AJ34>0,AK34>0),"Sí","No") -> No | AO34: =IF(M34>0,K34/M34,"") -> 1 | AP34: =IF(M34>=Resumen!$B$5,"Alto","Bajo") -> Bajo | AQ34: =IF(AO34>=Resumen!$B$28,"Alto","Bajo") -> Alto | AR34: =AP34&" Potencial / "&AQ34&" Share" -> Bajo Potencial / Alto Share | AS34: =IF(Q34="Sí",IF(AO34>=Resumen!$B$29,"Alto","Bajo"),"") | AT34: =IF(AS34<>"",AP34&" Potencial / "&AS34&" Share","") | AU34: =IF(AH34="","Sin dato",IF(AH34-AO34>Resumen!$B$6,"Sobre-exhibido",IF(AO34-AH34>Resumen!$B$6,"Sub-exhibido","En línea"))) -> Sin dato | AV34: =IF(AT34="","",IF(AT34="Alto Potencial / Bajo Share",1,IF(AT34="Alto Potencial / Alto Share",2,IF(AT34="Bajo Potencial / Alto Share",3,4)))) | AW34: =IF(Q34="No","Sin competencia directa",IF(AV34=1,"1 - Foco Conquista (Alto Pot / Bajo Share)",IF(AV34=2,"2 - Foco Defensa (Alto Pot / Alto Share)",IF(AV34=3,"3 - Monitoreo (Bajo Pot / Alto Share)","4 - Baja Prioridad (Bajo Pot / Bajo Share)")))) -> Sin competencia directa | AX34: =IF(OR(IFERROR(AND(W34<>"",Y34<>"",Y34-W34>Resumen!$B$8),FALSE()),IFERROR(AND(X34<>"",Y34<>"",Y34-X34>Resumen!$B$8),FALSE())),MAX(IF(IFERROR(AND(W34<>"",Y34<>"",Y34-W34>Resumen!$B$8),FALSE()),Y34-W34,0),IF(IFERROR(AND(X34<>"",Y34<>"",Y34-X34>Resumen!$B$8),FALSE()),Y34-X34,0)),"") | AY34: =IF(OR(IFERROR(AND(W34<>"",Y34<>"",Y34-W34>Resumen!$B$8),FALSE()),IFERROR(AND(X34<>"",Y34<>"",Y34-X34>Resumen!$B$8),FALSE())),TRIM("Lays tiene mayor markup que "&IF(IFERROR(AND(W34<>"",Y34<>"",Y34-W34>Resumen!$B$8),FALSE()),"Quento ","")&IF(IFERROR(AND(X34<>"",Y34<>"",Y34-X34>Resumen!$B$8),FALSE()),"Julicroc ","")&"en este PDV"),"") | AZ34: =IF(COUNTIF('Plan Pehuamar - Lista'!$A$2:$A$167,A34)>0,"Sí","No") -> No | BA34: =IF(COUNTIF('Plan Combo 9+1'!$A$2:$A$226,A34)>0,"Sí","No") -> No | BB34: =IF(AH34="","No",IF(BA34="Sí",IF((AO34-AH34)>Resumen!$B$6,"Sí","No"),IF((AO34-AH34)>=Resumen!$B$132,"Sí","No"))) -> No | BC34: =IF(AND(N34="Sí",AL34="Sí",AI34=0),"Sí","No") -> No | BD34: =IF(COUNTIF('Plan 9+1 (con Pehuamar)'!$A$2:$A$227,A34)>0,"Sí","No") -> No
A35: 403458 | B35: 1 | C35: 101 | D35: Lunes | E35: Alicia Silvia Ferrero | F35: Almacen/Despensa | G35: Santa Fe | H35: Conrado Pujol | I35: 0 | J35: 0 | K35: 0.6 | L35: =I35+J35 -> 0 | M35: =L35+K35 -> 0.6 | N35: =IF(I35>0,"Sí","No") -> No | O35: =IF(J35>0,"Sí","No") -> No | P35: =IF(K35>0,"Sí","No") -> Sí | Q35: =IF(OR(I35>0,J35>0),"Sí","No") -> No | W35: =IF(AND(I35>0,R35>0),(S35-R35)/R35,"") | X35: =IF(AND(J35>0,T35>0),(U35-T35)/T35,"") | Y35: =IF(AND(K35>0,V35>0),(V35-Resumen!$B$7)/Resumen!$B$7,"") | Z35: =IF(AND(K35>0,I35>0,V35>0,S35>0),V35-S35,"") | AA35: =IF(Z35<>"",Z35/S35,"") | AB35: =IF(AND(K35>0,J35>0,V35>0,U35>0),V35-U35,"") | AC35: =IF(AB35<>"",AB35/U35,"") | AD35: 0 | AE35: 0 | AF35: 0 | AG35: =AD35+AE35+AF35 -> 0 | AH35: =IF(AG35>0,AD35/AG35,"") | AI35: 0 | AJ35: 0 | AK35: 0 | AL35: =IF(OR(AJ35>0,AK35>0),"Sí","No") -> No | AO35: =IF(M35>0,K35/M35,"") -> 1 | AP35: =IF(M35>=Resumen!$B$5,"Alto","Bajo") -> Bajo | AQ35: =IF(AO35>=Resumen!$B$28,"Alto","Bajo") -> Alto | AR35: =AP35&" Potencial / "&AQ35&" Share" -> Bajo Potencial / Alto Share | AS35: =IF(Q35="Sí",IF(AO35>=Resumen!$B$29,"Alto","Bajo"),"") | AT35: =IF(AS35<>"",AP35&" Potencial / "&AS35&" Share","") | AU35: =IF(AH35="","Sin dato",IF(AH35-AO35>Resumen!$B$6,"Sobre-exhibido",IF(AO35-AH35>Resumen!$B$6,"Sub-exhibido","En línea"))) -> Sin dato | AV35: =IF(AT35="","",IF(AT35="Alto Potencial / Bajo Share",1,IF(AT35="Alto Potencial / Alto Share",2,IF(AT35="Bajo Potencial / Alto Share",3,4)))) | AW35: =IF(Q35="No","Sin competencia directa",IF(AV35=1,"1 - Foco Conquista (Alto Pot / Bajo Share)",IF(AV35=2,"2 - Foco Defensa (Alto Pot / Alto Share)",IF(AV35=3,"3 - Monitoreo (Bajo Pot / Alto Share)","4 - Baja Prioridad (Bajo Pot / Bajo Share)")))) -> Sin competencia directa | AX35: =IF(OR(IFERROR(AND(W35<>"",Y35<>"",Y35-W35>Resumen!$B$8),FALSE()),IFERROR(AND(X35<>"",Y35<>"",Y35-X35>Resumen!$B$8),FALSE())),MAX(IF(IFERROR(AND(W35<>"",Y35<>"",Y35-W35>Resumen!$B$8),FALSE()),Y35-W35,0),IF(IFERROR(AND(X35<>"",Y35<>"",Y35-X35>Resumen!$B$8),FALSE()),Y35-X35,0)),"") | AY35: =IF(OR(IFERROR(AND(W35<>"",Y35<>"",Y35-W35>Resumen!$B$8),FALSE()),IFERROR(AND(X35<>"",Y35<>"",Y35-X35>Resumen!$B$8),FALSE())),TRIM("Lays tiene mayor markup que "&IF(IFERROR(AND(W35<>"",Y35<>"",Y35-W35>Resumen!$B$8),FALSE()),"Quento ","")&IF(IFERROR(AND(X35<>"",Y35<>"",Y35-X35>Resumen!$B$8),FALSE()),"Julicroc ","")&"en este PDV"),"") | AZ35: =IF(COUNTIF('Plan Pehuamar - Lista'!$A$2:$A$167,A35)>0,"Sí","No") -> No | BA35: =IF(COUNTIF('Plan Combo 9+1'!$A$2:$A$226,A35)>0,"Sí","No") -> No | BB35: =IF(AH35="","No",IF(BA35="Sí",IF((AO35-AH35)>Resumen!$B$6,"Sí","No"),IF((AO35-AH35)>=Resumen!$B$132,"Sí","No"))) -> No | BC35: =IF(AND(N35="Sí",AL35="Sí",AI35=0),"Sí","No") -> No | BD35: =IF(COUNTIF('Plan 9+1 (con Pehuamar)'!$A$2:$A$227,A35)>0,"Sí","No") -> No
A36: 403459 | B36: 1 | C36: 101 | D36: Lunes | E36: Quinteros Laura Verónica | F36: Almacen/Despensa | G36: Santa Fe | H36: Conrado Pujol | I36: 0 | J36: 0 | K36: 0.2 | L36: =I36+J36 -> 0 | M36: =L36+K36 -> 0.2 | N36: =IF(I36>0,"Sí","No") -> No | O36: =IF(J36>0,"Sí","No") -> No | P36: =IF(K36>0,"Sí","No") -> Sí | Q36: =IF(OR(I36>0,J36>0),"Sí","No") -> No | W36: =IF(AND(I36>0,R36>0),(S36-R36)/R36,"") | X36: =IF(AND(J36>0,T36>0),(U36-T36)/T36,"") | Y36: =IF(AND(K36>0,V36>0),(V36-Resumen!$B$7)/Resumen!$B$7,"") | Z36: =IF(AND(K36>0,I36>0,V36>0,S36>0),V36-S36,"") | AA36: =IF(Z36<>"",Z36/S36,"") | AB36: =IF(AND(K36>0,J36>0,V36>0,U36>0),V36-U36,"") | AC36: =IF(AB36<>"",AB36/U36,"") | AD36: 0 | AE36: 0 | AF36: 0 | AG36: =AD36+AE36+AF36 -> 0 | AH36: =IF(AG36>0,AD36/AG36,"") | AI36: 0 | AJ36: 0 | AK36: 0 | AL36: =IF(OR(AJ36>0,AK36>0),"Sí","No") -> No | AO36: =IF(M36>0,K36/M36,"") -> 1 | AP36: =IF(M36>=Resumen!$B$5,"Alto","Bajo") -> Bajo | AQ36: =IF(AO36>=Resumen!$B$28,"Alto","Bajo") -> Alto | AR36: =AP36&" Potencial / "&AQ36&" Share" -> Bajo Potencial / Alto Share | AS36: =IF(Q36="Sí",IF(AO36>=Resumen!$B$29,"Alto","Bajo"),"") | AT36: =IF(AS36<>"",AP36&" Potencial / "&AS36&" Share","") | AU36: =IF(AH36="","Sin dato",IF(AH36-AO36>Resumen!$B$6,"Sobre-exhibido",IF(AO36-AH36>Resumen!$B$6,"Sub-exhibido","En línea"))) -> Sin dato | AV36: =IF(AT36="","",IF(AT36="Alto Potencial / Bajo Share",1,IF(AT36="Alto Potencial / Alto Share",2,IF(AT36="Bajo Potencial / Alto Share",3,4)))) | AW36: =IF(Q36="No","Sin competencia directa",IF(AV36=1,"1 - Foco Conquista (Alto Pot / Bajo Share)",IF(AV36=2,"2 - Foco Defensa (Alto Pot / Alto Share)",IF(AV36=3,"3 - Monitoreo (Bajo Pot / Alto Share)","4 - Baja Prioridad (Bajo Pot / Bajo Share)")))) -> Sin competencia directa | AX36: =IF(OR(IFERROR(AND(W36<>"",Y36<>"",Y36-W36>Resumen!$B$8),FALSE()),IFERROR(AND(X36<>"",Y36<>"",Y36-X36>Resumen!$B$8),FALSE())),MAX(IF(IFERROR(AND(W36<>"",Y36<>"",Y36-W36>Resumen!$B$8),FALSE()),Y36-W36,0),IF(IFERROR(AND(X36<>"",Y36<>"",Y36-X36>Resumen!$B$8),FALSE()),Y36-X36,0)),"") | AY36: =IF(OR(IFERROR(AND(W36<>"",Y36<>"",Y36-W36>Resumen!$B$8),FALSE()),IFERROR(AND(X36<>"",Y36<>"",Y36-X36>Resumen!$B$8),FALSE())),TRIM("Lays tiene mayor markup que "&IF(IFERROR(AND(W36<>"",Y36<>"",Y36-W36>Resumen!$B$8),FALSE()),"Quento ","")&IF(IFERROR(AND(X36<>"",Y36<>"",Y36-X36>Resumen!$B$8),FALSE()),"Julicroc ","")&"en este PDV"),"") | AZ36: =IF(COUNTIF('Plan Pehuamar - Lista'!$A$2:$A$167,A36)>0,"Sí","No") -> No | BA36: =IF(COUNTIF('Plan Combo 9+1'!$A$2:$A$226,A36)>0,"Sí","No") -> No | BB36: =IF(AH36="","No",IF(BA36="Sí",IF((AO36-AH36)>Resumen!$B$6,"Sí","No"),IF((AO36-AH36)>=Resumen!$B$132,"Sí","No"))) -> No | BC36: =IF(AND(N36="Sí",AL36="Sí",AI36=0),"Sí","No") -> No | BD36: =IF(COUNTIF('Plan 9+1 (con Pehuamar)'!$A$2:$A$227,A36)>0,"Sí","No") -> No
A37: 403774 | B37: 1 | C37: 101 | D37: Lunes | E37: HOFFMANN VIVIANA | F37: Almacen/Despensa | G37: Santa Fe | H37: Conrado Pujol | I37: 0 | J37: 0 | K37: 3 | L37: =I37+J37 -> 0 | M37: =L37+K37 -> 3 | N37: =IF(I37>0,"Sí","No") -> No | O37: =IF(J37>0,"Sí","No") -> No | P37: =IF(K37>0,"Sí","No") -> Sí | Q37: =IF(OR(I37>0,J37>0),"Sí","No") -> No | W37: =IF(AND(I37>0,R37>0),(S37-R37)/R37,"") | X37: =IF(AND(J37>0,T37>0),(U37-T37)/T37,"") | Y37: =IF(AND(K37>0,V37>0),(V37-Resumen!$B$7)/Resumen!$B$7,"") | Z37: =IF(AND(K37>0,I37>0,V37>0,S37>0),V37-S37,"") | AA37: =IF(Z37<>"",Z37/S37,"") | AB37: =IF(AND(K37>0,J37>0,V37>0,U37>0),V37-U37,"") | AC37: =IF(AB37<>"",AB37/U37,"") | AD37: 0 | AE37: 0 | AF37: 0 | AG37: =AD37+AE37+AF37 -> 0 | AH37: =IF(AG37>0,AD37/AG37,"") | AI37: 0 | AJ37: 0 | AK37: 0 | AL37: =IF(OR(AJ37>0,AK37>0),"Sí","No") -> No | AO37: =IF(M37>0,K37/M37,"") -> 1 | AP37: =IF(M37>=Resumen!$B$5,"Alto","Bajo") -> Bajo | AQ37: =IF(AO37>=Resumen!$B$28,"Alto","Bajo") -> Alto | AR37: =AP37&" Potencial / "&AQ37&" Share" -> Bajo Potencial / Alto Share | AS37: =IF(Q37="Sí",IF(AO37>=Resumen!$B$29,"Alto","Bajo"),"") | AT37: =IF(AS37<>"",AP37&" Potencial / "&AS37&" Share","") | AU37: =IF(AH37="","Sin dato",IF(AH37-AO37>Resumen!$B$6,"Sobre-exhibido",IF(AO37-AH37>Resumen!$B$6,"Sub-exhibido","En línea"))) -> Sin dato | AV37: =IF(AT37="","",IF(AT37="Alto Potencial / Bajo Share",1,IF(AT37="Alto Potencial / Alto Share",2,IF(AT37="Bajo Potencial / Alto Share",3,4)))) | AW37: =IF(Q37="No","Sin competencia directa",IF(AV37=1,"1 - Foco Conquista (Alto Pot / Bajo Share)",IF(AV37=2,"2 - Foco Defensa (Alto Pot / Alto Share)",IF(AV37=3,"3 - Monitoreo (Bajo Pot / Alto Share)","4 - Baja Prioridad (Bajo Pot / Bajo Share)")))) -> Sin competencia directa | AX37: =IF(OR(IFERROR(AND(W37<>"",Y37<>"",Y37-W37>Resumen!$B$8),FALSE()),IFERROR(AND(X37<>"",Y37<>"",Y37-X37>Resumen!$B$8),FALSE())),MAX(IF(IFERROR(AND(W37<>"",Y37<>"",Y37-W37>Resumen!$B$8),FALSE()),Y37-W37,0),IF(IFERROR(AND(X37<>"",Y37<>"",Y37-X37>Resumen!$B$8),FALSE()),Y37-X37,0)),"") | AY37: =IF(OR(IFERROR(AND(W37<>"",Y37<>"",Y37-W37>Resumen!$B$8),FALSE()),IFERROR(AND(X37<>"",Y37<>"",Y37-X37>Resumen!$B$8),FALSE())),TRIM("Lays tiene mayor markup que "&IF(IFERROR(AND(W37<>"",Y37<>"",Y37-W37>Resumen!$B$8),FALSE()),"Quento ","")&IF(IFERROR(AND(X37<>"",Y37<>"",Y37-X37>Resumen!$B$8),FALSE()),"Julicroc ","")&"en este PDV"),"") | AZ37: =IF(COUNTIF('Plan Pehuamar - Lista'!$A$2:$A$167,A37)>0,"Sí","No") -> No | BA37: =IF(COUNTIF('Plan Combo 9+1'!$A$2:$A$226,A37)>0,"Sí","No") -> No | BB37: =IF(AH37="","No",IF(BA37="Sí",IF((AO37-AH37)>Resumen!$B$6,"Sí","No"),IF((AO37-AH37)>=Resumen!$B$132,"Sí","No"))) -> No | BC37: =IF(AND(N37="Sí",AL37="Sí",AI37=0),"Sí","No") -> No | BD37: =IF(COUNTIF('Plan 9+1 (con Pehuamar)'!$A$2:$A$227,A37)>0,"Sí","No") -> No
A38: 404028 | B38: 1 | C38: 101 | D38: Lunes | E38: BUSTOS GUADALUPE ALICIA | F38: Almacen/Despensa | G38: Santa Fe | H38: Conrado Pujol | I38: 0 | J38: 0 | K38: 0.4 | L38: =I38+J38 -> 0 | M38: =L38+K38 -> 0.4 | N38: =IF(I38>0,"Sí","No") -> No | O38: =IF(J38>0,"Sí","No") -> No | P38: =IF(K38>0,"Sí","No") -> Sí | Q38: =IF(OR(I38>0,J38>0),"Sí","No") -> No | W38: =IF(AND(I38>0,R38>0),(S38-R38)/R38,"") | X38: =IF(AND(J38>0,T38>0),(U38-T38)/T38,"") | Y38: =IF(AND(K38>0,V38>0),(V38-Resumen!$B$7)/Resumen!$B$7,"") | Z38: =IF(AND(K38>0,I38>0,V38>0,S38>0),V38-S38,"") | AA38: =IF(Z38<>"",Z38/S38,"") | AB38: =IF(AND(K38>0,J38>0,V38>0,U38>0),V38-U38,"") | AC38: =IF(AB38<>"",AB38/U38,"") | AD38: 0 | AE38: 0 | AF38: 0 | AG38: =AD38+AE38+AF38 -> 0 | AH38: =IF(AG38>0,AD38/AG38,"") | AI38: 0 | AJ38: 0 | AK38: 0 | AL38: =IF(OR(AJ38>0,AK38>0),"Sí","No") -> No | AO38: =IF(M38>0,K38/M38,"") -> 1 | AP38: =IF(M38>=Resumen!$B$5,"Alto","Bajo") -> Bajo | AQ38: =IF(AO38>=Resumen!$B$28,"Alto","Bajo") -> Alto | AR38: =AP38&" Potencial / "&AQ38&" Share" -> Bajo Potencial / Alto Share | AS38: =IF(Q38="Sí",IF(AO38>=Resumen!$B$29,"Alto","Bajo"),"") | AT38: =IF(AS38<>"",AP38&" Potencial / "&AS38&" Share","") | AU38: =IF(AH38="","Sin dato",IF(AH38-AO38>Resumen!$B$6,"Sobre-exhibido",IF(AO38-AH38>Resumen!$B$6,"Sub-exhibido","En línea"))) -> Sin dato | AV38: =IF(AT38="","",IF(AT38="Alto Potencial / Bajo Share",1,IF(AT38="Alto Potencial / Alto Share",2,IF(AT38="Bajo Potencial / Alto Share",3,4)))) | AW38: =IF(Q38="No","Sin competencia directa",IF(AV38=1,"1 - Foco Conquista (Alto Pot / Bajo Share)",IF(AV38=2,"2 - Foco Defensa (Alto Pot / Alto Share)",IF(AV38=3,"3 - Monitoreo (Bajo Pot / Alto Share)","4 - Baja Prioridad (Bajo Pot / Bajo Share)")))) -> Sin competencia directa | AX38: =IF(OR(IFERROR(AND(W38<>"",Y38<>"",Y38-W38>Resumen!$B$8),FALSE()),IFERROR(AND(X38<>"",Y38<>"",Y38-X38>Resumen!$B$8),FALSE())),MAX(IF(IFERROR(AND(W38<>"",Y38<>"",Y38-W38>Resumen!$B$8),FALSE()),Y38-W38,0),IF(IFERROR(AND(X38<>"",Y38<>"",Y38-X38>Resumen!$B$8),FALSE()),Y38-X38,0)),"") | AY38: =IF(OR(IFERROR(AND(W38<>"",Y38<>"",Y38-W38>Resumen!$B$8),FALSE()),IFERROR(AND(X38<>"",Y38<>"",Y38-X38>Resumen!$B$8),FALSE())),TRIM("Lays tiene mayor markup que "&IF(IFERROR(AND(W38<>"",Y38<>"",Y38-W38>Resumen!$B$8),FALSE()),"Quento ","")&IF(IFERROR(AND(X38<>"",Y38<>"",Y38-X38>Resumen!$B$8),FALSE()),"Julicroc ","")&"en este PDV"),"") | AZ38: =IF(COUNTIF('Plan Pehuamar - Lista'!$A$2:$A$167,A38)>0,"Sí","No") -> No | BA38: =IF(COUNTIF('Plan Combo 9+1'!$A$2:$A$226,A38)>0,"Sí","No") -> No | BB38: =IF(AH38="","No",IF(BA38="Sí",IF((AO38-AH38)>Resumen!$B$6,"Sí","No"),IF((AO38-AH38)>=Resumen!$B$132,"Sí","No"))) -> No | BC38: =IF(AND(N38="Sí",AL38="Sí",AI38=0),"Sí","No") -> No | BD38: =IF(COUNTIF('Plan 9+1 (con Pehuamar)'!$A$2:$A$227,A38)>0,"Sí","No") -> No
A39: 404031 | B39: 1 | C39: 101 | D39: Lunes | E39: MAIDANA DAVID | F39: Kiosco/Maxikiosco | G39: Santa Fe | H39: Conrado Pujol | I39: 0 | J39: 0 | K39: 0.8 | L39: =I39+J39 -> 0 | M39: =L39+K39 -> 0.8 | N39: =IF(I39>0,"Sí","No") -> No | O39: =IF(J39>0,"Sí","No") -> No | P39: =IF(K39>0,"Sí","No") -> Sí | Q39: =IF(OR(I39>0,J39>0),"Sí","No") -> No | W39: =IF(AND(I39>0,R39>0),(S39-R39)/R39,"") | X39: =IF(AND(J39>0,T39>0),(U39-T39)/T39,"") | Y39: =IF(AND(K39>0,V39>0),(V39-Resumen!$B$7)/Resumen!$B$7,"") | Z39: =IF(AND(K39>0,I39>0,V39>0,S39>0),V39-S39,"") | AA39: =IF(Z39<>"",Z39/S39,"") | AB39: =IF(AND(K39>0,J39>0,V39>0,U39>0),V39-U39,"") | AC39: =IF(AB39<>"",AB39/U39,"") | AD39: 0 | AE39: 0 | AF39: 0 | AG39: =AD39+AE39+AF39 -> 0 | AH39: =IF(AG39>0,AD39/AG39,"") | AI39: 0 | AJ39: 0 | AK39: 0 | AL39: =IF(OR(AJ39>0,AK39>0),"Sí","No") -> No | AO39: =IF(M39>0,K39/M39,"") -> 1 | AP39: =IF(M39>=Resumen!$B$5,"Alto","Bajo") -> Bajo | AQ39: =IF(AO39>=Resumen!$B$28,"Alto","Bajo") -> Alto | AR39: =AP39&" Potencial / "&AQ39&" Share" -> Bajo Potencial / Alto Share | AS39: =IF(Q39="Sí",IF(AO39>=Resumen!$B$29,"Alto","Bajo"),"") | AT39: =IF(AS39<>"",AP39&" Potencial / "&AS39&" Share","") | AU39: =IF(AH39="","Sin dato",IF(AH39-AO39>Resumen!$B$6,"Sobre-exhibido",IF(AO39-AH39>Resumen!$B$6,"Sub-exhibido","En línea"))) -> Sin dato | AV39: =IF(AT39="","",IF(AT39="Alto Potencial / Bajo Share",1,IF(AT39="Alto Potencial / Alto Share",2,IF(AT39="Bajo Potencial / Alto Share",3,4)))) | AW39: =IF(Q39="No","Sin competencia directa",IF(AV39=1,"1 - Foco Conquista (Alto Pot / Bajo Share)",IF(AV39=2,"2 - Foco Defensa (Alto Pot / Alto Share)",IF(AV39=3,"3 - Monitoreo (Bajo Pot / Alto Share)","4 - Baja Prioridad (Bajo Pot / Bajo Share)")))) -> Sin competencia directa | AX39: =IF(OR(IFERROR(AND(W39<>"",Y39<>"",Y39-W39>Resumen!$B$8),FALSE()),IFERROR(AND(X39<>"",Y39<>"",Y39-X39>Resumen!$B$8),FALSE())),MAX(IF(IFERROR(AND(W39<>"",Y39<>"",Y39-W39>Resumen!$B$8),FALSE()),Y39-W39,0),IF(IFERROR(AND(X39<>"",Y39<>"",Y39-X39>Resumen!$B$8),FALSE()),Y39-X39,0)),"") | AY39: =IF(OR(IFERROR(AND(W39<>"",Y39<>"",Y39-W39>Resumen!$B$8),FALSE()),IFERROR(AND(X39<>"",Y39<>"",Y39-X39>Resumen!$B$8),FALSE())),TRIM("Lays tiene mayor markup que "&IF(IFERROR(AND(W39<>"",Y39<>"",Y39-W39>Resumen!$B$8),FALSE()),"Quento ","")&IF(IFERROR(AND(X39<>"",Y39<>"",Y39-X39>Resumen!$B$8),FALSE()),"Julicroc ","")&"en este PDV"),"") | AZ39: =IF(COUNTIF('Plan Pehuamar - Lista'!$A$2:$A$167,A39)>0,"Sí","No") -> No | BA39: =IF(COUNTIF('Plan Combo 9+1'!$A$2:$A$226,A39)>0,"Sí","No") -> No | BB39: =IF(AH39="","No",IF(BA39="Sí",IF((AO39-AH39)>Resumen!$B$6,"Sí","No"),IF((AO39-AH39)>=Resumen!$B$132,"Sí","No"))) -> No | BC39: =IF(AND(N39="Sí",AL39="Sí",AI39=0),"Sí","No") -> No | BD39: =IF(COUNTIF('Plan 9+1 (con Pehuamar)'!$A$2:$A$227,A39)>0,"Sí","No") -> No
A40: 404033 | B40: 1 | C40: 101 | D40: Lunes | E40: CEPEDA ALEJANDRA | F40: Kiosco/Maxikiosco | G40: Santa Fe | H40: Conrado Pujol | I40: 0 | J40: 0 | K40: 0.2 | L40: =I40+J40 -> 0 | M40: =L40+K40 -> 0.2 | N40: =IF(I40>0,"Sí","No") -> No | O40: =IF(J40>0,"Sí","No") -> No | P40: =IF(K40>0,"Sí","No") -> Sí | Q40: =IF(OR(I40>0,J40>0),"Sí","No") -> No | W40: =IF(AND(I40>0,R40>0),(S40-R40)/R40,"") | X40: =IF(AND(J40>0,T40>0),(U40-T40)/T40,"") | Y40: =IF(AND(K40>0,V40>0),(V40-Resumen!$B$7)/Resumen!$B$7,"") | Z40: =IF(AND(K40>0,I40>0,V40>0,S40>0),V40-S40,"") | AA40: =IF(Z40<>"",Z40/S40,"") | AB40: =IF(AND(K40>0,J40>0,V40>0,U40>0),V40-U40,"") | AC40: =IF(AB40<>"",AB40/U40,"") | AD40: 0 | AE40: 0 | AF40: 0 | AG40: =AD40+AE40+AF40 -> 0 | AH40: =IF(AG40>0,AD40/AG40,"") | AI40: 0 | AJ40: 0 | AK40: 0 | AL40: =IF(OR(AJ40>0,AK40>0),"Sí","No") -> No | AO40: =IF(M40>0,K40/M40,"") -> 1 | AP40: =IF(M40>=Resumen!$B$5,"Alto","Bajo") -> Bajo | AQ40: =IF(AO40>=Resumen!$B$28,"Alto","Bajo") -> Alto | AR40: =AP40&" Potencial / "&AQ40&" Share" -> Bajo Potencial / Alto Share | AS40: =IF(Q40="Sí",IF(AO40>=Resumen!$B$29,"Alto","Bajo"),"") | AT40: =IF(AS40<>"",AP40&" Potencial / "&AS40&" Share","") | AU40: =IF(AH40="","Sin dato",IF(AH40-AO40>Resumen!$B$6,"Sobre-exhibido",IF(AO40-AH40>Resumen!$B$6,"Sub-exhibido","En línea"))) -> Sin dato | AV40: =IF(AT40="","",IF(AT40="Alto Potencial / Bajo Share",1,IF(AT40="Alto Potencial / Alto Share",2,IF(AT40="Bajo Potencial / Alto Share",3,4)))) | AW40: =IF(Q40="No","Sin competencia directa",IF(AV40=1,"1 - Foco Conquista (Alto Pot / Bajo Share)",IF(AV40=2,"2 - Foco Defensa (Alto Pot / Alto Share)",IF(AV40=3,"3 - Monitoreo (Bajo Pot / Alto Share)","4 - Baja Prioridad (Bajo Pot / Bajo Share)")))) -> Sin competencia directa | AX40: =IF(OR(IFERROR(AND(W40<>"",Y40<>"",Y40-W40>Resumen!$B$8),FALSE()),IFERROR(AND(X40<>"",Y40<>"",Y40-X40>Resumen!$B$8),FALSE())),MAX(IF(IFERROR(AND(W40<>"",Y40<>"",Y40-W40>Resumen!$B$8),FALSE()),Y40-W40,0),IF(IFERROR(AND(X40<>"",Y40<>"",Y40-X40>Resumen!$B$8),FALSE()),Y40-X40,0)),"") | AY40: =IF(OR(IFERROR(AND(W40<>"",Y40<>"",Y40-W40>Resumen!$B$8),FALSE()),IFERROR(AND(X40<>"",Y40<>"",Y40-X40>Resumen!$B$8),FALSE())),TRIM("Lays tiene mayor markup que "&IF(IFERROR(AND(W40<>"",Y40<>"",Y40-W40>Resumen!$B$8),FALSE()),"Quento ","")&IF(IFERROR(AND(X40<>"",Y40<>"",Y40-X40>Resumen!$B$8),FALSE()),"Julicroc ","")&"en este PDV"),"") | AZ40: =IF(COUNTIF('Plan Pehuamar - Lista'!$A$2:$A$167,A40)>0,"Sí","No") -> No | BA40: =IF(COUNTIF('Plan Combo 9+1'!$A$2:$A$226,A40)>0,"Sí","No") -> No | BB40: =IF(AH40="","No",IF(BA40="Sí",IF((AO40-AH40)>Resumen!$B$6,"Sí","No"),IF((AO40-AH40)>=Resumen!$B$132,"Sí","No"))) -> No | BC40: =IF(AND(N40="Sí",AL40="Sí",AI40=0),"Sí","No") -> No | BD40: =IF(COUNTIF('Plan 9+1 (con Pehuamar)'!$A$2:$A$227,A40)>0,"Sí","No") -> No
A41: 404074 | B41: 1 | C41: 101 | D41: Lunes | E41: Martínez Javier Alejandro | F41: Autoservicio Tradicional | G41: Santa Fe | H41: Conrado Pujol | I41: 10 | J41: 25 | K41: 30 | L41: =I41+J41 -> 35 | M41: =L41+K41 -> 65 | N41: =IF(I41>0,"Sí","No") -> Sí | O41: =IF(J41>0,"Sí","No") -> Sí | P41: =IF(K41>0,"Sí","No") -> Sí | Q41: =IF(OR(I41>0,J41>0),"Sí","No") -> Sí | R41: 1750 | S41: 2500 | T41: 1700 | U41: 2600 | V41: 3700 | W41: =IF(AND(I41>0,R41>0),(S41-R41)/R41,"") -> 0.42857143 | X41: =IF(AND(J41>0,T41>0),(U41-T41)/T41,"") -> 0.52941176 | Y41: =IF(AND(K41>0,V41>0),(V41-Resumen!$B$7)/Resumen!$B$7,"") -> 0.48 | Z41: =IF(AND(K41>0,I41>0,V41>0,S41>0),V41-S41,"") -> 1200 | AA41: =IF(Z41<>"",Z41/S41,"") -> 0.48 | AB41: =IF(AND(K41>0,J41>0,V41>0,U41>0),V41-U41,"") -> 1100 | AC41: =IF(AB41<>"",AB41/U41,"") -> 0.42307692 | AD41: 4 | AE41: 2 | AF41: 5 | AG41: =AD41+AE41+AF41 -> 11 | AH41: =IF(AG41>0,AD41/AG41,"") -> 0.36363636 | AI41: 0 | AJ41: 0 | AK41: 1 | AL41: =IF(OR(AJ41>0,AK41>0),"Sí","No") -> Sí | AM41: Contado | AN41: Contado | AO41: =IF(M41>0,K41/M41,"") -> 0.46153846 | AP41: =IF(M41>=Resumen!$B$5,"Alto","Bajo") -> Alto | AQ41: =IF(AO41>=Resumen!$B$28,"Alto","Bajo") -> Alto | AR41: =AP41&" Potencial / "&AQ41&" Share" -> Alto Potencial / Alto Share | AS41: =IF(Q41="Sí",IF(AO41>=Resumen!$B$29,"Alto","Bajo"),"") -> Bajo | AT41: =IF(AS41<>"",AP41&" Potencial / "&AS41&" Share","") -> Alto Potencial / Bajo Share | AU41: =IF(AH41="","Sin dato",IF(AH41-AO41>Resumen!$B$6,"Sobre-exhibido",IF(AO41-AH41>Resumen!$B$6,"Sub-exhibido","En línea"))) -> Sub-exhibido | AV41: =IF(AT41="","",IF(AT41="Alto Potencial / Bajo Share",1,IF(AT41="Alto Potencial / Alto Share",2,IF(AT41="Bajo Potencial / Alto Share",3,4)))) -> 1 | AW41: =IF(Q41="No","Sin competencia directa",IF(AV41=1,"1 - Foco Conquista (Alto Pot / Bajo Share)",IF(AV41=2,"2 - Foco Defensa (Alto Pot / Alto Share)",IF(AV41=3,"3 - Monitoreo (Bajo Pot / Alto Share)","4 - Baja Prioridad (Bajo Pot / Bajo Share)")))) -> 1 - Foco Conquista (Alto Pot / Bajo Share) | AX41: =IF(OR(IFERROR(AND(W41<>"",Y41<>"",Y41-W41>Resumen!$B$8),FALSE()),IFERROR(AND(X41<>"",Y41<>"",Y41-X41>Resumen!$B$8),FALSE())),MAX(IF(IFERROR(AND(W41<>"",Y41<>"",Y41-W41>Resumen!$B$8),FALSE()),Y41-W41,0),IF(IFERROR(AND(X41<>"",Y41<>"",Y41-X41>Resumen!$B$8),FALSE()),Y41-X41,0)),"") -> 0.051428571 | AY41: =IF(OR(IFERROR(AND(W41<>"",Y41<>"",Y41-W41>Resumen!$B$8),FALSE()),IFERROR(AND(X41<>"",Y41<>"",Y41-X41>Resumen!$B$8),FALSE())),TRIM("Lays tiene mayor markup que "&IF(IFERROR(AND(W41<>"",Y41<>"",Y41-W41>Resumen!$B$8),FALSE()),"Quento ","")&IF(IFERROR(AND(X41<>"",Y41<>"",Y41-X41>Resumen!$B$8),FALSE()),"Julicroc ","")&"en este PDV"),"") -> Lays tiene mayor markup que Quento en este PDV | AZ41: =IF(COUNTIF('Plan Pehuamar - Lista'!$A$2:$A$167,A41)>0,"Sí","No") -> No | BA41: =IF(COUNTIF('Plan Combo 9+1'!$A$2:$A$226,A41)>0,"Sí","No") -> No | BB41: =IF(AH41="","No",IF(BA41="Sí",IF((AO41-AH41)>Resumen!$B$6,"Sí","No"),IF((AO41-AH41)>=Resumen!$B$132,"Sí","No"))) -> No | BC41: =IF(AND(N41="Sí",AL41="Sí",AI41=0),"Sí","No") -> Sí | BD41: =IF(COUNTIF('Plan 9+1 (con Pehuamar)'!$A$2:$A$227,A41)>0,"Sí","No") -> No
A42: 404079 | B42: 1 | C42: 101 | D42: Lunes | E42: Teresa Maldonado | F42: Kiosco/Maxikiosco | G42: Santa Fe | H42: Conrado Pujol | I42: 0 | J42: 0 | K42: 0.1 | L42: =I42+J42 -> 0 | M42: =L42+K42 -> 0.1 | N42: =IF(I42>0,"Sí","No") -> No | O42: =IF(J42>0,"Sí","No") -> No | P42: =IF(K42>0,"Sí","No") -> Sí | Q42: =IF(OR(I42>0,J42>0),"Sí","No") -> No | W42: =IF(AND(I42>0,R42>0),(S42-R42)/R42,"") | X42: =IF(AND(J42>0,T42>0),(U42-T42)/T42,"") | Y42: =IF(AND(K42>0,V42>0),(V42-Resumen!$B$7)/Resumen!$B$7,"") | Z42: =IF(AND(K42>0,I42>0,V42>0,S42>0),V42-S42,"") | AA42: =IF(Z42<>"",Z42/S42,"") | AB42: =IF(AND(K42>0,J42>0,V42>0,U42>0),V42-U42,"") | AC42: =IF(AB42<>"",AB42/U42,"") | AD42: 0 | AE42: 0 | AF42: 0 | AG42: =AD42+AE42+AF42 -> 0 | AH42: =IF(AG42>0,AD42/AG42,"") | AI42: 0 | AJ42: 0 | AK42: 0 | AL42: =IF(OR(AJ42>0,AK42>0),"Sí","No") -> No | AO42: =IF(M42>0,K42/M42,"") -> 1 | AP42: =IF(M42>=Resumen!$B$5,"Alto","Bajo") -> Bajo | AQ42: =IF(AO42>=Resumen!$B$28,"Alto","Bajo") -> Alto | AR42: =AP42&" Potencial / "&AQ42&" Share" -> Bajo Potencial / Alto Share | AS42: =IF(Q42="Sí",IF(AO42>=Resumen!$B$29,"Alto","Bajo"),"") | AT42: =IF(AS42<>"",AP42&" Potencial / "&AS42&" Share","") | AU42: =IF(AH42="","Sin dato",IF(AH42-AO42>Resumen!$B$6,"Sobre-exhibido",IF(AO42-AH42>Resumen!$B$6,"Sub-exhibido","En línea"))) -> Sin dato | AV42: =IF(AT42="","",IF(AT42="Alto Potencial / Bajo Share",1,IF(AT42="Alto Potencial / Alto Share",2,IF(AT42="Bajo Potencial / Alto Share",3,4)))) | AW42: =IF(Q42="No","Sin competencia directa",IF(AV42=1,"1 - Foco Conquista (Alto Pot / Bajo Share)",IF(AV42=2,"2 - Foco Defensa (Alto Pot / Alto Share)",IF(AV42=3,"3 - Monitoreo (Bajo Pot / Alto Share)","4 - Baja Prioridad (Bajo Pot / Bajo Share)")))) -> Sin competencia directa | AX42: =IF(OR(IFERROR(AND(W42<>"",Y42<>"",Y42-W42>Resumen!$B$8),FALSE()),IFERROR(AND(X42<>"",Y42<>"",Y42-X42>Resumen!$B$8),FALSE())),MAX(IF(IFERROR(AND(W42<>"",Y42<>"",Y42-W42>Resumen!$B$8),FALSE()),Y42-W42,0),IF(IFERROR(AND(X42<>"",Y42<>"",Y42-X42>Resumen!$B$8),FALSE()),Y42-X42,0)),"") | AY42: =IF(OR(IFERROR(AND(W42<>"",Y42<>"",Y42-W42>Resumen!$B$8),FALSE()),IFERROR(AND(X42<>"",Y42<>"",Y42-X42>Resumen!$B$8),FALSE())),TRIM("Lays tiene mayor markup que "&IF(IFERROR(AND(W42<>"",Y42<>"",Y42-W42>Resumen!$B$8),FALSE()),"Quento ","")&IF(IFERROR(AND(X42<>"",Y42<>"",Y42-X42>Resumen!$B$8),FALSE()),"Julicroc ","")&"en este PDV"),"") | AZ42: =IF(COUNTIF('Plan Pehuamar - Lista'!$A$2:$A$167,A42)>0,"Sí","No") -> No | BA42: =IF(COUNTIF('Plan Combo 9+1'!$A$2:$A$226,A42)>0,"Sí","No") -> No | BB42: =IF(AH42="","No",IF(BA42="Sí",IF((AO42-AH42)>Resumen!$B$6,"Sí","No"),IF((AO42-AH42)>=Resumen!$B$132,"Sí","No"))) -> No | BC42: =IF(AND(N42="Sí",AL42="Sí",AI42=0),"Sí","No") -> No | BD42: =IF(COUNTIF('Plan 9+1 (con Pehuamar)'!$A$2:$A$227,A42)>0,"Sí","No") -> No
A43: 404093 | B43: 1 | C43: 101 | D43: Lunes | E43: Clausen Daniel Eduardo | F43: Almacen/Despensa | G43: Santa Fe | H43: Conrado Pujol | I43: 0 | J43: 0 | K43: 0.2 | L43: =I43+J43 -> 0 | M43: =L43+K43 -> 0.2 | N43: =IF(I43>0,"Sí","No") -> No | O43: =IF(J43>0,"Sí","No") -> No | P43: =IF(K43>0,"Sí","No") -> Sí | Q43: =IF(OR(I43>0,J43>0),"Sí","No") -> No | W43: =IF(AND(I43>0,R43>0),(S43-R43)/R43,"") | X43: =IF(AND(J43>0,T43>0),(U43-T43)/T43,"") | Y43: =IF(AND(K43>0,V43>0),(V43-Resumen!$B$7)/Resumen!$B$7,"") | Z43: =IF(AND(K43>0,I43>0,V43>0,S43>0),V43-S43,"") | AA43: =IF(Z43<>"",Z43/S43,"") | AB43: =IF(AND(K43>0,J43>0,V43>0,U43>0),V43-U43,"") | AC43: =IF(AB43<>"",AB43/U43,"") | AD43: 0 | AE43: 0 | AF43: 0 | AG43: =AD43+AE43+AF43 -> 0 | AH43: =IF(AG43>0,AD43/AG43,"") | AI43: 0 | AJ43: 0 | AK43: 0 | AL43: =IF(OR(AJ43>0,AK43>0),"Sí","No") -> No | AO43: =IF(M43>0,K43/M43,"") -> 1 | AP43: =IF(M43>=Resumen!$B$5,"Alto","Bajo") -> Bajo | AQ43: =IF(AO43>=Resumen!$B$28,"Alto","Bajo") -> Alto | AR43: =AP43&" Potencial / "&AQ43&" Share" -> Bajo Potencial / Alto Share | AS43: =IF(Q43="Sí",IF(AO43>=Resumen!$B$29,"Alto","Bajo"),"") | AT43: =IF(AS43<>"",AP43&" Potencial / "&AS43&" Share","") | AU43: =IF(AH43="","Sin dato",IF(AH43-AO43>Resumen!$B$6,"Sobre-exhibido",IF(AO43-AH43>Resumen!$B$6,"Sub-exhibido","En línea"))) -> Sin dato | AV43: =IF(AT43="","",IF(AT43="Alto Potencial / Bajo Share",1,IF(AT43="Alto Potencial / Alto Share",2,IF(AT43="Bajo Potencial / Alto Share",3,4)))) | AW43: =IF(Q43="No","Sin competencia directa",IF(AV43=1,"1 - Foco Conquista (Alto Pot / Bajo Share)",IF(AV43=2,"2 - Foco Defensa (Alto Pot / Alto Share)",IF(AV43=3,"3 - Monitoreo (Bajo Pot / Alto Share)","4 - Baja Prioridad (Bajo Pot / Bajo Share)")))) -> Sin competencia directa | AX43: =IF(OR(IFERROR(AND(W43<>"",Y43<>"",Y43-W43>Resumen!$B$8),FALSE()),IFERROR(AND(X43<>"",Y43<>"",Y43-X43>Resumen!$B$8),FALSE())),MAX(IF(IFERROR(AND(W43<>"",Y43<>"",Y43-W43>Resumen!$B$8),FALSE()),Y43-W43,0),IF(IFERROR(AND(X43<>"",Y43<>"",Y43-X43>Resumen!$B$8),FALSE()),Y43-X43,0)),"") | AY43: =IF(OR(IFERROR(AND(W43<>"",Y43<>"",Y43-W43>Resumen!$B$8),FALSE()),IFERROR(AND(X43<>"",Y43<>"",Y43-X43>Resumen!$B$8),FALSE())),TRIM("Lays tiene mayor markup que "&IF(IFERROR(AND(W43<>"",Y43<>"",Y43-W43>Resumen!$B$8),FALSE()),"Quento ","")&IF(IFERROR(AND(X43<>"",Y43<>"",Y43-X43>Resumen!$B$8),FALSE()),"Julicroc ","")&"en este PDV"),"") | AZ43: =IF(COUNTIF('Plan Pehuamar - Lista'!$A$2:$A$167,A43)>0,"Sí","No") -> No | BA43: =IF(COUNTIF('Plan Combo 9+1'!$A$2:$A$226,A43)>0,"Sí","No") -> No | BB43: =IF(AH43="","No",IF(BA43="Sí",IF((AO43-AH43)>Resumen!$B$6,"Sí","No"),IF((AO43-AH43)>=Resumen!$B$132,"Sí","No"))) -> No | BC43: =IF(AND(N43="Sí",AL43="Sí",AI43=0),"Sí","No") -> No | BD43: =IF(COUNTIF('Plan 9+1 (con Pehuamar)'!$A$2:$A$227,A43)>0,"Sí","No") -> No
A44: 404179 | B44: 1 | C44: 101 | D44: Lunes | E44: MINIMERCADO OLIVIA | F44: Kiosco/Maxikiosco | G44: Santa Fe | H44: Conrado Pujol | I44: 0 | J44: 0 | K44: 0.3 | L44: =I44+J44 -> 0 | M44: =L44+K44 -> 0.3 | N44: =IF(I44>0,"Sí","No") -> No | O44: =IF(J44>0,"Sí","No") -> No | P44: =IF(K44>0,"Sí","No") -> Sí | Q44: =IF(OR(I44>0,J44>0),"Sí","No") -> No | W44: =IF(AND(I44>0,R44>0),(S44-R44)/R44,"") | X44: =IF(AND(J44>0,T44>0),(U44-T44)/T44,"") | Y44: =IF(AND(K44>0,V44>0),(V44-Resumen!$B$7)/Resumen!$B$7,"") | Z44: =IF(AND(K44>0,I44>0,V44>0,S44>0),V44-S44,"") | AA44: =IF(Z44<>"",Z44/S44,"") | AB44: =IF(AND(K44>0,J44>0,V44>0,U44>0),V44-U44,"") | AC44: =IF(AB44<>"",AB44/U44,"") | AD44: 0 | AE44: 0 | AF44: 0 | AG44: =AD44+AE44+AF44 -> 0 | AH44: =IF(AG44>0,AD44/AG44,"") | AI44: 0 | AJ44: 0 | AK44: 0 | AL44: =IF(OR(AJ44>0,AK44>0),"Sí","No") -> No | AO44: =IF(M44>0,K44/M44,"") -> 1 | AP44: =IF(M44>=Resumen!$B$5,"Alto","Bajo") -> Bajo | AQ44: =IF(AO44>=Resumen!$B$28,"Alto","Bajo") -> Alto | AR44: =AP44&" Potencial / "&AQ44&" Share" -> Bajo Potencial / Alto Share | AS44: =IF(Q44="Sí",IF(AO44>=Resumen!$B$29,"Alto","Bajo"),"") | AT44: =IF(AS44<>"",AP44&" Potencial / "&AS44&" Share","") | AU44: =IF(AH44="","Sin dato",IF(AH44-AO44>Resumen!$B$6,"Sobre-exhibido",IF(AO44-AH44>Resumen!$B$6,"Sub-exhibido","En línea"))) -> Sin dato | AV44: =IF(AT44="","",IF(AT44="Alto Potencial / Bajo Share",1,IF(AT44="Alto Potencial / Alto Share",2,IF(AT44="Bajo Potencial / Alto Share",3,4)))) | AW44: =IF(Q44="No","Sin competencia directa",IF(AV44=1,"1 - Foco Conquista (Alto Pot / Bajo Share)",IF(AV44=2,"2 - Foco Defensa (Alto Pot / Alto Share)",IF(AV44=3,"3 - Monitoreo (Bajo Pot / Alto Share)","4 - Baja Prioridad (Bajo Pot / Bajo Share)")))) -> Sin competencia directa | AX44: =IF(OR(IFERROR(AND(W44<>"",Y44<>"",Y44-W44>Resumen!$B$8),FALSE()),IFERROR(AND(X44<>"",Y44<>"",Y44-X44>Resumen!$B$8),FALSE())),MAX(IF(IFERROR(AND(W44<>"",Y44<>"",Y44-W44>Resumen!$B$8),FALSE()),Y44-W44,0),IF(IFERROR(AND(X44<>"",Y44<>"",Y44-X44>Resumen!$B$8),FALSE()),Y44-X44,0)),"") | AY44: =IF(OR(IFERROR(AND(W44<>"",Y44<>"",Y44-W44>Resumen!$B$8),FALSE()),IFERROR(AND(X44<>"",Y44<>"",Y44-X44>Resumen!$B$8),FALSE())),TRIM("Lays tiene mayor markup que "&IF(IFERROR(AND(W44<>"",Y44<>"",Y44-W44>Resumen!$B$8),FALSE()),"Quento ","")&IF(IFERROR(AND(X44<>"",Y44<>"",Y44-X44>Resumen!$B$8),FALSE()),"Julicroc ","")&"en este PDV"),"") | AZ44: =IF(COUNTIF('Plan Pehuamar - Lista'!$A$2:$A$167,A44)>0,"Sí","No") -> No | BA44: =IF(COUNTIF('Plan Combo 9+1'!$A$2:$A$226,A44)>0,"Sí","No") -> No | BB44: =IF(AH44="","No",IF(BA44="Sí",IF((AO44-AH44)>Resumen!$B$6,"Sí","No"),IF((AO44-AH44)>=Resumen!$B$132,"Sí","No"))) -> No | BC44: =IF(AND(N44="Sí",AL44="Sí",AI44=0),"Sí","No") -> No | BD44: =IF(COUNTIF('Plan 9+1 (con Pehuamar)'!$A$2:$A$227,A44)>0,"Sí","No") -> No
A45: 404190 | B45: 1 | C45: 101 | D45: Lunes | E45: MINIMERCADO PEÑALOZA | F45: Almacen/Despensa | G45: Santa Fe | H45: Conrado Pujol | I45: 30 | J45: 25 | K45: 35 | L45: =I45+J45 -> 55 | M45: =L45+K45 -> 90 | N45: =IF(I45>0,"Sí","No") -> Sí | O45: =IF(J45>0,"Sí","No") -> Sí | P45: =IF(K45>0,"Sí","No") -> Sí | Q45: =IF(OR(I45>0,J45>0),"Sí","No") -> Sí | R45: 1800 | S45: 3000 | T45: 1600 | U45: 2500 | V45: 3600 | W45: =IF(AND(I45>0,R45>0),(S45-R45)/R45,"") -> 0.66666667 | X45: =IF(AND(J45>0,T45>0),(U45-T45)/T45,"") -> 0.5625 | Y45: =IF(AND(K45>0,V45>0),(V45-Resumen!$B$7)/Resumen!$B$7,"") -> 0.44 | Z45: =IF(AND(K45>0,I45>0,V45>0,S45>0),V45-S45,"") -> 600 | AA45: =IF(Z45<>"",Z45/S45,"") -> 0.2 | AB45: =IF(AND(K45>0,J45>0,V45>0,U45>0),V45-U45,"") -> 1100 | AC45: =IF(AB45<>"",AB45/U45,"") -> 0.44 | AD45: 5 | AE45: 5 | AF45: 4 | AG45: =AD45+AE45+AF45 -> 14 | AH45: =IF(AG45>0,AD45/AG45,"") -> 0.35714286 | AI45: 1 | AJ45: 1 | AK45: 1 | AL45: =IF(OR(AJ45>0,AK45>0),"Sí","No") -> Sí | AM45: Contado | AN45: Contado | AO45: =IF(M45>0,K45/M45,"") -> 0.38888889 | AP45: =IF(M45>=Resumen!$B$5,"Alto","Bajo") -> Alto | AQ45: =IF(AO45>=Resumen!$B$28,"Alto","Bajo") -> Alto | AR45: =AP45&" Potencial / "&AQ45&" Share" -> Alto Potencial / Alto Share | AS45: =IF(Q45="Sí",IF(AO45>=Resumen!$B$29,"Alto","Bajo"),"") -> Bajo | AT45: =IF(AS45<>"",AP45&" Potencial / "&AS45&" Share","") -> Alto Potencial / Bajo Share | AU45: =IF(AH45="","Sin dato",IF(AH45-AO45>Resumen!$B$6,"Sobre-exhibido",IF(AO45-AH45>Resumen!$B$6,"Sub-exhibido","En línea"))) -> En línea | AV45: =IF(AT45="","",IF(AT45="Alto Potencial / Bajo Share",1,IF(AT45="Alto Potencial / Alto Share",2,IF(AT45="Bajo Potencial / Alto Share",3,4)))) -> 1 | AW45: =IF(Q45="No","Sin competencia directa",IF(AV45=1,"1 - Foco Conquista (Alto Pot / Bajo Share)",IF(AV45=2,"2 - Foco Defensa (Alto Pot / Alto Share)",IF(AV45=3,"3 - Monitoreo (Bajo Pot / Alto Share)","4 - Baja Prioridad (Bajo Pot / Bajo Share)")))) -> 1 - Foco Conquista (Alto Pot / Bajo Share) | AX45: =IF(OR(IFERROR(AND(W45<>"",Y45<>"",Y45-W45>Resumen!$B$8),FALSE()),IFERROR(AND(X45<>"",Y45<>"",Y45-X45>Resumen!$B$8),FALSE())),MAX(IF(IFERROR(AND(W45<>"",Y45<>"",Y45-W45>Resumen!$B$8),FALSE()),Y45-W45,0),IF(IFERROR(AND(X45<>"",Y45<>"",Y45-X45>Resumen!$B$8),FALSE()),Y45-X45,0)),"") | AY45: =IF(OR(IFERROR(AND(W45<>"",Y45<>"",Y45-W45>Resumen!$B$8),FALSE()),IFERROR(AND(X45<>"",Y45<>"",Y45-X45>Resumen!$B$8),FALSE())),TRIM("Lays tiene mayor markup que "&IF(IFERROR(AND(W45<>"",Y45<>"",Y45-W45>Resumen!$B$8),FALSE()),"Quento ","")&IF(IFERROR(AND(X45<>"",Y45<>"",Y45-X45>Resumen!$B$8),FALSE()),"Julicroc ","")&"en este PDV"),"") | AZ45: =IF(COUNTIF('Plan Pehuamar - Lista'!$A$2:$A$167,A45)>0,"Sí","No") -> Sí | BA45: =IF(COUNTIF('Plan Combo 9+1'!$A$2:$A$226,A45)>0,"Sí","No") -> No | BB45: =IF(AH45="","No",IF(BA45="Sí",IF((AO45-AH45)>Resumen!$B$6,"Sí","No"),IF((AO45-AH45)>=Resumen!$B$132,"Sí","No"))) -> No | BC45: =IF(AND(N45="Sí",AL45="Sí",AI45=0),"Sí","No") -> No | BD45: =IF(COUNTIF('Plan 9+1 (con Pehuamar)'!$A$2:$A$227,A45)>0,"Sí","No") -> No
A46: 404256 | B46: 1 | C46: 101 | D46: Lunes | E46: MINIMERCADO SAN JORGE | F46: Kiosco/Maxikiosco | G46: Santa Fe | H46: Conrado Pujol | I46: 0 | J46: 0 | K46: 0.4 | L46: =I46+J46 -> 0 | M46: =L46+K46 -> 0.4 | N46: =IF(I46>0,"Sí","No") -> No | O46: =IF(J46>0,"Sí","No") -> No | P46: =IF(K46>0,"Sí","No") -> Sí | Q46: =IF(OR(I46>0,J46>0),"Sí","No") -> No | W46: =IF(AND(I46>0,R46>0),(S46-R46)/R46,"") | X46: =IF(AND(J46>0,T46>0),(U46-T46)/T46,"") | Y46: =IF(AND(K46>0,V46>0),(V46-Resumen!$B$7)/Resumen!$B$7,"") | Z46: =IF(AND(K46>0,I46>0,V46>0,S46>0),V46-S46,"") | AA46: =IF(Z46<>"",Z46/S46,"") | AB46: =IF(AND(K46>0,J46>0,V46>0,U46>0),V46-U46,"") | AC46: =IF(AB46<>"",AB46/U46,"") | AD46: 0 | AE46: 0 | AF46: 0 | AG46: =AD46+AE46+AF46 -> 0 | AH46: =IF(AG46>0,AD46/AG46,"") | AI46: 0 | AJ46: 0 | AK46: 0 | AL46: =IF(OR(AJ46>0,AK46>0),"Sí","No") -> No | AO46: =IF(M46>0,K46/M46,"") -> 1 | AP46: =IF(M46>=Resumen!$B$5,"Alto","Bajo") -> Bajo | AQ46: =IF(AO46>=Resumen!$B$28,"Alto","Bajo") -> Alto | AR46: =AP46&" Potencial / "&AQ46&" Share" -> Bajo Potencial / Alto Share | AS46: =IF(Q46="Sí",IF(AO46>=Resumen!$B$29,"Alto","Bajo"),"") | AT46: =IF(AS46<>"",AP46&" Potencial / "&AS46&" Share","") | AU46: =IF(AH46="","Sin dato",IF(AH46-AO46>Resumen!$B$6,"Sobre-exhibido",IF(AO46-AH46>Resumen!$B$6,"Sub-exhibido","En línea"))) -> Sin dato | AV46: =IF(AT46="","",IF(AT46="Alto Potencial / Bajo Share",1,IF(AT46="Alto Potencial / Alto Share",2,IF(AT46="Bajo Potencial / Alto Share",3,4)))) | AW46: =IF(Q46="No","Sin competencia directa",IF(AV46=1,"1 - Foco Conquista (Alto Pot / Bajo Share)",IF(AV46=2,"2 - Foco Defensa (Alto Pot / Alto Share)",IF(AV46=3,"3 - Monitoreo (Bajo Pot / Alto Share)","4 - Baja Prioridad (Bajo Pot / Bajo Share)")))) -> Sin competencia directa | AX46: =IF(OR(IFERROR(AND(W46<>"",Y46<>"",Y46-W46>Resumen!$B$8),FALSE()),IFERROR(AND(X46<>"",Y46<>"",Y46-X46>Resumen!$B$8),FALSE())),MAX(IF(IFERROR(AND(W46<>"",Y46<>"",Y46-W46>Resumen!$B$8),FALSE()),Y46-W46,0),IF(IFERROR(AND(X46<>"",Y46<>"",Y46-X46>Resumen!$B$8),FALSE()),Y46-X46,0)),"") | AY46: =IF(OR(IFERROR(AND(W46<>"",Y46<>"",Y46-W46>Resumen!$B$8),FALSE()),IFERROR(AND(X46<>"",Y46<>"",Y46-X46>Resumen!$B$8),FALSE())),TRIM("Lays tiene mayor markup que "&IF(IFERROR(AND(W46<>"",Y46<>"",Y46-W46>Resumen!$B$8),FALSE()),"Quento ","")&IF(IFERROR(AND(X46<>"",Y46<>"",Y46-X46>Resumen!$B$8),FALSE()),"Julicroc ","")&"en este PDV"),"") | AZ46: =IF(COUNTIF('Plan Pehuamar - Lista'!$A$2:$A$167,A46)>0,"Sí","No") -> No | BA46: =IF(COUNTIF('Plan Combo 9+1'!$A$2:$A$226,A46)>0,"Sí","No") -> No | BB46: =IF(AH46="","No",IF(BA46="Sí",IF((AO46-AH46)>Resumen!$B$6,"Sí","No"),IF((AO46-AH46)>=Resumen!$B$132,"Sí","No"))) -> No | BC46: =IF(AND(N46="Sí",AL46="Sí",AI46=0),"Sí","No") -> No | BD46: =IF(COUNTIF('Plan 9+1 (con Pehuamar)'!$A$2:$A$227,A46)>0,"Sí","No") -> No
A47: 404278 | B47: 1 | C47: 101 | D47: Lunes | E47: GISEL EVA LO VUOLO - DRAXXO | F47: Kiosco/Maxikiosco | G47: Santa Fe | H47: Conrado Pujol | I47: 60 | J47: 0 | K47: 50 | L47: =I47+J47 -> 60 | M47: =L47+K47 -> 110 | N47: =IF(I47>0,"Sí","No") -> Sí | O47: =IF(J47>0,"Sí","No") -> No | P47: =IF(K47>0,"Sí","No") -> Sí | Q47: =IF(OR(I47>0,J47>0),"Sí","No") -> Sí | R47: 1800 | S47: 3200 | V47: 3800 | W47: =IF(AND(I47>0,R47>0),(S47-R47)/R47,"") -> 0.77777778 | X47: =IF(AND(J47>0,T47>0),(U47-T47)/T47,"") | Y47: =IF(AND(K47>0,V47>0),(V47-Resumen!$B$7)/Resumen!$B$7,"") -> 0.52 | Z47: =IF(AND(K47>0,I47>0,V47>0,S47>0),V47-S47,"") -> 600 | AA47: =IF(Z47<>"",Z47/S47,"") -> 0.1875 | AB47: =IF(AND(K47>0,J47>0,V47>0,U47>0),V47-U47,"") | AC47: =IF(AB47<>"",AB47/U47,"") | AD47: 5 | AE47: 4 | AF47: 0 | AG47: =AD47+AE47+AF47 -> 9 | AH47: =IF(AG47>0,AD47/AG47,"") -> 0.55555556 | AI47: 0 | AJ47: 0 | AK47: 0 | AL47: =IF(OR(AJ47>0,AK47>0),"Sí","No") -> No | AM47: Contado | AO47: =IF(M47>0,K47/M47,"") -> 0.45454545 | AP47: =IF(M47>=Resumen!$B$5,"Alto","Bajo") -> Alto | AQ47: =IF(AO47>=Resumen!$B$28,"Alto","Bajo") -> Alto | AR47: =AP47&" Potencial / "&AQ47&" Share" -> Alto Potencial / Alto Share | AS47: =IF(Q47="Sí",IF(AO47>=Resumen!$B$29,"Alto","Bajo"),"") -> Bajo | AT47: =IF(AS47<>"",AP47&" Potencial / "&AS47&" Share","") -> Alto Potencial / Bajo Share | AU47: =IF(AH47="","Sin dato",IF(AH47-AO47>Resumen!$B$6,"Sobre-exhibido",IF(AO47-AH47>Resumen!$B$6,"Sub-exhibido","En línea"))) -> Sobre-exhibido | AV47: =IF(AT47="","",IF(AT47="Alto Potencial / Bajo Share",1,IF(AT47="Alto Potencial / Alto Share",2,IF(AT47="Bajo Potencial / Alto Share",3,4)))) -> 1 | AW47: =IF(Q47="No","Sin competencia directa",IF(AV47=1,"1 - Foco Conquista (Alto Pot / Bajo Share)",IF(AV47=2,"2 - Foco Defensa (Alto Pot / Alto Share)",IF(AV47=3,"3 - Monitoreo (Bajo Pot / Alto Share)","4 - Baja Prioridad (Bajo Pot / Bajo Share)")))) -> 1 - Foco Conquista (Alto Pot / Bajo Share) | AX47: =IF(OR(IFERROR(AND(W47<>"",Y47<>"",Y47-W47>Resumen!$B$8),FALSE()),IFERROR(AND(X47<>"",Y47<>"",Y47-X47>Resumen!$B$8),FALSE())),MAX(IF(IFERROR(AND(W47<>"",Y47<>"",Y47-W47>Resumen!$B$8),FALSE()),Y47-W47,0),IF(IFERROR(AND(X47<>"",Y47<>"",Y47-X47>Resumen!$B$8),FALSE()),Y47-X47,0)),"") | AY47: =IF(OR(IFERROR(AND(W47<>"",Y47<>"",Y47-W47>Resumen!$B$8),FALSE()),IFERROR(AND(X47<>"",Y47<>"",Y47-X47>Resumen!$B$8),FALSE())),TRIM("Lays tiene mayor markup que "&IF(IFERROR(AND(W47<>"",Y47<>"",Y47-W47>Resumen!$B$8),FALSE()),"Quento ","")&IF(IFERROR(AND(X47<>"",Y47<>"",Y47-X47>Resumen!$B$8),FALSE()),"Julicroc ","")&"en este PDV"),"") | AZ47: =IF(COUNTIF('Plan Pehuamar - Lista'!$A$2:$A$167,A47)>0,"Sí","No") -> No | BA47: =IF(COUNTIF('Plan Combo 9+1'!$A$2:$A$226,A47)>0,"Sí","No") -> No | BB47: =IF(AH47="","No",IF(BA47="Sí",IF((AO47-AH47)>Resumen!$B$6,"Sí","No"),IF((AO47-AH47)>=Resumen!$B$132,"Sí","No"))) -> No | BC47: =IF(AND(N47="Sí",AL47="Sí",AI47=0),"Sí","No") -> No | BD47: =IF(COUNTIF('Plan 9+1 (con Pehuamar)'!$A$2:$A$227,A47)>0,"Sí","No") -> Sí
A48: 404310 | B48: 1 | C48: 101 | D48: Lunes | E48: MARIA LUZ CATALAN | F48: Almacen/Despensa | G48: Santa Fe | H48: Conrado Pujol | I48: 30 | J48: 0 | K48: 40 | L48: =I48+J48 -> 30 | M48: =L48+K48 -> 70 | N48: =IF(I48>0,"Sí","No") -> Sí | O48: =IF(J48>0,"Sí","No") -> No | P48: =IF(K48>0,"Sí","No") -> Sí | Q48: =IF(OR(I48>0,J48>0),"Sí","No") -> Sí | R48: 1800 | S48: 3000 | V48: 3500 | W48: =IF(AND(I48>0,R48>0),(S48-R48)/R48,"") -> 0.66666667 | X48: =IF(AND(J48>0,T48>0),(U48-T48)/T48,"") | Y48: =IF(AND(K48>0,V48>0),(V48-Resumen!$B$7)/Resumen!$B$7,"") -> 0.4 | Z48: =IF(AND(K48>0,I48>0,V48>0,S48>0),V48-S48,"") -> 500 | AA48: =IF(Z48<>"",Z48/S48,"") -> 0.16666667 | AB48: =IF(AND(K48>0,J48>0,V48>0,U48>0),V48-U48,"") | AC48: =IF(AB48<>"",AB48/U48,"") | AD48: 5 | AE48: 4 | AF48: 0 | AG48: =AD48+AE48+AF48 -> 9 | AH48: =IF(AG48>0,AD48/AG48,"") -> 0.55555556 | AI48: 1 | AJ48: 1 | AK48: 0 | AL48: =IF(OR(AJ48>0,AK48>0),"Sí","No") -> Sí | AM48: Contado | AO48: =IF(M48>0,K48/M48,"") -> 0.57142857 | AP48: =IF(M48>=Resumen!$B$5,"Alto","Bajo") -> Alto | AQ48: =IF(AO48>=Resumen!$B$28,"Alto","Bajo") -> Alto | AR48: =AP48&" Potencial / "&AQ48&" Share" -> Alto Potencial / Alto Share | AS48: =IF(Q48="Sí",IF(AO48>=Resumen!$B$29,"Alto","Bajo"),"") -> Alto | AT48: =IF(AS48<>"",AP48&" Potencial / "&AS48&" Share","") -> Alto Potencial / Alto Share | AU48: =IF(AH48="","Sin dato",IF(AH48-AO48>Resumen!$B$6,"Sobre-exhibido",IF(AO48-AH48>Resumen!$B$6,"Sub-exhibido","En línea"))) -> En línea | AV48: =IF(AT48="","",IF(AT48="Alto Potencial / Bajo Share",1,IF(AT48="Alto Potencial / Alto Share",2,IF(AT48="Bajo Potencial / Alto Share",3,4)))) -> 2 | AW48: =IF(Q48="No","Sin competencia directa",IF(AV48=1,"1 - Foco Conquista (Alto Pot / Bajo Share)",IF(AV48=2,"2 - Foco Defensa (Alto Pot / Alto Share)",IF(AV48=3,"3 - Monitoreo (Bajo Pot / Alto Share)","4 - Baja Prioridad (Bajo Pot / Bajo Share)")))) -> 2 - Foco Defensa (Alto Pot / Alto Share) | AX48: =IF(OR(IFERROR(AND(W48<>"",Y48<>"",Y48-W48>Resumen!$B$8),FALSE()),IFERROR(AND(X48<>"",Y48<>"",Y48-X48>Resumen!$B$8),FALSE())),MAX(IF(IFERROR(AND(W48<>"",Y48<>"",Y48-W48>Resumen!$B$8),FALSE()),Y48-W48,0),IF(IFERROR(AND(X48<>"",Y48<>"",Y48-X48>Resumen!$B$8),FALSE()),Y48-X48,0)),"") | AY48: =IF(OR(IFERROR(AND(W48<>"",Y48<>"",Y48-W48>Resumen!$B$8),FALSE()),IFERROR(AND(X48<>"",Y48<>"",Y48-X48>Resumen!$B$8),FALSE())),TRIM("Lays tiene mayor markup que "&IF(IFERROR(AND(W48<>"",Y48<>"",Y48-W48>Resumen!$B$8),FALSE()),"Quento ","")&IF(IFERROR(AND(X48<>"",Y48<>"",Y48-X48>Resumen!$B$8),FALSE()),"Julicroc ","")&"en este PDV"),"") | AZ48: =IF(COUNTIF('Plan Pehuamar - Lista'!$A$2:$A$167,A48)>0,"Sí","No") -> No | BA48: =IF(COUNTIF('Plan Combo 9+1'!$A$2:$A$226,A48)>0,"Sí","No") -> No | BB48: =IF(AH48="","No",IF(BA48="Sí",IF((AO48-AH48)>Resumen!$B$6,"Sí","No"),IF((AO48-AH48)>=Resumen!$B$132,"Sí","No"))) -> No | BC48: =IF(AND(N48="Sí",AL48="Sí",AI48=0),"Sí","No") -> No | BD48: =IF(COUNTIF('Plan 9+1 (con Pehuamar)'!$A$2:$A$227,A48)>0,"Sí","No") -> No
A49: 404311 | B49: 1 | C49: 101 | D49: Lunes | E49: BRIAN IVAN FERNANDEZ | F49: Almacen/Despensa | G49: Santa Fe | H49: Conrado Pujol | I49: 0 | J49: 0 | K49: 2.1 | L49: =I49+J49 -> 0 | M49: =L49+K49 -> 2.1 | N49: =IF(I49>0,"Sí","No") -> No | O49: =IF(J49>0,"Sí","No") -> No | P49: =IF(K49>0,"Sí","No") -> Sí | Q49: =IF(OR(I49>0,J49>0),"Sí","No") -> No | W49: =IF(AND(I49>0,R49>0),(S49-R49)/R49,"") | X49: =IF(AND(J49>0,T49>0),(U49-T49)/T49,"") | Y49: =IF(AND(K49>0,V49>0),(V49-Resumen!$B$7)/Resumen!$B$7,"") | Z49: =IF(AND(K49>0,I49>0,V49>0,S49>0),V49-S49,"") | AA49: =IF(Z49<>"",Z49/S49,"") | AB49: =IF(AND(K49>0,J49>0,V49>0,U49>0),V49-U49,"") | AC49: =IF(AB49<>"",AB49/U49,"") | AD49: 0 | AE49: 0 | AF49: 0 | AG49: =AD49+AE49+AF49 -> 0 | AH49: =IF(AG49>0,AD49/AG49,"") | AI49: 0 | AJ49: 0 | AK49: 0 | AL49: =IF(OR(AJ49>0,AK49>0),"Sí","No") -> No | AO49: =IF(M49>0,K49/M49,"") -> 1 | AP49: =IF(M49>=Resumen!$B$5,"Alto","Bajo") -> Bajo | AQ49: =IF(AO49>=Resumen!$B$28,"Alto","Bajo") -> Alto | AR49: =AP49&" Potencial / "&AQ49&" Share" -> Bajo Potencial / Alto Share | AS49: =IF(Q49="Sí",IF(AO49>=Resumen!$B$29,"Alto","Bajo"),"") | AT49: =IF(AS49<>"",AP49&" Potencial / "&AS49&" Share","") | AU49: =IF(AH49="","Sin dato",IF(AH49-AO49>Resumen!$B$6,"Sobre-exhibido",IF(AO49-AH49>Resumen!$B$6,"Sub-exhibido","En línea"))) -> Sin dato | AV49: =IF(AT49="","",IF(AT49="Alto Potencial / Bajo Share",1,IF(AT49="Alto Potencial / Alto Share",2,IF(AT49="Bajo Potencial / Alto Share",3,4)))) | AW49: =IF(Q49="No","Sin competencia directa",IF(AV49=1,"1 - Foco Conquista (Alto Pot / Bajo Share)",IF(AV49=2,"2 - Foco Defensa (Alto Pot / Alto Share)",IF(AV49=3,"3 - Monitoreo (Bajo Pot / Alto Share)","4 - Baja Prioridad (Bajo Pot / Bajo Share)")))) -> Sin competencia directa | AX49: =IF(OR(IFERROR(AND(W49<>"",Y49<>"",Y49-W49>Resumen!$B$8),FALSE()),IFERROR(AND(X49<>"",Y49<>"",Y49-X49>Resumen!$B$8),FALSE())),MAX(IF(IFERROR(AND(W49<>"",Y49<>"",Y49-W49>Resumen!$B$8),FALSE()),Y49-W49,0),IF(IFERROR(AND(X49<>"",Y49<>"",Y49-X49>Resumen!$B$8),FALSE()),Y49-X49,0)),"") | AY49: =IF(OR(IFERROR(AND(W49<>"",Y49<>"",Y49-W49>Resumen!$B$8),FALSE()),IFERROR(AND(X49<>"",Y49<>"",Y49-X49>Resumen!$B$8),FALSE())),TRIM("Lays tiene mayor markup que "&IF(IFERROR(AND(W49<>"",Y49<>"",Y49-W49>Resumen!$B$8),FALSE()),"Quento ","")&IF(IFERROR(AND(X49<>"",Y49<>"",Y49-X49>Resumen!$B$8),FALSE()),"Julicroc ","")&"en este PDV"),"") | AZ49: =IF(COUNTIF('Plan Pehuamar - Lista'!$A$2:$A$167,A49)>0,"Sí","No") -> No | BA49: =IF(COUNTIF('Plan Combo 9+1'!$A$2:$A$226,A49)>0,"Sí","No") -> No | BB49: =IF(AH49="","No",IF(BA49="Sí",IF((AO49-AH49)>Resumen!$B$6,"Sí","No"),IF((AO49-AH49)>=Resumen!$B$132,"Sí","No"))) -> No | BC49: =IF(AND(N49="Sí",AL49="Sí",AI49=0),"Sí","No") -> No | BD49: =IF(COUNTIF('Plan 9+1 (con Pehuamar)'!$A$2:$A$227,A49)>0,"Sí","No") -> No
A50: 404316 | B50: 1 | C50: 101 | D50: Lunes | E50: JAVIER HERNAN INGARAMO | F50: Almacen/Despensa | G50: Santa Fe | H50: Conrado Pujol | I50: 0 | J50: 0 | K50: 1.2 | L50: =I50+J50 -> 0 | M50: =L50+K50 -> 1.2 | N50: =IF(I50>0,"Sí","No") -> No | O50: =IF(J50>0,"Sí","No") -> No | P50: =IF(K50>0,"Sí","No") -> Sí | Q50: =IF(OR(I50>0,J50>0),"Sí","No") -> No | W50: =IF(AND(I50>0,R50>0),(S50-R50)/R50,"") | X50: =IF(AND(J50>0,T50>0),(U50-T50)/T50,"") | Y50: =IF(AND(K50>0,V50>0),(V50-Resumen!$B$7)/Resumen!$B$7,"") | Z50: =IF(AND(K50>0,I50>0,V50>0,S50>0),V50-S50,"") | AA50: =IF(Z50<>"",Z50/S50,"") | AB50: =IF(AND(K50>0,J50>0,V50>0,U50>0),V50-U50,"") | AC50: =IF(AB50<>"",AB50/U50,"") | AD50: 0 | AE50: 0 | AF50: 0 | AG50: =AD50+AE50+AF50 -> 0 | AH50: =IF(AG50>0,AD50/AG50,"") | AI50: 0 | AJ50: 0 | AK50: 0 | AL50: =IF(OR(AJ50>0,AK50>0),"Sí","No") -> No | AO50: =IF(M50>0,K50/M50,"") -> 1 | AP50: =IF(M50>=Resumen!$B$5,"Alto","Bajo") -> Bajo | AQ50: =IF(AO50>=Resumen!$B$28,"Alto","Bajo") -> Alto | AR50: =AP50&" Potencial / "&AQ50&" Share" -> Bajo Potencial / Alto Share | AS50: =IF(Q50="Sí",IF(AO50>=Resumen!$B$29,"Alto","Bajo"),"") | AT50: =IF(AS50<>"",AP50&" Potencial / "&AS50&" Share","") | AU50: =IF(AH50="","Sin dato",IF(AH50-AO50>Resumen!$B$6,"Sobre-exhibido",IF(AO50-AH50>Resumen!$B$6,"Sub-exhibido","En línea"))) -> Sin dato | AV50: =IF(AT50="","",IF(AT50="Alto Potencial / Bajo Share",1,IF(AT50="Alto Potencial / Alto Share",2,IF(AT50="Bajo Potencial / Alto Share",3,4)))) | AW50: =IF(Q50="No","Sin competencia directa",IF(AV50=1,"1 - Foco Conquista (Alto Pot / Bajo Share)",IF(AV50=2,"2 - Foco Defensa (Alto Pot / Alto Share)",IF(AV50=3,"3 - Monitoreo (Bajo Pot / Alto Share)","4 - Baja Prioridad (Bajo Pot / Bajo Share)")))) -> Sin competencia directa | AX50: =IF(OR(IFERROR(AND(W50<>"",Y50<>"",Y50-W50>Resumen!$B$8),FALSE()),IFERROR(AND(X50<>"",Y50<>"",Y50-X50>Resumen!$B$8),FALSE())),MAX(IF(IFERROR(AND(W50<>"",Y50<>"",Y50-W50>Resumen!$B$8),FALSE()),Y50-W50,0),IF(IFERROR(AND(X50<>"",Y50<>"",Y50-X50>Resumen!$B$8),FALSE()),Y50-X50,0)),"") | AY50: =IF(OR(IFERROR(AND(W50<>"",Y50<>"",Y50-W50>Resumen!$B$8),FALSE()),IFERROR(AND(X50<>"",Y50<>"",Y50-X50>Resumen!$B$8),FALSE())),TRIM("Lays tiene mayor markup que "&IF(IFERROR(AND(W50<>"",Y50<>"",Y50-W50>Resumen!$B$8),FALSE()),"Quento ","")&IF(IFERROR(AND(X50<>"",Y50<>"",Y50-X50>Resumen!$B$8),FALSE()),"Julicroc ","")&"en este PDV"),"") | AZ50: =IF(COUNTIF('Plan Pehuamar - Lista'!$A$2:$A$167,A50)>0,"Sí","No") -> No | BA50: =IF(COUNTIF('Plan Combo 9+1'!$A$2:$A$226,A50)>0,"Sí","No") -> No | BB50: =IF(AH50="","No",IF(BA50="Sí",IF((AO50-AH50)>Resumen!$B$6,"Sí","No"),IF((AO50-AH50)>=Resumen!$B$132,"Sí","No"))) -> No | BC50: =IF(AND(N50="Sí",AL50="Sí",AI50=0),"Sí","No") -> No | BD50: =IF(COUNTIF('Plan 9+1 (con Pehuamar)'!$A$2:$A$227,A50)>0,"Sí","No") -> No
A51: 404334 | B51: 1 | C51: 101 | D51: Lunes | E51: IARA FATIMA PATRICIA MONTERO | F51: Almacen/Despensa | G51: Santa Fe | H51: Conrado Pujol | I51: 0 | J51: 0 | K51: 0.8 | L51: =I51+J51 -> 0 | M51: =L51+K51 -> 0.8 | N51: =IF(I51>0,"Sí","No") -> No | O51: =IF(J51>0,"Sí","No") -> No | P51: =IF(K51>0,"Sí","No") -> Sí | Q51: =IF(OR(I51>0,J51>0),"Sí","No") -> No | W51: =IF(AND(I51>0,R51>0),(S51-R51)/R51,"") | X51: =IF(AND(J51>0,T51>0),(U51-T51)/T51,"") | Y51: =IF(AND(K51>0,V51>0),(V51-Resumen!$B$7)/Resumen!$B$7,"") | Z51: =IF(AND(K51>0,I51>0,V51>0,S51>0),V51-S51,"") | AA51: =IF(Z51<>"",Z51/S51,"") | AB51: =IF(AND(K51>0,J51>0,V51>0,U51>0),V51-U51,"") | AC51: =IF(AB51<>"",AB51/U51,"") | AD51: 0 | AE51: 0 | AF51: 0 | AG51: =AD51+AE51+AF51 -> 0 | AH51: =IF(AG51>0,AD51/AG51,"") | AI51: 0 | AJ51: 0 | AK51: 0 | AL51: =IF(OR(AJ51>0,AK51>0),"Sí","No") -> No | AO51: =IF(M51>0,K51/M51,"") -> 1 | AP51: =IF(M51>=Resumen!$B$5,"Alto","Bajo") -> Bajo | AQ51: =IF(AO51>=Resumen!$B$28,"Alto","Bajo") -> Alto | AR51: =AP51&" Potencial / "&AQ51&" Share" -> Bajo Potencial / Alto Share | AS51: =IF(Q51="Sí",IF(AO51>=Resumen!$B$29,"Alto","Bajo"),"") | AT51: =IF(AS51<>"",AP51&" Potencial / "&AS51&" Share","") | AU51: =IF(AH51="","Sin dato",IF(AH51-AO51>Resumen!$B$6,"Sobre-exhibido",IF(AO51-AH51>Resumen!$B$6,"Sub-exhibido","En línea"))) -> Sin dato | AV51: =IF(AT51="","",IF(AT51="Alto Potencial / Bajo Share",1,IF(AT51="Alto Potencial / Alto Share",2,IF(AT51="Bajo Potencial / Alto Share",3,4)))) | AW51: =IF(Q51="No","Sin competencia directa",IF(AV51=1,"1 - Foco Conquista (Alto Pot / Bajo Share)",IF(AV51=2,"2 - Foco Defensa (Alto Pot / Alto Share)",IF(AV51=3,"3 - Monitoreo (Bajo Pot / Alto Share)","4 - Baja Prioridad (Bajo Pot / Bajo Share)")))) -> Sin competencia directa | AX51: =IF(OR(IFERROR(AND(W51<>"",Y51<>"",Y51-W51>Resumen!$B$8),FALSE()),IFERROR(AND(X51<>"",Y51<>"",Y51-X51>Resumen!$B$8),FALSE())),MAX(IF(IFERROR(AND(W51<>"",Y51<>"",Y51-W51>Resumen!$B$8),FALSE()),Y51-W51,0),IF(IFERROR(AND(X51<>"",Y51<>"",Y51-X51>Resumen!$B$8),FALSE()),Y51-X51,0)),"") | AY51: =IF(OR(IFERROR(AND(W51<>"",Y51<>"",Y51-W51>Resumen!$B$8),FALSE()),IFERROR(AND(X51<>"",Y51<>"",Y51-X51>Resumen!$B$8),FALSE())),TRIM("Lays tiene mayor markup que "&IF(IFERROR(AND(W51<>"",Y51<>"",Y51-W51>Resumen!$B$8),FALSE()),"Quento ","")&IF(IFERROR(AND(X51<>"",Y51<>"",Y51-X51>Resumen!$B$8),FALSE()),"Julicroc ","")&"en este PDV"),"") | AZ51: =IF(COUNTIF('Plan Pehuamar - Lista'!$A$2:$A$167,A51)>0,"Sí","No") -> No | BA51: =IF(COUNTIF('Plan Combo 9+1'!$A$2:$A$226,A51)>0,"Sí","No") -> No | BB51: =IF(AH51="","No",IF(BA51="Sí",IF((AO51-AH51)>Resumen!$B$6,"Sí","No"),IF((AO51-AH51)>=Resumen!$B$132,"Sí","No"))) -> No | BC51: =IF(AND(N51="Sí",AL51="Sí",AI51=0),"Sí","No") -> No | BD51: =IF(COUNTIF('Plan 9+1 (con Pehuamar)'!$A$2:$A$227,A51)>0,"Sí","No") -> No
A52: 404357 | B52: 1 | C52: 101 | D52: Lunes | E52: ISAURRALDE AILEN ROCIO | F52: Kiosco/Maxikiosco | G52: Santa Fe | H52: Conrado Pujol | I52: 30 | J52: 0 | K52: 40 | L52: =I52+J52 -> 30 | M52: =L52+K52 -> 70 | N52: =IF(I52>0,"Sí","No") -> Sí | O52: =IF(J52>0,"Sí","No") -> No | P52: =IF(K52>0,"Sí","No") -> Sí | Q52: =IF(OR(I52>0,J52>0),"Sí","No") -> Sí | R52: 1800 | S52: 2900 | V52: 3400 | W52: =IF(AND(I52>0,R52>0),(S52-R52)/R52,"") -> 0.61111111 | X52: =IF(AND(J52>0,T52>0),(U52-T52)/T52,"") | Y52: =IF(AND(K52>0,V52>0),(V52-Resumen!$B$7)/Resumen!$B$7,"") -> 0.36 | Z52: =IF(AND(K52>0,I52>0,V52>0,S52>0),V52-S52,"") -> 500 | AA52: =IF(Z52<>"",Z52/S52,"") -> 0.17241379 | AB52: =IF(AND(K52>0,J52>0,V52>0,U52>0),V52-U52,"") | AC52: =IF(AB52<>"",AB52/U52,"") | AD52: 4 | AE52: 4 | AF52: 0 | AG52: =AD52+AE52+AF52 -> 8 | AH52: =IF(AG52>0,AD52/AG52,"") -> 0.5 | AI52: 0 | AJ52: 0 | AK52: 0 | AL52: =IF(OR(AJ52>0,AK52>0),"Sí","No") -> No | AM52: Contado | AO52: =IF(M52>0,K52/M52,"") -> 0.57142857 | AP52: =IF(M52>=Resumen!$B$5,"Alto","Bajo") -> Alto | AQ52: =IF(AO52>=Resumen!$B$28,"Alto","Bajo") -> Alto | AR52: =AP52&" Potencial / "&AQ52&" Share" -> Alto Potencial / Alto Share | AS52: =IF(Q52="Sí",IF(AO52>=Resumen!$B$29,"Alto","Bajo"),"") -> Alto | AT52: =IF(AS52<>"",AP52&" Potencial / "&AS52&" Share","") -> Alto Potencial / Alto Share | AU52: =IF(AH52="","Sin dato",IF(AH52-AO52>Resumen!$B$6,"Sobre-exhibido",IF(AO52-AH52>Resumen!$B$6,"Sub-exhibido","En línea"))) -> Sub-exhibido | AV52: =IF(AT52="","",IF(AT52="Alto Potencial / Bajo Share",1,IF(AT52="Alto Potencial / Alto Share",2,IF(AT52="Bajo Potencial / Alto Share",3,4)))) -> 2 | AW52: =IF(Q52="No","Sin competencia directa",IF(AV52=1,"1 - Foco Conquista (Alto Pot / Bajo Share)",IF(AV52=2,"2 - Foco Defensa (Alto Pot / Alto Share)",IF(AV52=3,"3 - Monitoreo (Bajo Pot / Alto Share)","4 - Baja Prioridad (Bajo Pot / Bajo Share)")))) -> 2 - Foco Defensa (Alto Pot / Alto Share) | AX52: =IF(OR(IFERROR(AND(W52<>"",Y52<>"",Y52-W52>Resumen!$B$8),FALSE()),IFERROR(AND(X52<>"",Y52<>"",Y52-X52>Resumen!$B$8),FALSE())),MAX(IF(IFERROR(AND(W52<>"",Y52<>"",Y52-W52>Resumen!$B$8),FALSE()),Y52-W52,0),IF(IFERROR(AND(X52<>"",Y52<>"",Y52-X52>Resumen!$B$8),FALSE()),Y52-X52,0)),"") | AY52: =IF(OR(IFERROR(AND(W52<>"",Y52<>"",Y52-W52>Resumen!$B$8),FALSE()),IFERROR(AND(X52<>"",Y52<>"",Y52-X52>Resumen!$B$8),FALSE())),TRIM("Lays tiene mayor markup que "&IF(IFERROR(AND(W52<>"",Y52<>"",Y52-W52>Resumen!$B$8),FALSE()),"Quento ","")&IF(IFERROR(AND(X52<>"",Y52<>"",Y52-X52>Resumen!$B$8),FALSE()),"Julicroc ","")&"en este PDV"),"") | AZ52: =IF(COUNTIF('Plan Pehuamar - Lista'!$A$2:$A$167,A52)>0,"Sí","No") -> No | BA52: =IF(COUNTIF('Plan Combo 9+1'!$A$2:$A$226,A52)>0,"Sí","No") -> No | BB52: =IF(AH52="","No",IF(BA52="Sí",IF((AO52-AH52)>Resumen!$B$6,"Sí","No"),IF((AO52-AH52)>=Resumen!$B$132,"Sí","No"))) -> No | BC52: =IF(AND(N52="Sí",AL52="Sí",AI52=0),"Sí","No") -> No | BD52: =IF(COUNTIF('Plan 9+1 (con Pehuamar)'!$A$2:$A$227,A52)>0,"Sí","No") -> No
A53: 404437 | B53: 1 | C53: 101 | D53: Lunes | E53: GOMEZ ALEXIS SEBASTIAN | F53: Kiosco/Maxikiosco | G53: Santa Fe | H53: Conrado Pujol | I53: 30 | J53: 0 | K53: 40 | L53: =I53+J53 -> 30 | M53: =L53+K53 -> 70 | N53: =IF(I53>0,"Sí","No") -> Sí | O53: =IF(J53>0,"Sí","No") -> No | P53: =IF(K53>0,"Sí","No") -> Sí | Q53: =IF(OR(I53>0,J53>0),"Sí","No") -> Sí | R53: 1800 | S53: 3000 | V53: 3500 | W53: =IF(AND(I53>0,R53>0),(S53-R53)/R53,"") -> 0.66666667 | X53: =IF(AND(J53>0,T53>0),(U53-T53)/T53,"") | Y53: =IF(AND(K53>0,V53>0),(V53-Resumen!$B$7)/Resumen!$B$7,"") -> 0.4 | Z53: =IF(AND(K53>0,I53>0,V53>0,S53>0),V53-S53,"") -> 500 | AA53: =IF(Z53<>"",Z53/S53,"") -> 0.16666667 | AB53: =IF(AND(K53>0,J53>0,V53>0,U53>0),V53-U53,"") | AC53: =IF(AB53<>"",AB53/U53,"") | AD53: 8 | AE53: 4 | AF53: 0 | AG53: =AD53+AE53+AF53 -> 12 | AH53: =IF(AG53>0,AD53/AG53,"") -> 0.66666667 | AI53: 1 | AJ53: 0 | AK53: 0 | AL53: =IF(OR(AJ53>0,AK53>0),"Sí","No") -> No | AM53: Contado | AO53: =IF(M53>0,K53/M53,"") -> 0.57142857 | AP53: =IF(M53>=Resumen!$B$5,"Alto","Bajo") -> Alto | AQ53: =IF(AO53>=Resumen!$B$28,"Alto","Bajo") -> Alto | AR53: =AP53&" Potencial / "&AQ53&" Share" -> Alto Potencial / Alto Share | AS53: =IF(Q53="Sí",IF(AO53>=Resumen!$B$29,"Alto","Bajo"),"") -> Alto | AT53: =IF(AS53<>"",AP53&" Potencial / "&AS53&" Share","") -> Alto Potencial / Alto Share | AU53: =IF(AH53="","Sin dato",IF(AH53-AO53>Resumen!$B$6,"Sobre-exhibido",IF(AO53-AH53>Resumen!$B$6,"Sub-exhibido","En línea"))) -> Sobre-exhibido | AV53: =IF(AT53="","",IF(AT53="Alto Potencial / Bajo Share",1,IF(AT53="Alto Potencial / Alto Share",2,IF(AT53="Bajo Potencial / Alto Share",3,4)))) -> 2 | AW53: =IF(Q53="No","Sin competencia directa",IF(AV53=1,"1 - Foco Conquista (Alto Pot / Bajo Share)",IF(AV53=2,"2 - Foco Defensa (Alto Pot / Alto Share)",IF(AV53=3,"3 - Monitoreo (Bajo Pot / Alto Share)","4 - Baja Prioridad (Bajo Pot / Bajo Share)")))) -> 2 - Foco Defensa (Alto Pot / Alto Share) | AX53: =IF(OR(IFERROR(AND(W53<>"",Y53<>"",Y53-W53>Resumen!$B$8),FALSE()),IFERROR(AND(X53<>"",Y53<>"",Y53-X53>Resumen!$B$8),FALSE())),MAX(IF(IFERROR(AND(W53<>"",Y53<>"",Y53-W53>Resumen!$B$8),FALSE()),Y53-W53,0),IF(IFERROR(AND(X53<>"",Y53<>"",Y53-X53>Resumen!$B$8),FALSE()),Y53-X53,0)),"") | AY53: =IF(OR(IFERROR(AND(W53<>"",Y53<>"",Y53-W53>Resumen!$B$8),FALSE()),IFERROR(AND(X53<>"",Y53<>"",Y53-X53>Resumen!$B$8),FALSE())),TRIM("Lays tiene mayor markup que "&IF(IFERROR(AND(W53<>"",Y53<>"",Y53-W53>Resumen!$B$8),FALSE()),"Quento ","")&IF(IFERROR(AND(X53<>"",Y53<>"",Y53-X53>Resumen!$B$8),FALSE()),"Julicroc ","")&"en este PDV"),"") | AZ53: =IF(COUNTIF('Plan Pehuamar - Lista'!$A$2:$A$167,A53)>0,"Sí","No") -> No | BA53: =IF(COUNTIF('Plan Combo 9+1'!$A$2:$A$226,A53)>0,"Sí","No") -> No | BB53: =IF(AH53="","No",IF(BA53="Sí",IF((AO53-AH53)>Resumen!$B$6,"Sí","No"),IF((AO53-AH53)>=Resumen!$B$132,"Sí","No"))) -> No | BC53: =IF(AND(N53="Sí",AL53="Sí",AI53=0),"Sí","No") -> No | BD53: =IF(COUNTIF('Plan 9+1 (con Pehuamar)'!$A$2:$A$227,A53)>0,"Sí","No") -> No
A54: 400682 | B54: 1 | C54: 102 | D54: Martes | E54: MELIAN MIGUEL ANGEL | F54: Almacen/Despensa | G54: Santa Fe | H54: Conrado Pujol | I54: 0 | J54: 0 | K54: 0.5 | L54: =I54+J54 -> 0 | M54: =L54+K54 -> 0.5 | N54: =IF(I54>0,"Sí","No") -> No | O54: =IF(J54>0,"Sí","No") -> No | P54: =IF(K54>0,"Sí","No") -> Sí | Q54: =IF(OR(I54>0,J54>0),"Sí","No") -> No | W54: =IF(AND(I54>0,R54>0),(S54-R54)/R54,"") | X54: =IF(AND(J54>0,T54>0),(U54-T54)/T54,"") | Y54: =IF(AND(K54>0,V54>0),(V54-Resumen!$B$7)/Resumen!$B$7,"") | Z54: =IF(AND(K54>0,I54>0,V54>0,S54>0),V54-S54,"") | AA54: =IF(Z54<>"",Z54/S54,"") | AB54: =IF(AND(K54>0,J54>0,V54>0,U54>0),V54-U54,"") | AC54: =IF(AB54<>"",AB54/U54,"") | AD54: 0 | AE54: 0 | AF54: 0 | AG54: =AD54+AE54+AF54 -> 0 | AH54: =IF(AG54>0,AD54/AG54,"") | AI54: 0 | AJ54: 0 | AK54: 0 | AL54: =IF(OR(AJ54>0,AK54>0),"Sí","No") -> No | AO54: =IF(M54>0,K54/M54,"") -> 1 | AP54: =IF(M54>=Resumen!$B$5,"Alto","Bajo") -> Bajo | AQ54: =IF(AO54>=Resumen!$B$28,"Alto","Bajo") -> Alto | AR54: =AP54&" Potencial / "&AQ54&" Share" -> Bajo Potencial / Alto Share | AS54: =IF(Q54="Sí",IF(AO54>=Resumen!$B$29,"Alto","Bajo"),"") | AT54: =IF(AS54<>"",AP54&" Potencial / "&AS54&" Share","") | AU54: =IF(AH54="","Sin dato",IF(AH54-AO54>Resumen!$B$6,"Sobre-exhibido",IF(AO54-AH54>Resumen!$B$6,"Sub-exhibido","En línea"))) -> Sin dato | AV54: =IF(AT54="","",IF(AT54="Alto Potencial / Bajo Share",1,IF(AT54="Alto Potencial / Alto Share",2,IF(AT54="Bajo Potencial / Alto Share",3,4)))) | AW54: =IF(Q54="No","Sin competencia directa",IF(AV54=1,"1 - Foco Conquista (Alto Pot / Bajo Share)",IF(AV54=2,"2 - Foco Defensa (Alto Pot / Alto Share)",IF(AV54=3,"3 - Monitoreo (Bajo Pot / Alto Share)","4 - Baja Prioridad (Bajo Pot / Bajo Share)")))) -> Sin competencia directa | AX54: =IF(OR(IFERROR(AND(W54<>"",Y54<>"",Y54-W54>Resumen!$B$8),FALSE()),IFERROR(AND(X54<>"",Y54<>"",Y54-X54>Resumen!$B$8),FALSE())),MAX(IF(IFERROR(AND(W54<>"",Y54<>"",Y54-W54>Resumen!$B$8),FALSE()),Y54-W54,0),IF(IFERROR(AND(X54<>"",Y54<>"",Y54-X54>Resumen!$B$8),FALSE()),Y54-X54,0)),"") | AY54: =IF(OR(IFERROR(AND(W54<>"",Y54<>"",Y54-W54>Resumen!$B$8),FALSE()),IFERROR(AND(X54<>"",Y54<>"",Y54-X54>Resumen!$B$8),FALSE())),TRIM("Lays tiene mayor markup que "&IF(IFERROR(AND(W54<>"",Y54<>"",Y54-W54>Resumen!$B$8),FALSE()),"Quento ","")&IF(IFERROR(AND(X54<>"",Y54<>"",Y54-X54>Resumen!$B$8),FALSE()),"Julicroc ","")&"en este PDV"),"") | AZ54: =IF(COUNTIF('Plan Pehuamar - Lista'!$A$2:$A$167,A54)>0,"Sí","No") -> No | BA54: =IF(COUNTIF('Plan Combo 9+1'!$A$2:$A$226,A54)>0,"Sí","No") -> No | BB54: =IF(AH54="","No",IF(BA54="Sí",IF((AO54-AH54)>Resumen!$B$6,"Sí","No"),IF((AO54-AH54)>=Resumen!$B$132,"Sí","No"))) -> No | BC54: =IF(AND(N54="Sí",AL54="Sí",AI54=0),"Sí","No") -> No | BD54: =IF(COUNTIF('Plan 9+1 (con Pehuamar)'!$A$2:$A$227,A54)>0,"Sí","No") -> No
A55: 400699 | B55: 1 | C55: 102 | D55: Martes | E55: HADAD VANINA FERNANDA | F55: Kiosco/Maxikiosco | G55: Santa Fe | H55: Conrado Pujol | I55: 0 | J55: 0 | K55: 4.3 | L55: =I55+J55 -> 0 | M55: =L55+K55 -> 4.3 | N55: =IF(I55>0,"Sí","No") -> No | O55: =IF(J55>0,"Sí","No") -> No | P55: =IF(K55>0,"Sí","No") -> Sí | Q55: =IF(OR(I55>0,J55>0),"Sí","No") -> No | W55: =IF(AND(I55>0,R55>0),(S55-R55)/R55,"") | X55: =IF(AND(J55>0,T55>0),(U55-T55)/T55,"") | Y55: =IF(AND(K55>0,V55>0),(V55-Resumen!$B$7)/Resumen!$B$7,"") | Z55: =IF(AND(K55>0,I55>0,V55>0,S55>0),V55-S55,"") | AA55: =IF(Z55<>"",Z55/S55,"") | AB55: =IF(AND(K55>0,J55>0,V55>0,U55>0),V55-U55,"") | AC55: =IF(AB55<>"",AB55/U55,"") | AD55: 0 | AE55: 0 | AF55: 0 | AG55: =AD55+AE55+AF55 -> 0 | AH55: =IF(AG55>0,AD55/AG55,"") | AI55: 0 | AJ55: 0 | AK55: 0 | AL55: =IF(OR(AJ55>0,AK55>0),"Sí","No") -> No | AO55: =IF(M55>0,K55/M55,"") -> 1 | AP55: =IF(M55>=Resumen!$B$5,"Alto","Bajo") -> Bajo | AQ55: =IF(AO55>=Resumen!$B$28,"Alto","Bajo") -> Alto | AR55: =AP55&" Potencial / "&AQ55&" Share" -> Bajo Potencial / Alto Share | AS55: =IF(Q55="Sí",IF(AO55>=Resumen!$B$29,"Alto","Bajo"),"") | AT55: =IF(AS55<>"",AP55&" Potencial / "&AS55&" Share","") | AU55: =IF(AH55="","Sin dato",IF(AH55-AO55>Resumen!$B$6,"Sobre-exhibido",IF(AO55-AH55>Resumen!$B$6,"Sub-exhibido","En línea"))) -> Sin dato | AV55: =IF(AT55="","",IF(AT55="Alto Potencial / Bajo Share",1,IF(AT55="Alto Potencial / Alto Share",2,IF(AT55="Bajo Potencial / Alto Share",3,4)))) | AW55: =IF(Q55="No","Sin competencia directa",IF(AV55=1,"1 - Foco Conquista (Alto Pot / Bajo Share)",IF(AV55=2,"2 - Foco Defensa (Alto Pot / Alto Share)",IF(AV55=3,"3 - Monitoreo (Bajo Pot / Alto Share)","4 - Baja Prioridad (Bajo Pot / Bajo Share)")))) -> Sin competencia directa | AX55: =IF(OR(IFERROR(AND(W55<>"",Y55<>"",Y55-W55>Resumen!$B$8),FALSE()),IFERROR(AND(X55<>"",Y55<>"",Y55-X55>Resumen!$B$8),FALSE())),MAX(IF(IFERROR(AND(W55<>"",Y55<>"",Y55-W55>Resumen!$B$8),FALSE()),Y55-W55,0),IF(IFERROR(AND(X55<>"",Y55<>"",Y55-X55>Resumen!$B$8),FALSE()),Y55-X55,0)),"") | AY55: =IF(OR(IFERROR(AND(W55<>"",Y55<>"",Y55-W55>Resumen!$B$8),FALSE()),IFERROR(AND(X55<>"",Y55<>"",Y55-X55>Resumen!$B$8),FALSE())),TRIM("Lays tiene mayor markup que "&IF(IFERROR(AND(W55<>"",Y55<>"",Y55-W55>Resumen!$B$8),FALSE()),"Quento ","")&IF(IFERROR(AND(X55<>"",Y55<>"",Y55-X55>Resumen!$B$8),FALSE()),"Julicroc ","")&"en este PDV"),"") | AZ55: =IF(COUNTIF('Plan Pehuamar - Lista'!$A$2:$A$167,A55)>0,"Sí","No") -> No | BA55: =IF(COUNTIF('Plan Combo 9+1'!$A$2:$A$226,A55)>0,"Sí","No") -> No | BB55: =IF(AH55="","No",IF(BA55="Sí",IF((AO55-AH55)>Resumen!$B$6,"Sí","No"),IF((AO55-AH55)>=Resumen!$B$132,"Sí","No"))) -> No | BC55: =IF(AND(N55="Sí",AL55="Sí",AI55=0),"Sí","No") -> No | BD55: =IF(COUNTIF('Plan 9+1 (con Pehuamar)'!$A$2:$A$227,A55)>0,"Sí","No") -> No
A56: 400829 | B56: 1 | C56: 102 | D56: Martes | E56: MARTINEZ NELLI SUSANA | F56: Almacen/Despensa | G56: Santa Fe | H56: Conrado Pujol | I56: 0 | J56: 0 | K56: 0.2 | L56: =I56+J56 -> 0 | M56: =L56+K56 -> 0.2 | N56: =IF(I56>0,"Sí","No") -> No | O56: =IF(J56>0,"Sí","No") -> No | P56: =IF(K56>0,"Sí","No") -> Sí | Q56: =IF(OR(I56>0,J56>0),"Sí","No") -> No | W56: =IF(AND(I56>0,R56>0),(S56-R56)/R56,"") | X56: =IF(AND(J56>0,T56>0),(U56-T56)/T56,"") | Y56: =IF(AND(K56>0,V56>0),(V56-Resumen!$B$7)/Resumen!$B$7,"") | Z56: =IF(AND(K56>0,I56>0,V56>0,S56>0),V56-S56,"") | AA56: =IF(Z56<>"",Z56/S56,"") | AB56: =IF(AND(K56>0,J56>0,V56>0,U56>0),V56-U56,"") | AC56: =IF(AB56<>"",AB56/U56,"") | AD56: 0 | AE56: 0 | AF56: 0 | AG56: =AD56+AE56+AF56 -> 0 | AH56: =IF(AG56>0,AD56/AG56,"") | AI56: 0 | AJ56: 0 | AK56: 0 | AL56: =IF(OR(AJ56>0,AK56>0),"Sí","No") -> No | AO56: =IF(M56>0,K56/M56,"") -> 1 | AP56: =IF(M56>=Resumen!$B$5,"Alto","Bajo") -> Bajo | AQ56: =IF(AO56>=Resumen!$B$28,"Alto","Bajo") -> Alto | AR56: =AP56&" Potencial / "&AQ56&" Share" -> Bajo Potencial / Alto Share | AS56: =IF(Q56="Sí",IF(AO56>=Resumen!$B$29,"Alto","Bajo"),"") | AT56: =IF(AS56<>"",AP56&" Potencial / "&AS56&" Share","") | AU56: =IF(AH56="","Sin dato",IF(AH56-AO56>Resumen!$B$6,"Sobre-exhibido",IF(AO56-AH56>Resumen!$B$6,"Sub-exhibido","En línea"))) -> Sin dato | AV56: =IF(AT56="","",IF(AT56="Alto Potencial / Bajo Share",1,IF(AT56="Alto Potencial / Alto Share",2,IF(AT56="Bajo Potencial / Alto Share",3,4)))) | AW56: =IF(Q56="No","Sin competencia directa",IF(AV56=1,"1 - Foco Conquista (Alto Pot / Bajo Share)",IF(AV56=2,"2 - Foco Defensa (Alto Pot / Alto Share)",IF(AV56=3,"3 - Monitoreo (Bajo Pot / Alto Share)","4 - Baja Prioridad (Bajo Pot / Bajo Share)")))) -> Sin competencia directa | AX56: =IF(OR(IFERROR(AND(W56<>"",Y56<>"",Y56-W56>Resumen!$B$8),FALSE()),IFERROR(AND(X56<>"",Y56<>"",Y56-X56>Resumen!$B$8),FALSE())),MAX(IF(IFERROR(AND(W56<>"",Y56<>"",Y56-W56>Resumen!$B$8),FALSE()),Y56-W56,0),IF(IFERROR(AND(X56<>"",Y56<>"",Y56-X56>Resumen!$B$8),FALSE()),Y56-X56,0)),"") | AY56: =IF(OR(IFERROR(AND(W56<>"",Y56<>"",Y56-W56>Resumen!$B$8),FALSE()),IFERROR(AND(X56<>"",Y56<>"",Y56-X56>Resumen!$B$8),FALSE())),TRIM("Lays tiene mayor markup que "&IF(IFERROR(AND(W56<>"",Y56<>"",Y56-W56>Resumen!$B$8),FALSE()),"Quento ","")&IF(IFERROR(AND(X56<>"",Y56<>"",Y56-X56>Resumen!$B$8),FALSE()),"Julicroc ","")&"en este PDV"),"") | AZ56: =IF(COUNTIF('Plan Pehuamar - Lista'!$A$2:$A$167,A56)>0,"Sí","No") -> No | BA56: =IF(COUNTIF('Plan Combo 9+1'!$A$2:$A$226,A56)>0,"Sí","No") -> No | BB56: =IF(AH56="","No",IF(BA56="Sí",IF((AO56-AH56)>Resumen!$B$6,"Sí","No"),IF((AO56-AH56)>=Resumen!$B$132,"Sí","No"))) -> No | BC56: =IF(AND(N56="Sí",AL56="Sí",AI56=0),"Sí","No") -> No | BD56: =IF(COUNTIF('Plan 9+1 (con Pehuamar)'!$A$2:$A$227,A56)>0,"Sí","No") -> No
A57: 400855 | B57: 1 | C57: 102 | D57: Martes | E57: RIOJA ADRIAN FEDERICO DEL CORA | F57: Kiosco/Maxikiosco | G57: Santa Fe | H57: Conrado Pujol | I57: 0 | J57: 0 | K57: 3.1 | L57: =I57+J57 -> 0 | M57: =L57+K57 -> 3.1 | N57: =IF(I57>0,"Sí","No") -> No | O57: =IF(J57>0,"Sí","No") -> No | P57: =IF(K57>0,"Sí","No") -> Sí | Q57: =IF(OR(I57>0,J57>0),"Sí","No") -> No | W57: =IF(AND(I57>0,R57>0),(S57-R57)/R57,"") | X57: =IF(AND(J57>0,T57>0),(U57-T57)/T57,"") | Y57: =IF(AND(K57>0,V57>0),(V57-Resumen!$B$7)/Resumen!$B$7,"") | Z57: =IF(AND(K57>0,I57>0,V57>0,S57>0),V57-S57,"") | AA57: =IF(Z57<>"",Z57/S57,"") | AB57: =IF(AND(K57>0,J57>0,V57>0,U57>0),V57-U57,"") | AC57: =IF(AB57<>"",AB57/U57,"") | AD57: 0 | AE57: 0 | AF57: 0 | AG57: =AD57+AE57+AF57 -> 0 | AH57: =IF(AG57>0,AD57/AG57,"") | AI57: 0 | AJ57: 0 | AK57: 0 | AL57: =IF(OR(AJ57>0,AK57>0),"Sí","No") -> No | AO57: =IF(M57>0,K57/M57,"") -> 1 | AP57: =IF(M57>=Resumen!$B$5,"Alto","Bajo") -> Bajo | AQ57: =IF(AO57>=Resumen!$B$28,"Alto","Bajo") -> Alto | AR57: =AP57&" Potencial / "&AQ57&" Share" -> Bajo Potencial / Alto Share | AS57: =IF(Q57="Sí",IF(AO57>=Resumen!$B$29,"Alto","Bajo"),"") | AT57: =IF(AS57<>"",AP57&" Potencial / "&AS57&" Share","") | AU57: =IF(AH57="","Sin dato",IF(AH57-AO57>Resumen!$B$6,"Sobre-exhibido",IF(AO57-AH57>Resumen!$B$6,"Sub-exhibido","En línea"))) -> Sin dato | AV57: =IF(AT57="","",IF(AT57="Alto Potencial / Bajo Share",1,IF(AT57="Alto Potencial / Alto Share",2,IF(AT57="Bajo Potencial / Alto Share",3,4)))) | AW57: =IF(Q57="No","Sin competencia directa",IF(AV57=1,"1 - Foco Conquista (Alto Pot / Bajo Share)",IF(AV57=2,"2 - Foco Defensa (Alto Pot / Alto Share)",IF(AV57=3,"3 - Monitoreo (Bajo Pot / Alto Share)","4 - Baja Prioridad (Bajo Pot / Bajo Share)")))) -> Sin competencia directa | AX57: =IF(OR(IFERROR(AND(W57<>"",Y57<>"",Y57-W57>Resumen!$B$8),FALSE()),IFERROR(AND(X57<>"",Y57<>"",Y57-X57>Resumen!$B$8),FALSE())),MAX(IF(IFERROR(AND(W57<>"",Y57<>"",Y57-W57>Resumen!$B$8),FALSE()),Y57-W57,0),IF(IFERROR(AND(X57<>"",Y57<>"",Y57-X57>Resumen!$B$8),FALSE()),Y57-X57,0)),"") | AY57: =IF(OR(IFERROR(AND(W57<>"",Y57<>"",Y57-W57>Resumen!$B$8),FALSE()),IFERROR(AND(X57<>"",Y57<>"",Y57-X57>Resumen!$B$8),FALSE())),TRIM("Lays tiene mayor markup que "&IF(IFERROR(AND(W57<>"",Y57<>"",Y57-W57>Resumen!$B$8),FALSE()),"Quento ","")&IF(IFERROR(AND(X57<>"",Y57<>"",Y57-X57>Resumen!$B$8),FALSE()),"Julicroc ","")&"en este PDV"),"") | AZ57: =IF(COUNTIF('Plan Pehuamar - Lista'!$A$2:$A$167,A57)>0,"Sí","No") -> No | BA57: =IF(COUNTIF('Plan Combo 9+1'!$A$2:$A$226,A57)>0,"Sí","No") -> No | BB57: =IF(AH57="","No",IF(BA57="Sí",IF((AO57-AH57)>Resumen!$B$6,"Sí","No"),IF((AO57-AH57)>=Resumen!$B$132,"Sí","No"))) -> No | BC57: =IF(AND(N57="Sí",AL57="Sí",AI57=0),"Sí","No") -> No | BD57: =IF(COUNTIF('Plan 9+1 (con Pehuamar)'!$A$2:$A$227,A57)>0,"Sí","No") -> No
A58: 400856 | B58: 1 | C58: 102 | D58: Martes | E58: BODE SRL | F58: Autoservicio Tradicional | G58: Santa Fe | H58: Conrado Pujol | I58: 70 | J58: 50 | K58: 80 | L58: =I58+J58 -> 120 | M58: =L58+K58 -> 200 | N58: =IF(I58>0,"Sí","No") -> Sí | O58: =IF(J58>0,"Sí","No") -> Sí | P58: =IF(K58>0,"Sí","No") -> Sí | Q58: =IF(OR(I58>0,J58>0),"Sí","No") -> Sí | R58: 1900 | S58: 2900 | T58: 1700 | U58: 2508 | V58: 3700 | W58: =IF(AND(I58>0,R58>0),(S58-R58)/R58,"") -> 0.52631579 | X58: =IF(AND(J58>0,T58>0),(U58-T58)/T58,"") -> 0.47529412 | Y58: =IF(AND(K58>0,V58>0),(V58-Resumen!$B$7)/Resumen!$B$7,"") -> 0.48 | Z58: =IF(AND(K58>0,I58>0,V58>0,S58>0),V58-S58,"") -> 800 | AA58: =IF(Z58<>"",Z58/S58,"") -> 0.27586207 | AB58: =IF(AND(K58>0,J58>0,V58>0,U58>0),V58-U58,"") -> 1192 | AC58: =IF(AB58<>"",AB58/U58,"") -> 0.47527911 | AD58: 8 | AE58: 4 | AF58: 3 | AG58: =AD58+AE58+AF58 -> 15 | AH58: =IF(AG58>0,AD58/AG58,"") -> 0.53333333 | AI58: 1 | AJ58: 0 | AK58: 0 | AL58: =IF(OR(AJ58>0,AK58>0),"Sí","No") -> No | AM58: Contado | AN58: Contado | AO58: =IF(M58>0,K58/M58,"") -> 0.4 | AP58: =IF(M58>=Resumen!$B$5,"Alto","Bajo") -> Alto | AQ58: =IF(AO58>=Resumen!$B$28,"Alto","Bajo") -> Alto | AR58: =AP58&" Potencial / "&AQ58&" Share" -> Alto Potencial / Alto Share | AS58: =IF(Q58="Sí",IF(AO58>=Resumen!$B$29,"Alto","Bajo"),"") -> Bajo | AT58: =IF(AS58<>"",AP58&" Potencial / "&AS58&" Share","") -> Alto Potencial / Bajo Share | AU58: =IF(AH58="","Sin dato",IF(AH58-AO58>Resumen!$B$6,"Sobre-exhibido",IF(AO58-AH58>Resumen!$B$6,"Sub-exhibido","En línea"))) -> Sobre-exhibido | AV58: =IF(AT58="","",IF(AT58="Alto Potencial / Bajo Share",1,IF(AT58="Alto Potencial / Alto Share",2,IF(AT58="Bajo Potencial / Alto Share",3,4)))) -> 1 | AW58: =IF(Q58="No","Sin competencia directa",IF(AV58=1,"1 - Foco Conquista (Alto Pot / Bajo Share)",IF(AV58=2,"2 - Foco Defensa (Alto Pot / Alto Share)",IF(AV58=3,"3 - Monitoreo (Bajo Pot / Alto Share)","4 - Baja Prioridad (Bajo Pot / Bajo Share)")))) -> 1 - Foco Conquista (Alto Pot / Bajo Share) | AX58: =IF(OR(IFERROR(AND(W58<>"",Y58<>"",Y58-W58>Resumen!$B$8),FALSE()),IFERROR(AND(X58<>"",Y58<>"",Y58-X58>Resumen!$B$8),FALSE())),MAX(IF(IFERROR(AND(W58<>"",Y58<>"",Y58-W58>Resumen!$B$8),FALSE()),Y58-W58,0),IF(IFERROR(AND(X58<>"",Y58<>"",Y58-X58>Resumen!$B$8),FALSE()),Y58-X58,0)),"") | AY58: =IF(OR(IFERROR(AND(W58<>"",Y58<>"",Y58-W58>Resumen!$B$8),FALSE()),IFERROR(AND(X58<>"",Y58<>"",Y58-X58>Resumen!$B$8),FALSE())),TRIM("Lays tiene mayor markup que "&IF(IFERROR(AND(W58<>"",Y58<>"",Y58-W58>Resumen!$B$8),FALSE()),"Quento ","")&IF(IFERROR(AND(X58<>"",Y58<>"",Y58-X58>Resumen!$B$8),FALSE()),"Julicroc ","")&"en este PDV"),"") | AZ58: =IF(COUNTIF('Plan Pehuamar - Lista'!$A$2:$A$167,A58)>0,"Sí","No") -> No | BA58: =IF(COUNTIF('Plan Combo 9+1'!$A$2:$A$226,A58)>0,"Sí","No") -> No | BB58: =IF(AH58="","No",IF(BA58="Sí",IF((AO58-AH58)>Resumen!$B$6,"Sí","No"),IF((AO58-AH58)>=Resumen!$B$132,"Sí","No"))) -> No | BC58: =IF(AND(N58="Sí",AL58="Sí",AI58=0),"Sí","No") -> No | BD58: =IF(COUNTIF('Plan 9+1 (con Pehuamar)'!$A$2:$A$227,A58)>0,"Sí","No") -> No
A59: 400859 | B59: 1 | C59: 102 | D59: Martes | E59: ROMERO JULIO ARIEL IVAN | F59: Centros de entrenamiento/Espacios Deportivos | G59: Santa Fe | H59: Conrado Pujol | I59: 0 | J59: 0 | K59: 0.2 | L59: =I59+J59 -> 0 | M59: =L59+K59 -> 0.2 | N59: =IF(I59>0,"Sí","No") -> No | O59: =IF(J59>0,"Sí","No") -> No | P59: =IF(K59>0,"Sí","No") -> Sí | Q59: =IF(OR(I59>0,J59>0),"Sí","No") -> No | W59: =IF(AND(I59>0,R59>0),(S59-R59)/R59,"") | X59: =IF(AND(J59>0,T59>0),(U59-T59)/T59,"") | Y59: =IF(AND(K59>0,V59>0),(V59-Resumen!$B$7)/Resumen!$B$7,"") | Z59: =IF(AND(K59>0,I59>0,V59>0,S59>0),V59-S59,"") | AA59: =IF(Z59<>"",Z59/S59,"") | AB59: =IF(AND(K59>0,J59>0,V59>0,U59>0),V59-U59,"") | AC59: =IF(AB59<>"",AB59/U59,"") | AD59: 0 | AE59: 0 | AF59: 0 | AG59: =AD59+AE59+AF59 -> 0 | AH59: =IF(AG59>0,AD59/AG59,"") | AI59: 0 | AJ59: 0 | AK59: 0 | AL59: =IF(OR(AJ59>0,AK59>0),"Sí","No") -> No | AO59: =IF(M59>0,K59/M59,"") -> 1 | AP59: =IF(M59>=Resumen!$B$5,"Alto","Bajo") -> Bajo | AQ59: =IF(AO59>=Resumen!$B$28,"Alto","Bajo") -> Alto | AR59: =AP59&" Potencial / "&AQ59&" Share" -> Bajo Potencial / Alto Share | AS59: =IF(Q59="Sí",IF(AO59>=Resumen!$B$29,"Alto","Bajo"),"") | AT59: =IF(AS59<>"",AP59&" Potencial / "&AS59&" Share","") | AU59: =IF(AH59="","Sin dato",IF(AH59-AO59>Resumen!$B$6,"Sobre-exhibido",IF(AO59-AH59>Resumen!$B$6,"Sub-exhibido","En línea"))) -> Sin dato | AV59: =IF(AT59="","",IF(AT59="Alto Potencial / Bajo Share",1,IF(AT59="Alto Potencial / Alto Share",2,IF(AT59="Bajo Potencial / Alto Share",3,4)))) | AW59: =IF(Q59="No","Sin competencia directa",IF(AV59=1,"1 - Foco Conquista (Alto Pot / Bajo Share)",IF(AV59=2,"2 - Foco Defensa (Alto Pot / Alto Share)",IF(AV59=3,"3 - Monitoreo (Bajo Pot / Alto Share)","4 - Baja Prioridad (Bajo Pot / Bajo Share)")))) -> Sin competencia directa | AX59: =IF(OR(IFERROR(AND(W59<>"",Y59<>"",Y59-W59>Resumen!$B$8),FALSE()),IFERROR(AND(X59<>"",Y59<>"",Y59-X59>Resumen!$B$8),FALSE())),MAX(IF(IFERROR(AND(W59<>"",Y59<>"",Y59-W59>Resumen!$B$8),FALSE()),Y59-W59,0),IF(IFERROR(AND(X59<>"",Y59<>"",Y59-X59>Resumen!$B$8),FALSE()),Y59-X59,0)),"") | AY59: =IF(OR(IFERROR(AND(W59<>"",Y59<>"",Y59-W59>Resumen!$B$8),FALSE()),IFERROR(AND(X59<>"",Y59<>"",Y59-X59>Resumen!$B$8),FALSE())),TRIM("Lays tiene mayor markup que "&IF(IFERROR(AND(W59<>"",Y59<>"",Y59-W59>Resumen!$B$8),FALSE()),"Quento ","")&IF(IFERROR(AND(X59<>"",Y59<>"",Y59-X59>Resumen!$B$8),FALSE()),"Julicroc ","")&"en este PDV"),"") | AZ59: =IF(COUNTIF('Plan Pehuamar - Lista'!$A$2:$A$167,A59)>0,"Sí","No") -> No | BA59: =IF(COUNTIF('Plan Combo 9+1'!$A$2:$A$226,A59)>0,"Sí","No") -> No | BB59: =IF(AH59="","No",IF(BA59="Sí",IF((AO59-AH59)>Resumen!$B$6,"Sí","No"),IF((AO59-AH59)>=Resumen!$B$132,"Sí","No"))) -> No | BC59: =IF(AND(N59="Sí",AL59="Sí",AI59=0),"Sí","No") -> No | BD59: =IF(COUNTIF('Plan 9+1 (con Pehuamar)'!$A$2:$A$227,A59)>0,"Sí","No") -> No
A60: 400865 | B60: 1 | C60: 102 | D60: Martes | E60: SANTORO MARCELO FABIAN | F60: Autoservicio Tradicional | G60: Santa Fe | H60: Conrado Pujol | I60: 40 | J60: 30 | K60: 50 | L60: =I60+J60 -> 70 | M60: =L60+K60 -> 120 | N60: =IF(I60>0,"Sí","No") -> Sí | O60: =IF(J60>0,"Sí","No") -> Sí | P60: =IF(K60>0,"Sí","No") -> Sí | Q60: =IF(OR(I60>0,J60>0),"Sí","No") -> Sí | R60: 1700 | S60: 2800 | T60: 1500 | U60: 2600 | V60: 3500 | W60: =IF(AND(I60>0,R60>0),(S60-R60)/R60,"") -> 0.64705882 | X60: =IF(AND(J60>0,T60>0),(U60-T60)/T60,"") -> 0.73333333 | Y60: =IF(AND(K60>0,V60>0),(V60-Resumen!$B$7)/Resumen!$B$7,"") -> 0.4 | Z60: =IF(AND(K60>0,I60>0,V60>0,S60>0),V60-S60,"") -> 700 | AA60: =IF(Z60<>"",Z60/S60,"") -> 0.25 | AB60: =IF(AND(K60>0,J60>0,V60>0,U60>0),V60-U60,"") -> 900 | AC60: =IF(AB60<>"",AB60/U60,"") -> 0.34615385 | AD60: 8 | AE60: 4 | AF60: 4 | AG60: =AD60+AE60+AF60 -> 16 | AH60: =IF(AG60>0,AD60/AG60,"") -> 0.5 | AI60: 1 | AJ60: 1 | AK60: 1 | AL60: =IF(OR(AJ60>0,AK60>0),"Sí","No") -> Sí | AM60: Contado | AN60: Contado | AO60: =IF(M60>0,K60/M60,"") -> 0.41666667 | AP60: =IF(M60>=Resumen!$B$5,"Alto","Bajo") -> Alto | AQ60: =IF(AO60>=Resumen!$B$28,"Alto","Bajo") -> Alto | AR60: =AP60&" Potencial / "&AQ60&" Share" -> Alto Potencial / Alto Share | AS60: =IF(Q60="Sí",IF(AO60>=Resumen!$B$29,"Alto","Bajo"),"") -> Bajo | AT60: =IF(AS60<>"",AP60&" Potencial / "&AS60&" Share","") -> Alto Potencial / Bajo Share | AU60: =IF(AH60="","Sin dato",IF(AH60-AO60>Resumen!$B$6,"Sobre-exhibido",IF(AO60-AH60>Resumen!$B$6,"Sub-exhibido","En línea"))) -> Sobre-exhibido | AV60: =IF(AT60="","",IF(AT60="Alto Potencial / Bajo Share",1,IF(AT60="Alto Potencial / Alto Share",2,IF(AT60="Bajo Potencial / Alto Share",3,4)))) -> 1 | AW60: =IF(Q60="No","Sin competencia directa",IF(AV60=1,"1 - Foco Conquista (Alto Pot / Bajo Share)",IF(AV60=2,"2 - Foco Defensa (Alto Pot / Alto Share)",IF(AV60=3,"3 - Monitoreo (Bajo Pot / Alto Share)","4 - Baja Prioridad (Bajo Pot / Bajo Share)")))) -> 1 - Foco Conquista (Alto Pot / Bajo Share) | AX60: =IF(OR(IFERROR(AND(W60<>"",Y60<>"",Y60-W60>Resumen!$B$8),FALSE()),IFERROR(AND(X60<>"",Y60<>"",Y60-X60>Resumen!$B$8),FALSE())),MAX(IF(IFERROR(AND(W60<>"",Y60<>"",Y60-W60>Resumen!$B$8),FALSE()),Y60-W60,0),IF(IFERROR(AND(X60<>"",Y60<>"",Y60-X60>Resumen!$B$8),FALSE()),Y60-X60,0)),"") | AY60: =IF(OR(IFERROR(AND(W60<>"",Y60<>"",Y60-W60>Resumen!$B$8),FALSE()),IFERROR(AND(X60<>"",Y60<>"",Y60-X60>Resumen!$B$8),FALSE())),TRIM("Lays tiene mayor markup que "&IF(IFERROR(AND(W60<>"",Y60<>"",Y60-W60>Resumen!$B$8),FALSE()),"Quento ","")&IF(IFERROR(AND(X60<>"",Y60<>"",Y60-X60>Resumen!$B$8),FALSE()),"Julicroc ","")&"en este PDV"),"") | AZ60: =IF(COUNTIF('Plan Pehuamar - Lista'!$A$2:$A$167,A60)>0,"Sí","No") -> No | BA60: =IF(COUNTIF('Plan Combo 9+1'!$A$2:$A$226,A60)>0,"Sí","No") -> No | BB60: =IF(AH60="","No",IF(BA60="Sí",IF((AO60-AH60)>Resumen!$B$6,"Sí","No"),IF((AO60-AH60)>=Resumen!$B$132,"Sí","No"))) -> No | BC60: =IF(AND(N60="Sí",AL60="Sí",AI60=0),"Sí","No") -> No | BD60: =IF(COUNTIF('Plan 9+1 (con Pehuamar)'!$A$2:$A$227,A60)>0,"Sí","No") -> No
A61: 400873 | B61: 1 | C61: 102 | D61: Martes | E61: LIU MINGMET | F61: Autoservicio Tradicional | G61: Santa Fe | H61: Conrado Pujol | I61: 40 | J61: 40 | K61: 50 | L61: =I61+J61 -> 80 | M61: =L61+K61 -> 130 | N61: =IF(I61>0,"Sí","No") -> Sí | O61: =IF(J61>0,"Sí","No") -> Sí | P61: =IF(K61>0,"Sí","No") -> Sí | Q61: =IF(OR(I61>0,J61>0),"Sí","No") -> Sí | R61: 2000 | S61: 3050 | T61: 1700 | U61: 2500 | V61: 3500 | W61: =IF(AND(I61>0,R61>0),(S61-R61)/R61,"") -> 0.525 | X61: =IF(AND(J61>0,T61>0),(U61-T61)/T61,"") -> 0.47058824 | Y61: =IF(AND(K61>0,V61>0),(V61-Resumen!$B$7)/Resumen!$B$7,"") -> 0.4 | Z61: =IF(AND(K61>0,I61>0,V61>0,S61>0),V61-S61,"") -> 450 | AA61: =IF(Z61<>"",Z61/S61,"") -> 0.14754098 | AB61: =IF(AND(K61>0,J61>0,V61>0,U61>0),V61-U61,"") -> 1000 | AC61: =IF(AB61<>"",AB61/U61,"") -> 0.4 | AD61: 5 | AE61: 3 | AF61: 2 | AG61: =AD61+AE61+AF61 -> 10 | AH61: =IF(AG61>0,AD61/AG61,"") -> 0.5 | AI61: 1 | AJ61: 0 | AK61: 0 | AL61: =IF(OR(AJ61>0,AK61>0),"Sí","No") -> No | AM61: Contado | AN61: Contado | AO61: =IF(M61>0,K61/M61,"") -> 0.38461538 | AP61: =IF(M61>=Resumen!$B$5,"Alto","Bajo") -> Alto | AQ61: =IF(AO61>=Resumen!$B$28,"Alto","Bajo") -> Bajo | AR61: =AP61&" Potencial / "&AQ61&" Share" -> Alto Potencial / Bajo Share | AS61: =IF(Q61="Sí",IF(AO61>=Resumen!$B$29,"Alto","Bajo"),"") -> Bajo | AT61: =IF(AS61<>"",AP61&" Potencial / "&AS61&" Share","") -> Alto Potencial / Bajo Share | AU61: =IF(AH61="","Sin dato",IF(AH61-AO61>Resumen!$B$6,"Sobre-exhibido",IF(AO61-AH61>Resumen!$B$6,"Sub-exhibido","En línea"))) -> Sobre-exhibido | AV61: =IF(AT61="","",IF(AT61="Alto Potencial / Bajo Share",1,IF(AT61="Alto Potencial / Alto Share",2,IF(AT61="Bajo Potencial / Alto Share",3,4)))) -> 1 | AW61: =IF(Q61="No","Sin competencia directa",IF(AV61=1,"1 - Foco Conquista (Alto Pot / Bajo Share)",IF(AV61=2,"2 - Foco Defensa (Alto Pot / Alto Share)",IF(AV61=3,"3 - Monitoreo (Bajo Pot / Alto Share)","4 - Baja Prioridad (Bajo Pot / Bajo Share)")))) -> 1 - Foco Conquista (Alto Pot / Bajo Share) | AX61: =IF(OR(IFERROR(AND(W61<>"",Y61<>"",Y61-W61>Resumen!$B$8),FALSE()),IFERROR(AND(X61<>"",Y61<>"",Y61-X61>Resumen!$B$8),FALSE())),MAX(IF(IFERROR(AND(W61<>"",Y61<>"",Y61-W61>Resumen!$B$8),FALSE()),Y61-W61,0),IF(IFERROR(AND(X61<>"",Y61<>"",Y61-X61>Resumen!$B$8),FALSE()),Y61-X61,0)),"") | AY61: =IF(OR(IFERROR(AND(W61<>"",Y61<>"",Y61-W61>Resumen!$B$8),FALSE()),IFERROR(AND(X61<>"",Y61<>"",Y61-X61>Resumen!$B$8),FALSE())),TRIM("Lays tiene mayor markup que "&IF(IFERROR(AND(W61<>"",Y61<>"",Y61-W61>Resumen!$B$8),FALSE()),"Quento ","")&IF(IFERROR(AND(X61<>"",Y61<>"",Y61-X61>Resumen!$B$8),FALSE()),"Julicroc ","")&"en este PDV"),"") | AZ61: =IF(COUNTIF('Plan Pehuamar - Lista'!$A$2:$A$167,A61)>0,"Sí","No") -> No | BA61: =IF(COUNTIF('Plan Combo 9+1'!$A$2:$A$226,A61)>0,"Sí","No") -> No | BB61: =IF(AH61="","No",IF(BA61="Sí",IF((AO61-AH61)>Resumen!$B$6,"Sí","No"),IF((AO61-AH61)>=Resumen!$B$132,"Sí","No"))) -> No | BC61: =IF(AND(N61="Sí",AL61="Sí",AI61=0),"Sí","No") -> No | BD61: =IF(COUNTIF('Plan 9+1 (con Pehuamar)'!$A$2:$A$227,A61)>0,"Sí","No") -> No
A62: 400875 | B62: 1 | C62: 102 | D62: Martes | E62: LACOSTE GRISELDA | F62: Kiosco/Maxikiosco | G62: Santa Fe | H62: Conrado Pujol | I62: 0 | J62: 0 | K62: 0.8 | L62: =I62+J62 -> 0 | M62: =L62+K62 -> 0.8 | N62: =IF(I62>0,"Sí","No") -> No | O62: =IF(J62>0,"Sí","No") -> No | P62: =IF(K62>0,"Sí","No") -> Sí | Q62: =IF(OR(I62>0,J62>0),"Sí","No") -> No | W62: =IF(AND(I62>0,R62>0),(S62-R62)/R62,"") | X62: =IF(AND(J62>0,T62>0),(U62-T62)/T62,"") | Y62: =IF(AND(K62>0,V62>0),(V62-Resumen!$B$7)/Resumen!$B$7,"") | Z62: =IF(AND(K62>0,I62>0,V62>0,S62>0),V62-S62,"") | AA62: =IF(Z62<>"",Z62/S62,"") | AB62: =IF(AND(K62>0,J62>0,V62>0,U62>0),V62-U62,"") | AC62: =IF(AB62<>"",AB62/U62,"") | AD62: 0 | AE62: 0 | AF62: 0 | AG62: =AD62+AE62+AF62 -> 0 | AH62: =IF(AG62>0,AD62/AG62,"") | AI62: 0 | AJ62: 0 | AK62: 0 | AL62: =IF(OR(AJ62>0,AK62>0),"Sí","No") -> No | AO62: =IF(M62>0,K62/M62,"") -> 1 | AP62: =IF(M62>=Resumen!$B$5,"Alto","Bajo") -> Bajo | AQ62: =IF(AO62>=Resumen!$B$28,"Alto","Bajo") -> Alto | AR62: =AP62&" Potencial / "&AQ62&" Share" -> Bajo Potencial / Alto Share | AS62: =IF(Q62="Sí",IF(AO62>=Resumen!$B$29,"Alto","Bajo"),"") | AT62: =IF(AS62<>"",AP62&" Potencial / "&AS62&" Share","") | AU62: =IF(AH62="","Sin dato",IF(AH62-AO62>Resumen!$B$6,"Sobre-exhibido",IF(AO62-AH62>Resumen!$B$6,"Sub-exhibido","En línea"))) -> Sin dato | AV62: =IF(AT62="","",IF(AT62="Alto Potencial / Bajo Share",1,IF(AT62="Alto Potencial / Alto Share",2,IF(AT62="Bajo Potencial / Alto Share",3,4)))) | AW62: =IF(Q62="No","Sin competencia directa",IF(AV62=1,"1 - Foco Conquista (Alto Pot / Bajo Share)",IF(AV62=2,"2 - Foco Defensa (Alto Pot / Alto Share)",IF(AV62=3,"3 - Monitoreo (Bajo Pot / Alto Share)","4 - Baja Prioridad (Bajo Pot / Bajo Share)")))) -> Sin competencia directa | AX62: =IF(OR(IFERROR(AND(W62<>"",Y62<>"",Y62-W62>Resumen!$B$8),FALSE()),IFERROR(AND(X62<>"",Y62<>"",Y62-X62>Resumen!$B$8),FALSE())),MAX(IF(IFERROR(AND(W62<>"",Y62<>"",Y62-W62>Resumen!$B$8),FALSE()),Y62-W62,0),IF(IFERROR(AND(X62<>"",Y62<>"",Y62-X62>Resumen!$B$8),FALSE()),Y62-X62,0)),"") | AY62: =IF(OR(IFERROR(AND(W62<>"",Y62<>"",Y62-W62>Resumen!$B$8),FALSE()),IFERROR(AND(X62<>"",Y62<>"",Y62-X62>Resumen!$B$8),FALSE())),TRIM("Lays tiene mayor markup que "&IF(IFERROR(AND(W62<>"",Y62<>"",Y62-W62>Resumen!$B$8),FALSE()),"Quento ","")&IF(IFERROR(AND(X62<>"",Y62<>"",Y62-X62>Resumen!$B$8),FALSE()),"Julicroc ","")&"en este PDV"),"") | AZ62: =IF(COUNTIF('Plan Pehuamar - Lista'!$A$2:$A$167,A62)>0,"Sí","No") -> No | BA62: =IF(COUNTIF('Plan Combo 9+1'!$A$2:$A$226,A62)>0,"Sí","No") -> No | BB62: =IF(AH62="","No",IF(BA62="Sí",IF((AO62-AH62)>Resumen!$B$6,"Sí","No"),IF((AO62-AH62)>=Resumen!$B$132,"Sí","No"))) -> No | BC62: =IF(AND(N62="Sí",AL62="Sí",AI62=0),"Sí","No") -> No | BD62: =IF(COUNTIF('Plan 9+1 (con Pehuamar)'!$A$2:$A$227,A62)>0,"Sí","No") -> No
A63: 400876 | B63: 1 | C63: 102 | D63: Martes | E63: MASCHERONI PABLO ALBERTO | F63: Almacen/Despensa | G63: Santa Fe | H63: Conrado Pujol | I63: 0 | J63: 0 | K63: 1.5 | L63: =I63+J63 -> 0 | M63: =L63+K63 -> 1.5 | N63: =IF(I63>0,"Sí","No") -> No | O63: =IF(J63>0,"Sí","No") -> No | P63: =IF(K63>0,"Sí","No") -> Sí | Q63: =IF(OR(I63>0,J63>0),"Sí","No") -> No | W63: =IF(AND(I63>0,R63>0),(S63-R63)/R63,"") | X63: =IF(AND(J63>0,T63>0),(U63-T63)/T63,"") | Y63: =IF(AND(K63>0,V63>0),(V63-Resumen!$B$7)/Resumen!$B$7,"") | Z63: =IF(AND(K63>0,I63>0,V63>0,S63>0),V63-S63,"") | AA63: =IF(Z63<>"",Z63/S63,"") | AB63: =IF(AND(K63>0,J63>0,V63>0,U63>0),V63-U63,"") | AC63: =IF(AB63<>"",AB63/U63,"") | AD63: 0 | AE63: 0 | AF63: 0 | AG63: =AD63+AE63+AF63 -> 0 | AH63: =IF(AG63>0,AD63/AG63,"") | AI63: 0 | AJ63: 0 | AK63: 0 | AL63: =IF(OR(AJ63>0,AK63>0),"Sí","No") -> No | AO63: =IF(M63>0,K63/M63,"") -> 1 | AP63: =IF(M63>=Resumen!$B$5,"Alto","Bajo") -> Bajo | AQ63: =IF(AO63>=Resumen!$B$28,"Alto","Bajo") -> Alto | AR63: =AP63&" Potencial / "&AQ63&" Share" -> Bajo Potencial / Alto Share | AS63: =IF(Q63="Sí",IF(AO63>=Resumen!$B$29,"Alto","Bajo"),"") | AT63: =IF(AS63<>"",AP63&" Potencial / "&AS63&" Share","") | AU63: =IF(AH63="","Sin dato",IF(AH63-AO63>Resumen!$B$6,"Sobre-exhibido",IF(AO63-AH63>Resumen!$B$6,"Sub-exhibido","En línea"))) -> Sin dato | AV63: =IF(AT63="","",IF(AT63="Alto Potencial / Bajo Share",1,IF(AT63="Alto Potencial / Alto Share",2,IF(AT63="Bajo Potencial / Alto Share",3,4)))) | AW63: =IF(Q63="No","Sin competencia directa",IF(AV63=1,"1 - Foco Conquista (Alto Pot / Bajo Share)",IF(AV63=2,"2 - Foco Defensa (Alto Pot / Alto Share)",IF(AV63=3,"3 - Monitoreo (Bajo Pot / Alto Share)","4 - Baja Prioridad (Bajo Pot / Bajo Share)")))) -> Sin competencia directa | AX63: =IF(OR(IFERROR(AND(W63<>"",Y63<>"",Y63-W63>Resumen!$B$8),FALSE()),IFERROR(AND(X63<>"",Y63<>"",Y63-X63>Resumen!$B$8),FALSE())),MAX(IF(IFERROR(AND(W63<>"",Y63<>"",Y63-W63>Resumen!$B$8),FALSE()),Y63-W63,0),IF(IFERROR(AND(X63<>"",Y63<>"",Y63-X63>Resumen!$B$8),FALSE()),Y63-X63,0)),"") | AY63: =IF(OR(IFERROR(AND(W63<>"",Y63<>"",Y63-W63>Resumen!$B$8),FALSE()),IFERROR(AND(X63<>"",Y63<>"",Y63-X63>Resumen!$B$8),FALSE())),TRIM("Lays tiene mayor markup que "&IF(IFERROR(AND(W63<>"",Y63<>"",Y63-W63>Resumen!$B$8),FALSE()),"Quento ","")&IF(IFERROR(AND(X63<>"",Y63<>"",Y63-X63>Resumen!$B$8),FALSE()),"Julicroc ","")&"en este PDV"),"") | AZ63: =IF(COUNTIF('Plan Pehuamar - Lista'!$A$2:$A$167,A63)>0,"Sí","No") -> No | BA63: =IF(COUNTIF('Plan Combo 9+1'!$A$2:$A$226,A63)>0,"Sí","No") -> No | BB63: =IF(AH63="","No",IF(BA63="Sí",IF((AO63-AH63)>Resumen!$B$6,"Sí","No"),IF((AO63-AH63)>=Resumen!$B$132,"Sí","No"))) -> No | BC63: =IF(AND(N63="Sí",AL63="Sí",AI63=0),"Sí","No") -> No | BD63: =IF(COUNTIF('Plan 9+1 (con Pehuamar)'!$A$2:$A$227,A63)>0,"Sí","No") -> No
A64: 400878 | B64: 1 | C64: 102 | D64: Martes | E64: AGHEMO PABLO FEDERICO | F64: Kiosco/Maxikiosco | G64: Santa Fe | H64: Conrado Pujol | I64: 0 | J64: 0 | K64: 0.5 | L64: =I64+J64 -> 0 | M64: =L64+K64 -> 0.5 | N64: =IF(I64>0,"Sí","No") -> No | O64: =IF(J64>0,"Sí","No") -> No | P64: =IF(K64>0,"Sí","No") -> Sí | Q64: =IF(OR(I64>0,J64>0),"Sí","No") -> No | W64: =IF(AND(I64>0,R64>0),(S64-R64)/R64,"") | X64: =IF(AND(J64>0,T64>0),(U64-T64)/T64,"") | Y64: =IF(AND(K64>0,V64>0),(V64-Resumen!$B$7)/Resumen!$B$7,"") | Z64: =IF(AND(K64>0,I64>0,V64>0,S64>0),V64-S64,"") | AA64: =IF(Z64<>"",Z64/S64,"") | AB64: =IF(AND(K64>0,J64>0,V64>0,U64>0),V64-U64,"") | AC64: =IF(AB64<>"",AB64/U64,"") | AD64: 0 | AE64: 0 | AF64: 0 | AG64: =AD64+AE64+AF64 -> 0 | AH64: =IF(AG64>0,AD64/AG64,"") | AI64: 0 | AJ64: 0 | AK64: 0 | AL64: =IF(OR(AJ64>0,AK64>0),"Sí","No") -> No | AO64: =IF(M64>0,K64/M64,"") -> 1 | AP64: =IF(M64>=Resumen!$B$5,"Alto","Bajo") -> Bajo | AQ64: =IF(AO64>=Resumen!$B$28,"Alto","Bajo") -> Alto | AR64: =AP64&" Potencial / "&AQ64&" Share" -> Bajo Potencial / Alto Share | AS64: =IF(Q64="Sí",IF(AO64>=Resumen!$B$29,"Alto","Bajo"),"") | AT64: =IF(AS64<>"",AP64&" Potencial / "&AS64&" Share","") | AU64: =IF(AH64="","Sin dato",IF(AH64-AO64>Resumen!$B$6,"Sobre-exhibido",IF(AO64-AH64>Resumen!$B$6,"Sub-exhibido","En línea"))) -> Sin dato | AV64: =IF(AT64="","",IF(AT64="Alto Potencial / Bajo Share",1,IF(AT64="Alto Potencial / Alto Share",2,IF(AT64="Bajo Potencial / Alto Share",3,4)))) | AW64: =IF(Q64="No","Sin competencia directa",IF(AV64=1,"1 - Foco Conquista (Alto Pot / Bajo Share)",IF(AV64=2,"2 - Foco Defensa (Alto Pot / Alto Share)",IF(AV64=3,"3 - Monitoreo (Bajo Pot / Alto Share)","4 - Baja Prioridad (Bajo Pot / Bajo Share)")))) -> Sin competencia directa | AX64: =IF(OR(IFERROR(AND(W64<>"",Y64<>"",Y64-W64>Resumen!$B$8),FALSE()),IFERROR(AND(X64<>"",Y64<>"",Y64-X64>Resumen!$B$8),FALSE())),MAX(IF(IFERROR(AND(W64<>"",Y64<>"",Y64-W64>Resumen!$B$8),FALSE()),Y64-W64,0),IF(IFERROR(AND(X64<>"",Y64<>"",Y64-X64>Resumen!$B$8),FALSE()),Y64-X64,0)),"") | AY64: =IF(OR(IFERROR(AND(W64<>"",Y64<>"",Y64-W64>Resumen!$B$8),FALSE()),IFERROR(AND(X64<>"",Y64<>"",Y64-X64>Resumen!$B$8),FALSE())),TRIM("Lays tiene mayor markup que "&IF(IFERROR(AND(W64<>"",Y64<>"",Y64-W64>Resumen!$B$8),FALSE()),"Quento ","")&IF(IFERROR(AND(X64<>"",Y64<>"",Y64-X64>Resumen!$B$8),FALSE()),"Julicroc ","")&"en este PDV"),"") | AZ64: =IF(COUNTIF('Plan Pehuamar - Lista'!$A$2:$A$167,A64)>0,"Sí","No") -> No | BA64: =IF(COUNTIF('Plan Combo 9+1'!$A$2:$A$226,A64)>0,"Sí","No") -> No | BB64: =IF(AH64="","No",IF(BA64="Sí",IF((AO64-AH64)>Resumen!$B$6,"Sí","No"),IF((AO64-AH64)>=Resumen!$B$132,"Sí","No"))) -> No | BC64: =IF(AND(N64="Sí",AL64="Sí",AI64=0),"Sí","No") -> No | BD64: =IF(COUNTIF('Plan 9+1 (con Pehuamar)'!$A$2:$A$227,A64)>0,"Sí","No") -> No
A65: 400886 | B65: 1 | C65: 102 | D65: Martes | E65: PEREYRA LEONARDO MARTIN | F65: Centros de entrenamiento/Espacios Deportivos | G65: Santa Fe | H65: Conrado Pujol | I65: 40 | J65: 0 | K65: 40 | L65: =I65+J65 -> 40 | M65: =L65+K65 -> 80 | N65: =IF(I65>0,"Sí","No") -> Sí | O65: =IF(J65>0,"Sí","No") -> No | P65: =IF(K65>0,"Sí","No") -> Sí | Q65: =IF(OR(I65>0,J65>0),"Sí","No") -> Sí | R65: 1800 | S65: 2900 | V65: 3500 | W65: =IF(AND(I65>0,R65>0),(S65-R65)/R65,"") -> 0.61111111 | X65: =IF(AND(J65>0,T65>0),(U65-T65)/T65,"") | Y65: =IF(AND(K65>0,V65>0),(V65-Resumen!$B$7)/Resumen!$B$7,"") -> 0.4 | Z65: =IF(AND(K65>0,I65>0,V65>0,S65>0),V65-S65,"") -> 600 | AA65: =IF(Z65<>"",Z65/S65,"") -> 0.20689655 | AB65: =IF(AND(K65>0,J65>0,V65>0,U65>0),V65-U65,"") | AC65: =IF(AB65<>"",AB65/U65,"") | AD65: 4 | AE65: 4 | AF65: 0 | AG65: =AD65+AE65+AF65 -> 8 | AH65: =IF(AG65>0,AD65/AG65,"") -> 0.5 | AI65: 0 | AJ65: 0 | AK65: 0 | AL65: =IF(OR(AJ65>0,AK65>0),"Sí","No") -> No | AM65: Contado | AO65: =IF(M65>0,K65/M65,"") -> 0.5 | AP65: =IF(M65>=Resumen!$B$5,"Alto","Bajo") -> Alto | AQ65: =IF(AO65>=Resumen!$B$28,"Alto","Bajo") -> Alto | AR65: =AP65&" Potencial / "&AQ65&" Share" -> Alto Potencial / Alto Share | AS65: =IF(Q65="Sí",IF(AO65>=Resumen!$B$29,"Alto","Bajo"),"") -> Alto | AT65: =IF(AS65<>"",AP65&" Potencial / "&AS65&" Share","") -> Alto Potencial / Alto Share | AU65: =IF(AH65="","Sin dato",IF(AH65-AO65>Resumen!$B$6,"Sobre-exhibido",IF(AO65-AH65>Resumen!$B$6,"Sub-exhibido","En línea"))) -> En línea | AV65: =IF(AT65="","",IF(AT65="Alto Potencial / Bajo Share",1,IF(AT65="Alto Potencial / Alto Share",2,IF(AT65="Bajo Potencial / Alto Share",3,4)))) -> 2 | AW65: =IF(Q65="No","Sin competencia directa",IF(AV65=1,"1 - Foco Conquista (Alto Pot / Bajo Share)",IF(AV65=2,"2 - Foco Defensa (Alto Pot / Alto Share)",IF(AV65=3,"3 - Monitoreo (Bajo Pot / Alto Share)","4 - Baja Prioridad (Bajo Pot / Bajo Share)")))) -> 2 - Foco Defensa (Alto Pot / Alto Share) | AX65: =IF(OR(IFERROR(AND(W65<>"",Y65<>"",Y65-W65>Resumen!$B$8),FALSE()),IFERROR(AND(X65<>"",Y65<>"",Y65-X65>Resumen!$B$8),FALSE())),MAX(IF(IFERROR(AND(W65<>"",Y65<>"",Y65-W65>Resumen!$B$8),FALSE()),Y65-W65,0),IF(IFERROR(AND(X65<>"",Y65<>"",Y65-X65>Resumen!$B$8),FALSE()),Y65-X65,0)),"") | AY65: =IF(OR(IFERROR(AND(W65<>"",Y65<>"",Y65-W65>Resumen!$B$8),FALSE()),IFERROR(AND(X65<>"",Y65<>"",Y65-X65>Resumen!$B$8),FALSE())),TRIM("Lays tiene mayor markup que "&IF(IFERROR(AND(W65<>"",Y65<>"",Y65-W65>Resumen!$B$8),FALSE()),"Quento ","")&IF(IFERROR(AND(X65<>"",Y65<>"",Y65-X65>Resumen!$B$8),FALSE()),"Julicroc ","")&"en este PDV"),"") | AZ65: =IF(COUNTIF('Plan Pehuamar - Lista'!$A$2:$A$167,A65)>0,"Sí","No") -> No | BA65: =IF(COUNTIF('Plan Combo 9+1'!$A$2:$A$226,A65)>0,"Sí","No") -> No | BB65: =IF(AH65="","No",IF(BA65="Sí",IF((AO65-AH65)>Resumen!$B$6,"Sí","No"),IF((AO65-AH65)>=Resumen!$B$132,"Sí","No"))) -> No | BC65: =IF(AND(N65="Sí",AL65="Sí",AI65=0),"Sí","No") -> No | BD65: =IF(COUNTIF('Plan 9+1 (con Pehuamar)'!$A$2:$A$227,A65)>0,"Sí","No") -> No
